Workbook

Sheet LÉEME
A1: Campañas de email L'Oréal · agosto a octubre 2025
A2: Caso DDX · María Fernanda Girón Rojas
B4: QUÉ ES ESTE ARCHIVO
B5: El análisis de 576 campañas de email enviadas entre agosto y octubre de 2025, con el detalle de qué funcionó, qué no, y qué datos no se pudieron usar.
B6: Cómo leerlo: empiece por la hoja TABLERO, que resume todo en cuatro gráficos. H0 DATOS muestra qué filas se usan y por qué se excluye el 15 %. HALLAZGOS tiene la lista de todas las hipótesis probadas, y cada una tiene su tabla y su gráfica en las hojas H1 CALENDARIO, H2 CAMPAÑA, H3 ASUNTO y H4 TEMÁTICA HOT SALE. RANKING ASUNTOS es el listado completo. DATOS LIMPIOS y FILAS EXCLUIDAS están para que cualquiera pueda auditar las cifras.
B8: LAS MÉTRICAS, EXPLICADAS
B9: Para los ejemplos: imagine que enviamos 1.000 correos, 300 personas lo abren y de esas 90 hacen clic en algún enlace.
B10: Métrica | C10: Qué responde | D10: Cómo se calcula | E10: Ejemplo | F10: Para qué sirve
B11: Tasa de Apertura | C11: De todos los que recibieron el correo, ¿cuántos lo abrieron? | D11: Aperturas ÷ Envíos | E11: 300 ÷ 1.000 = 30 % | F11: Mide si el ASUNTO fue lo bastante atractivo para ganarse el clic en la bandeja.
B12: CTR (Tasa de Clics) | C12: De todos los que recibieron el correo, ¿cuántos hicieron clic? | D12: Clics ÷ Envíos | E12: 90 ÷ 1.000 = 9 % | F12: Mide el resultado de toda la cadena: asunto más contenido, de punta a punta.
B13: CTOR (Clics por Apertura) | C13: De los que ABRIERON, ¿cuántos hicieron clic? | D13: Clics ÷ Aperturas | E13: 90 ÷ 300 = 30 % | F13: Aísla el contenido: una vez abierto el correo, ¿convenció lo de adentro?
B14: Tasa de Conversión | C14: De los que recibieron, ¿cuántos terminaron comprando? | D14: Viene en el archivo original | E14: — | F14: Es la métrica de negocio. Ojo: en estos datos no se relaciona con nada (ver TABLERO).
B15: Tasa de Desuscripción | C15: ¿Cuántos pidieron no recibir más correos? | D15: Viene en el archivo original | E15: — | F15: El costo oculto de enviar de más. Sube cuando cansamos a la base.
B16: Ingreso por mil envíos | C16: Cuánto dinero deja cada 1.000 correos enviados. | D16: Ingresos ÷ Envíos × 1.000 | E16: — | F16: Permite comparar campañas grandes con pequeñas en la misma vara.
B18: QUÉ DATOS SE DEJARON FUERA, Y POR QUÉ
B19: De las 576 filas del archivo original se excluyeron 87 (15.1 %). Ninguna se borró en silencio: la hoja FILAS EXCLUIDAS tiene cada una con su motivo y su número de fila original.
B20: Motivo | C20: Filas que rompen la regla (crudo) | D20: Filas excluidas por esta razón | E20: Por qué se excluye
B21: Imposible: más clics que aperturas | C21: 75 | D21: 72 | E21: No puede hacer clic quien no abrió. Implicaría CTOR de hasta 917 %.
B22: Fecha fuera de la ventana ago-oct 2025 | C22: 7 | D22: 7 | E22: Hay registros de 1990, 2022 y 2026. El caso pide los últimos tres meses.
B23: Imposible: más aperturas que envíos | C23: 5 | D23: 5 | E23: No puede abrir más gente de la que recibió el correo.
B24: Campos vacíos en métricas de cálculo | C24: 3 | D24: 3 | E24: Sin envíos o sin aperturas no se puede calcular ninguna tasa.
B25: Las dos columnas de número no coinciden en una fila, y es correcto: hay 3 registros que rompen DOS reglas a la vez. En la columna de exclusiones cada fila se cuenta una sola vez, bajo la primera razón que aplica. Por eso 75 filas tienen más clics que aperturas pero solo 72 se excluyen por eso: las otras 3 ya habían caído por fecha o por aperturas imposibles.
B26: Quedan 489 campañas para analizar.

Sheet TABLERO PRO
A1: Email marketing L'Oréal · agosto a octubre de 2025
A2: 489 campañas usables de 576. Todo lo que se ve son fórmulas que leen DATOS LIMPIOS: si se corrige un dato crudo, el tablero se mueve con él.
A4: CAMPAÑAS USABLES | D4: APERTURA PONDERADA | G4: LO EXPLICA EL ASUNTO | J4: COSTO DE ABRIR CON ETIQUETA | M4: …Y EN CLICS | P4: INGRESO POR CAMPAÑA CORREGIDA
A5: =COUNT('DATOS LIMPIOS'!$M$5:$M$493) -> 489 | D5: =SUM('DATOS LIMPIOS'!$H$5:$H$493)/SUM('DATOS LIMPIOS'!$G$5:$G$493)*100 -> 28.944019 | G5: =(SUMPRODUCT(('DATOS LIMPIOS'!$M$5:$M$493-AVERAGE('DATOS LIMPIOS'!$M$5:$M$493))^2)-SUMPRODUCT(('DATOS LIMPIOS'!$M$5:$M$493-'DATOS LIMPIOS'!$Q$5:$Q$493)^2))/SUMPRODUCT(('DATOS LIMPIOS'!$M$5:$M$493-AVERAGE('DATOS LIMPIOS'!$M$5:$M$493))^2)*100 -> 47.410372 | J5: =(AVERAGEIF('DATOS LIMPIOS'!$AH$5:$AH$493,"No",'DATOS LIMPIOS'!$M$5:$M$493)-AVERAGEIF('DATOS LIMPIOS'!$AH$5:$AH$493,"Sí",'DATOS LIMPIOS'!$M$5:$M$493)) -> 13.255766 | M5: =(AVERAGEIF('DATOS LIMPIOS'!$AH$5:$AH$493,"No",'DATOS LIMPIOS'!$N$5:$N$493)-AVERAGEIF('DATOS LIMPIOS'!$AH$5:$AH$493,"Sí",'DATOS LIMPIOS'!$N$5:$N$493)) -> 1.8958056 | P5: ='PROYECCIÓN COP'!$D$8*(AVERAGEIF('DATOS LIMPIOS'!$AH$5:$AH$493,"No",'DATOS LIMPIOS'!$N$5:$N$493)-AVERAGEIF('DATOS LIMPIOS'!$AH$5:$AH$493,"Sí",'DATOS LIMPIOS'!$N$5:$N$493))/100*'PROYECCIÓN COP'!$D$15/100*'PROYECCIÓN COP'!$D$16/1000000 -> 16.016744
A6: de 576; 87 con datos imposibles | D6: sobre 120,1 M de envíos | G6: el calendario no llega al 2 % | J6: de apertura · 43 asuntos contra 23 | M6: de CTR · el intervalo no toca el cero | P6: COP · rango +7,4 a +24,7 M
A8: DÓNDE ESTÁ LA PALANCA
A24: LO QUE NO MUEVE EL RESULTADO | J24: QUÉ VALE CORREGIRLO
A25: Hipótesis | E25: % que explica | G25: p
A26: El tipo de campaña | E26: =(SUMPRODUCT(('DATOS LIMPIOS'!$M$5:$M$493-AVERAGE('DATOS LIMPIOS'!$M$5:$M$493))^2)-SUMPRODUCT(('DATOS LIMPIOS'!$M$5:$M$493-'DATOS LIMPIOS'!$R$5:$R$493)^2))/SUMPRODUCT(('DATOS LIMPIOS'!$M$5:$M$493-AVERAGE('DATOS LIMPIOS'!$M$5:$M$493))^2)*100 -> 1.3828802 | G26: 0,212 | J26: Aperturas ganadas por campaña | M26: ='PROYECCIÓN COP'!$D$8*(AVERAGEIF('DATOS LIMPIOS'!$AH$5:$AH$493,"No",'DATOS LIMPIOS'!$M$5:$M$493)-AVERAGEIF('DATOS LIMPIOS'!$AH$5:$AH$493,"Sí",'DATOS LIMPIOS'!$M$5:$M$493))/100 -> 31108.764 | O26: medido; el intervalo nunca toca el cero
A27: La hora de envío | E27: ='H3 ASUNTO'!$B$12 -> 1.0467798 | G27: 0,750 | J27: Clics ganados por campaña | M27: ='PROYECCIÓN COP'!$D$8*(AVERAGEIF('DATOS LIMPIOS'!$AH$5:$AH$493,"No",'DATOS LIMPIOS'!$N$5:$N$493)-AVERAGEIF('DATOS LIMPIOS'!$AH$5:$AH$493,"Sí",'DATOS LIMPIOS'!$N$5:$N$493))/100 -> 4449.0955 | O27: medido; el intervalo tampoco lo toca
A28: El día de la semana | E28: ='H3 ASUNTO'!$B$13 -> 0.52913858 | G28: 0,860 | J28: Ingreso por campaña corregida | M28: ='PROYECCIÓN COP'!$D$8*(AVERAGEIF('DATOS LIMPIOS'!$AH$5:$AH$493,"No",'DATOS LIMPIOS'!$N$5:$N$493)-AVERAGEIF('DATOS LIMPIOS'!$AH$5:$AH$493,"Sí",'DATOS LIMPIOS'!$N$5:$N$493))/100*'PROYECCIÓN COP'!$D$15/100*'PROYECCIÓN COP'!$D$16/1000000 -> 16.016744 | O28: conversión y ticket son supuestos de marca
A29: El mes | E29: ='H3 ASUNTO'!$B$14 -> 0.09407893 | G29: 0,823 | J29: Al año, al ritmo observado | M29: ='PROYECCIÓN COP'!$D$17*COUNTIF('DATOS LIMPIOS'!$AH$5:$AH$493,"Sí")/COUNT('DATOS LIMPIOS'!$M$5:$M$493)*'PROYECCIÓN COP'!$D$8*(AVERAGEIF('DATOS LIMPIOS'!$AH$5:$AH$493,"No",'DATOS LIMPIOS'!$N$5:$N$493)-AVERAGEIF('DATOS LIMPIOS'!$AH$5:$AH$493,"Sí",'DATOS LIMPIOS'!$N$5:$N$493))/100*'PROYECCIÓN COP'!$D$15/100*'PROYECCIÓN COP'!$D$16/1000000 -> 106.90931 | O29: 27,8 % de las campañas abre con etiqueta
A30: El momento del mes (quincena) | E30: ='H3 ASUNTO'!$B$15 -> 0.17975665 | G30: 0,024 · ver nota
A31: Ninguna diferencia supera lo que mueve el azar (Kruskal-Wallis, p > 0,05). Los cinco factores juntos no explican el 3 % de la apertura. La quincena da p = 0,024 en CTR, pero se corrieron 16 pruebas (el umbral corregido es 0,003), se cae al mover la definición un día, y va al revés: el CTR es MENOR en quincena. Detalle en HALLAZGOS. | J31: Las aperturas y los clics están MEDIDOS: las dos brechas salen de comparar 353 campañas contra 136 y sus intervalos de confianza no tocan el cero. Lo que es supuesto es la conversión del clic a compra (2 %) y el ticket (180.000 COP): esas dos celdas viven en PROYECCIÓN COP y marca debe reemplazarlas por las reales.
A33: LA DECISIÓN DE MAÑANA
A34: Asuntos para RETIRAR, ya identificados | F34: =COUNTIF('BIBLIOTECA ASUNTOS'!$H$10:$H$31,"RETIRAR") -> 10 | H34: Asunto propuesto para Hot Sale | K34: Hasta 40% en tus favoritos - Hot Sale L’Oréal Paris
A35: Asuntos para REPETIR sin miedo | F35: =COUNTIF('BIBLIOTECA ASUNTOS'!$H$10:$H$31,"REPETIR") -> 12 | H35: Y el A/B que lo confirma | K35: 10 % de la base por versión · la cifra al principio contra la cifra al final
A37: EL LÍMITE, DICHO ANTES DE QUE LO PREGUNTEN. Lo que está medido es que abrir con una etiqueta cuesta apertura y clics: 43 asuntos contra 23, los tres meses, y la brecha resiste quitar cualquiera de los 66 asuntos. Lo que NO está medido es que poner una cifra en el asunto suba la apertura por sí sola: en todo el archivo hay un único asunto con cifra, así que no se puede separar «lleva número» de «es esa frase». Por eso la cifra va al A/B y no al plan. Hoja PRUEBA DE ROBUSTEZ.
A39: Dónde seguir: PRUEBA DE ROBUSTEZ para las pruebas duras · HALLAZGOS y H1 a H4 para cada hipótesis · DESCUENTO ÓPTIMO y PROYECCIÓN COP para la plata · BIBLIOTECA ASUNTOS para el asunto del próximo envío · FÓRMULAS Y VERIFICACIÓN para recalcular cada cifra.
A42: DATOS QUE ALIMENTAN LOS GRÁFICOS · fuera del área de impresión
A43: Estilo de apertura | B43: Apertura
A44: Dice qué hay dentro | B44: =AVERAGEIF('DATOS LIMPIOS'!$AH$5:$AH$493,"No",'DATOS LIMPIOS'!$M$5:$M$493) -> 32.873289
A45: Abre con etiqueta | B45: =AVERAGEIF('DATOS LIMPIOS'!$AH$5:$AH$493,"Sí",'DATOS LIMPIOS'!$M$5:$M$493) -> 19.617523
A47: Mes | B47: Dice qué hay dentro | C47: Abre con etiqueta
A48: Agosto | B48: =AVERAGEIFS('DATOS LIMPIOS'!$M$5:$M$493,'DATOS LIMPIOS'!$T$5:$T$493,"Agosto",'DATOS LIMPIOS'!$AH$5:$AH$493,"No") -> 32.555382 | C48: =AVERAGEIFS('DATOS LIMPIOS'!$M$5:$M$493,'DATOS LIMPIOS'!$T$5:$T$493,"Agosto",'DATOS LIMPIOS'!$AH$5:$AH$493,"Sí") -> 22.687529
A49: Septiembre | B49: =AVERAGEIFS('DATOS LIMPIOS'!$M$5:$M$493,'DATOS LIMPIOS'!$T$5:$T$493,"Septiembre",'DATOS LIMPIOS'!$AH$5:$AH$493,"No") -> 32.87815 | C49: =AVERAGEIFS('DATOS LIMPIOS'!$M$5:$M$493,'DATOS LIMPIOS'!$T$5:$T$493,"Septiembre",'DATOS LIMPIOS'!$AH$5:$AH$493,"Sí") -> 16.127339
A50: Octubre | B50: =AVERAGEIFS('DATOS LIMPIOS'!$M$5:$M$493,'DATOS LIMPIOS'!$T$5:$T$493,"Octubre",'DATOS LIMPIOS'!$AH$5:$AH$493,"No") -> 33.164494 | C50: =AVERAGEIFS('DATOS LIMPIOS'!$M$5:$M$493,'DATOS LIMPIOS'!$T$5:$T$493,"Octubre",'DATOS LIMPIOS'!$AH$5:$AH$493,"Sí") -> 19.532131
A52: Factor | B52: % explicado
A53: El asunto | B53: =(SUMPRODUCT(('DATOS LIMPIOS'!$M$5:$M$493-AVERAGE('DATOS LIMPIOS'!$M$5:$M$493))^2)-SUMPRODUCT(('DATOS LIMPIOS'!$M$5:$M$493-'DATOS LIMPIOS'!$Q$5:$Q$493)^2))/SUMPRODUCT(('DATOS LIMPIOS'!$M$5:$M$493-AVERAGE('DATOS LIMPIOS'!$M$5:$M$493))^2)*100 -> 47.410372
A54: El tipo de campaña | B54: =(SUMPRODUCT(('DATOS LIMPIOS'!$M$5:$M$493-AVERAGE('DATOS LIMPIOS'!$M$5:$M$493))^2)-SUMPRODUCT(('DATOS LIMPIOS'!$M$5:$M$493-'DATOS LIMPIOS'!$R$5:$R$493)^2))/SUMPRODUCT(('DATOS LIMPIOS'!$M$5:$M$493-AVERAGE('DATOS LIMPIOS'!$M$5:$M$493))^2)*100 -> 1.3828802
A55: La hora | B55: ='H3 ASUNTO'!$B$12 -> 1.0467798
A56: El día | B56: ='H3 ASUNTO'!$B$13 -> 0.52913858
A57: El mes | B57: ='H3 ASUNTO'!$B$14 -> 0.09407893

Sheet PRUEBA DE ROBUSTEZ
A1: Prueba de robustez · qué aguanta y qué no
A2: Un hallazgo que solo existe en el promedio general no sirve para decidir. Aquí se le hacen cuatro pruebas distintas y se dice dónde se rompe.
A4: EL HALLAZGO. Un asunto que abre con una etiqueta genérica («Actualización de…», «Presentamos:», «Oportunidades de…») dice qué TIPO de correo es, no qué hay adentro. Los que dicen qué hay adentro abren 13,3 puntos más. La lista de 15 etiquetas está escrita en la fórmula de la columna AH de DATOS LIMPIOS y se puede auditar palabra por palabra.
A6: A · LA MEDICIÓN
B7: Dice qué hay dentro | C7: Abre con etiqueta | D7: Brecha o total | E7: Unidad
A8: Campañas | B8: =COUNTIF('DATOS LIMPIOS'!$AH$5:$AH$493,"No") -> 353 | C8: =COUNTIF('DATOS LIMPIOS'!$AH$5:$AH$493,"Sí") -> 136 | D8: =B8+C8 -> 489 | E8: campañas en total
A9: Asuntos distintos | B9: =SUMPRODUCT(('DATOS LIMPIOS'!$AH$5:$AH$493="No")/COUNTIF('DATOS LIMPIOS'!$E$5:$E$493,'DATOS LIMPIOS'!$E$5:$E$493)) -> 43 | C9: =SUMPRODUCT(('DATOS LIMPIOS'!$AH$5:$AH$493="Sí")/COUNTIF('DATOS LIMPIOS'!$E$5:$E$493,'DATOS LIMPIOS'!$E$5:$E$493)) -> 23 | D9: =B9+C9 -> 66 | E9: asuntos en total
A10: Apertura media | B10: =AVERAGEIF('DATOS LIMPIOS'!$AH$5:$AH$493,"No",'DATOS LIMPIOS'!$M$5:$M$493) -> 32.873289 | C10: =AVERAGEIF('DATOS LIMPIOS'!$AH$5:$AH$493,"Sí",'DATOS LIMPIOS'!$M$5:$M$493) -> 19.617523 | D10: =B10-C10 -> 13.255766 | E10: puntos de brecha
A11: CTR medio | B11: =AVERAGEIF('DATOS LIMPIOS'!$AH$5:$AH$493,"No",'DATOS LIMPIOS'!$N$5:$N$493) -> 10.314437 | C11: =AVERAGEIF('DATOS LIMPIOS'!$AH$5:$AH$493,"Sí",'DATOS LIMPIOS'!$N$5:$N$493) -> 8.4186314 | D11: =B11-C11 -> 1.8958056 | E11: puntos de brecha
A13: B · ¿PUEDE SER AZAR? T DE WELCH, CALCULADA AQUÍ MISMO
A14: Paso del cálculo | B14: Apertura | C14: CTR
A15: Varianza · dice qué hay dentro | B15: =SUMPRODUCT(('DATOS LIMPIOS'!$AH$5:$AH$493="No")*('DATOS LIMPIOS'!$M$5:$M$493-$B$10)^2)/(COUNTIF('DATOS LIMPIOS'!$AH$5:$AH$493,"No")-1) -> 128.23122 | C15: =SUMPRODUCT(('DATOS LIMPIOS'!$AH$5:$AH$493="No")*('DATOS LIMPIOS'!$N$5:$N$493-$B$11)^2)/(COUNTIF('DATOS LIMPIOS'!$AH$5:$AH$493,"No")-1) -> 29.389996 | D15: SUMPRODUCT con máscara 0/1, dividido por n−1
A16: Varianza · abre con etiqueta | B16: =SUMPRODUCT(('DATOS LIMPIOS'!$AH$5:$AH$493="Sí")*('DATOS LIMPIOS'!$M$5:$M$493-$C$10)^2)/(COUNTIF('DATOS LIMPIOS'!$AH$5:$AH$493,"Sí")-1) -> 88.540649 | C16: =SUMPRODUCT(('DATOS LIMPIOS'!$AH$5:$AH$493="Sí")*('DATOS LIMPIOS'!$N$5:$N$493-$C$11)^2)/(COUNTIF('DATOS LIMPIOS'!$AH$5:$AH$493,"Sí")-1) -> 26.158632
A17: Error estándar de la brecha | B17: =SQRT(B15/$B$8+B16/$C$8) -> 1.0071224 | C17: =SQRT(C15/$B$8+C16/$C$8) -> 0.52497682 | D17: √(v₁/n₁ + v₂/n₂), sin suponer varianzas iguales
A18: t | B18: =$D$10/B17 -> 13.162021 | C18: =$D$11/C17 -> 3.6112177 | D18: la brecha dividida por su error estándar
A19: Grados de libertad (Welch-Satterthwaite) | B19: =(B15/$B$8+B16/$C$8)^2/((B15/$B$8)^2/($B$8-1)+(B16/$C$8)^2/($C$8-1)) -> 292.7305 | C19: =(C15/$B$8+C16/$C$8)^2/((C15/$B$8)^2/($B$8-1)+(C16/$C$8)^2/($C$8-1)) -> 258.58533
A20: p a dos colas | B20: =TDIST(ABS(B18),B19,2) -> 2.2189444e-31 | C20: =TDIST(ABS(C18),C19,2) -> 0.00036614835 | D20: por debajo de 0,05 el hallazgo no es azar
A22: Las dos p salen muy por debajo de 0,001. Con 353 campañas contra 136, una brecha de este tamaño no la produce el azar. Y a diferencia de lo que pasaba con la cifra en el asunto, aquí el CTR también pasa: la plata deja de depender de un supuesto.
A24: C · ¿SE SOSTIENE MES A MES, O VIVE EN EL PROMEDIO?
A25: Mes | B25: Dice qué hay dentro | C25: Abre con etiqueta | D25: Brecha | E25: Campañas del mes
A26: Agosto | B26: =AVERAGEIFS('DATOS LIMPIOS'!$M$5:$M$493,'DATOS LIMPIOS'!$T$5:$T$493,"Agosto",'DATOS LIMPIOS'!$AH$5:$AH$493,"No") -> 32.555382 | C26: =AVERAGEIFS('DATOS LIMPIOS'!$M$5:$M$493,'DATOS LIMPIOS'!$T$5:$T$493,"Agosto",'DATOS LIMPIOS'!$AH$5:$AH$493,"Sí") -> 22.687529 | D26: =B26-C26 -> 9.8678524 | E26: =COUNTIF('DATOS LIMPIOS'!$T$5:$T$493,"Agosto") -> 159
A27: Septiembre | B27: =AVERAGEIFS('DATOS LIMPIOS'!$M$5:$M$493,'DATOS LIMPIOS'!$T$5:$T$493,"Septiembre",'DATOS LIMPIOS'!$AH$5:$AH$493,"No") -> 32.87815 | C27: =AVERAGEIFS('DATOS LIMPIOS'!$M$5:$M$493,'DATOS LIMPIOS'!$T$5:$T$493,"Septiembre",'DATOS LIMPIOS'!$AH$5:$AH$493,"Sí") -> 16.127339 | D27: =B27-C27 -> 16.75081 | E27: =COUNTIF('DATOS LIMPIOS'!$T$5:$T$493,"Septiembre") -> 167
A28: Octubre | B28: =AVERAGEIFS('DATOS LIMPIOS'!$M$5:$M$493,'DATOS LIMPIOS'!$T$5:$T$493,"Octubre",'DATOS LIMPIOS'!$AH$5:$AH$493,"No") -> 33.164494 | C28: =AVERAGEIFS('DATOS LIMPIOS'!$M$5:$M$493,'DATOS LIMPIOS'!$T$5:$T$493,"Octubre",'DATOS LIMPIOS'!$AH$5:$AH$493,"Sí") -> 19.532131 | D28: =B28-C28 -> 13.632363 | E28: =COUNTIF('DATOS LIMPIOS'!$T$5:$T$493,"Octubre") -> 163
A30: Tres meses independientes, brecha positiva en los tres. El mes más flojo (agosto) sigue dando casi 10 puntos. No es un mes raro arrastrando el promedio.
A32: D · PRUEBAS QUE NO CABEN EN UNA CELDA
A33: Prueba | B33: Apertura | C33: CTR | D33: Qué la descartaría
A34: Brecha medida | B34: +13,26 pts | C34: +1,90 pts | D34: —
A35: Intervalo de confianza al 95 % · bootstrap de 20.000 remuestreos | B35: +11,25 a +15,22 | C35: +0,88 a +2,90 | D35: Que el intervalo tocara el cero. No lo toca.
A36: Probabilidad de que la brecha sea positiva | B36: 100,0 % | C36: 100,0 % | D36: Que bajara del 95 %.
A37: Deja uno fuera: la brecha quitando cada uno de los 66 asuntos, uno por uno | B37: nunca baja de +12,70 | C37: nunca baja de +1,69 | D37: Que un solo asunto sostuviera todo. Ninguno lo hace.
A38: Quitando el único asunto que lleva cifra | B38: +12,70 pts | C38: +1,88 pts | D38: Que este hallazgo fuera el de la cifra disfrazado. No lo es.
A39: Mann-Whitney contando cada asunto una vez, no cada campaña | B39: p < 0,00001 | C39: — | D39: Que la brecha viniera de repetir mucho unos pocos asuntos.
A41: Estas seis filas se calculan en fuente/robustez-etiqueta.py con semilla 20251022, para que den lo mismo cada vez que se corran. Las secciones A, B y C de esta hoja se recalculan solas dentro del Excel, y ese mismo script las vuelve a calcular aparte: las dos vías dan la misma cifra.
A43: E · DÓNDE NO LLEGA EL DATO
A44: EL ASUNTO CON CIFRA. En las tablas por estilo, «Con cifra concreta» abre 41,6 % contra 29,2 % del promedio, y es tentador titular con eso. No se puede, por una razón que hay que decir antes de que la pregunten: son 21 campañas pero UN SOLO asunto, el único del archivo que lleva un número. Con un solo caso no se puede separar «lleva cifra» de «es esa frase», que además dice «Flash Sale», «Ahorra YA» y «tus favoritos». Y el segundo mejor asunto, sin ninguna cifra, abre 40,7 %: nueve décimas de punto menos.
A46: LO MISMO AL REVÉS. «Pregunta abierta» es el estilo que peor abre (15,9 %) y también es un solo asunto. Tampoco se reporta como hallazgo.
A48: QUÉ SE HACE CON ESO. La cifra pasa de recomendación a hipótesis, y la hipótesis se resuelve con el A/B que ya está propuesto: la misma campaña, 10 % de la base por versión, una con la cifra al principio y otra con la cifra al final. Cuesta cero y en una campaña queda medido. El plan que se ejecuta sin esperar nada es el otro: ningún asunto vuelve a abrir con etiqueta.

Sheet TABLERO
A1: Tablero
A2: Los números grandes son el embudo. Los gráficos responden, en orden: ¿qué impulsa los resultados? ¿qué no? ¿y los ingresos?
A4: Campañas analizadas | C4: Emails enviados | E4: Tasa de apertura | G4: CTR | I4: CTOR | K4: Brecha mejor/peor asunto
A5: 489 | C5: 120096662 | E5: 28.944019 | G5: 9.7276675 | I5: 33.608558 | K5: 3.8810091
A6: de 576 en el archivo | C6: en los tres meses | E6: promedio ponderado | G6: clics sobre envíos | I6: clics sobre aperturas | K6: la palanca real
A54: CÓMO LEER ESTOS CUATRO GRÁFICOS
A55: Arriba a la izquierda | C55: Cada barra es un asunto. El mejor logra 41,6 % de apertura y el peor 10,7 %: casi cuatro veces de diferencia con la misma base de datos y la misma marca.
A56: Arriba a la derecha | C56: Mide cuánto explica cada factor. El asunto explica el 47 % de la variación. El tipo de campaña, la hora, el día y el mes explican entre 0 y 1,4 %, que es decir nada.
A57: Abajo a la izquierda | C57: Agosto, septiembre y octubre son prácticamente idénticos. No hay estacionalidad que aprovechar en esta ventana.
A58: Abajo a la derecha | C58: Si los ingresos dependieran de los clics, esta nube sería una diagonal. Es una mancha. Eso apunta a un problema de medición, no a un hallazgo de negocio.

Sheet HALLAZGOS
A1: Hallazgos · qué se probó y qué resultó
A2: Todas las hipótesis que se probaron, en una lista. Cada una tiene su tabla y su gráfica en las hojas H1 a H4. "p" es la probabilidad de ver la diferencia por azar: por debajo de 0,05 se considera real.
A4: # | B4: Hipótesis | C4: Métrica | D4: p | E4: ¿Cambia el resultado? | F4: Dónde ver la gráfica
A5: H1 | B5: ¿El mes cambia cuántas personas abren? | C5: Apertura | D5: 0,823 | E5: No | F5: =HYPERLINK("#'H1 CALENDARIO'!A5","H1 CALENDARIO") -> H1 CALENDARIO
A6: H2 | B6: ¿El día de la semana cambia cuántas personas abren? | C6: Apertura | D6: 0,860 | E6: No | F6: =HYPERLINK("#'H1 CALENDARIO'!A29","H1 CALENDARIO") -> H1 CALENDARIO
A7: H3 | B7: ¿La hora de envío cambia cuántas personas abren? | C7: Apertura | D7: 0,750 | E7: No | F7: =HYPERLINK("#'H1 CALENDARIO'!A53","H1 CALENDARIO") -> H1 CALENDARIO
A8: H4 | B8: ¿Las fechas de pago (quincena) cambian cuántas personas abren? | C8: Apertura | D8: 0,659 | E8: No | F8: =HYPERLINK("#'H1 CALENDARIO'!A77","H1 CALENDARIO") -> H1 CALENDARIO
A9: H5 | B9: ¿Las fechas de Colombia cambian cuántas personas abren? | C9: Apertura | D9: — | E9: No | F9: =HYPERLINK("#'H1 CALENDARIO'!A101","H1 CALENDARIO") -> H1 CALENDARIO
A10: H6 | B10: ¿Los días con muchos envíos (20 o más campañas) abren menos? | C10: Apertura | D10: 0,373 | E10: No | F10: =HYPERLINK("#'H1 CALENDARIO'!A125","H1 CALENDARIO") -> H1 CALENDARIO
A11: H7 | B11: ¿Hay algún día o semana que se salga de lo normal? | C11: Apertura | D11: — | E11: No | F11: =HYPERLINK("#'H1 CALENDARIO'!A149","H1 CALENDARIO") -> H1 CALENDARIO
A12: H8 | B12: ¿El tipo de campaña cambia cuántas personas abren? | C12: Apertura | D12: 0,211 | E12: No | F12: =HYPERLINK("#'H2 CAMPAÑA'!A5","H2 CAMPAÑA") -> H2 CAMPAÑA
A13: H9 | B13: ¿El objetivo de la campaña (vender, educar, lanzar, fidelizar) cambia el resultado? | C13: Apertura | D13: 0,357 | E13: No | F13: =HYPERLINK("#'H2 CAMPAÑA'!A29","H2 CAMPAÑA") -> H2 CAMPAÑA
A14: H10 | B14: ¿El tamaño del envío cambia cuántas personas abren? | C14: Apertura | D14: 0,832 | E14: No | F14: =HYPERLINK("#'H2 CAMPAÑA'!A53","H2 CAMPAÑA") -> H2 CAMPAÑA
A15: H11 | B15: ¿Repetir el mismo asunto lo desgasta? | C15: Apertura | D15: 0,449 | E15: No | F15: =HYPERLINK("#'H2 CAMPAÑA'!A77","H2 CAMPAÑA") -> H2 CAMPAÑA
A16: H12 | B16: ¿Los ingresos y la conversión suben con los clics? | C16: Ingresos | D16: 0,406 | E16: No | F16: =HYPERLINK("#'H2 CAMPAÑA'!A101","H2 CAMPAÑA") -> H2 CAMPAÑA
A17: H13 | B17: ¿Qué explica más la apertura? | C17: Apertura | D17: < 0,001 | E17: Sí | F17: =HYPERLINK("#'H3 ASUNTO'!A5","H3 ASUNTO") -> H3 ASUNTO
A18: H14 | B18: ¿El efecto del asunto es real o es suerte? | C18: Apertura | D18: — | E18: Sí | F18: =HYPERLINK("#'H3 ASUNTO'!A29","H3 ASUNTO") -> H3 ASUNTO
A19: H15 | B19: ¿Qué estilo de asunto abre más: con cifra, recompensa, solo urgencia o pregunta? | C19: Apertura | D19: < 0,001 | E19: Sí | F19: =HYPERLINK("#'H3 ASUNTO'!A53","H3 ASUNTO") -> H3 ASUNTO
A20: H16 | B20: ¿Empezar el asunto con una etiqueta ("Actualización", "Presentamos", "Oportunidades") resta? | C20: Apertura | D20: < 0,001 | E20: Sí | F20: =HYPERLINK("#'H3 ASUNTO'!A77","H3 ASUNTO") -> H3 ASUNTO
A21: H17 | B21: ¿Un preheader vago resta? | C21: Apertura | D21: < 0,001 | E21: Sí | F21: =HYPERLINK("#'H3 ASUNTO'!A101","H3 ASUNTO") -> H3 ASUNTO
A22: H18 | B22: ¿Se ve en ejemplos concretos? | C22: Apertura | D22: — | E22: Sí | F22: =HYPERLINK("#'H3 ASUNTO'!A125","H3 ASUNTO") -> H3 ASUNTO
A23: H19 | B23: ¿Los asuntos que se abren también reciben clics? | C23: CTR | D23: < 0,001 | E23: Sí | F23: =HYPERLINK("#'H3 ASUNTO'!A149","H3 ASUNTO") -> H3 ASUNTO
A24: H20 | B24: ¿Cumplir las buenas prácticas de Mailchimp (máximo 60 caracteres, 9 palabras, 3 signos y 1 emoji) sube la apertura? | C24: Apertura | D24: 0,525 | E24: No | F24: =HYPERLINK("#'H3 ASUNTO'!A173","H3 ASUNTO") -> H3 ASUNTO
A25: H21 | B25: En las campañas de descuento, ¿qué tipo de campaña funciona mejor? | C25: Apertura | D25: 0,002 | E25: Sí | F25: =HYPERLINK("#'H4 TEMÁTICA HOT SALE'!A8","H4 TEMÁTICA HOT SALE") -> H4 TEMÁTICA HOT SALE
A26: H22 | B26: En las campañas de descuento, ¿qué estilo de asunto funciona? | C26: Apertura | D26: < 0,001 | E26: Sí | F26: =HYPERLINK("#'H4 TEMÁTICA HOT SALE'!A32","H4 TEMÁTICA HOT SALE") -> H4 TEMÁTICA HOT SALE
A27: H23 | B27: En las campañas de descuento, ¿importan las fechas de pago (quincena)? | C27: Apertura | D27: 0,613 | E27: No | F27: =HYPERLINK("#'H4 TEMÁTICA HOT SALE'!A56","H4 TEMÁTICA HOT SALE") -> H4 TEMÁTICA HOT SALE
A28: H24 | B28: En las campañas de descuento, ¿importa el día de la semana? | C28: Apertura | D28: 0,474 | E28: No | F28: =HYPERLINK("#'H4 TEMÁTICA HOT SALE'!A80","H4 TEMÁTICA HOT SALE") -> H4 TEMÁTICA HOT SALE
A29: H25 | B29: En las campañas de descuento, ¿importa la hora de envío? | C29: Apertura | D29: 0,155 | E29: No | F29: =HYPERLINK("#'H4 TEMÁTICA HOT SALE'!A104","H4 TEMÁTICA HOT SALE") -> H4 TEMÁTICA HOT SALE
A30: H26 | B30: ¿Poner el límite de tiempo en el asunto ("solo por hoy", "últimas horas") ayuda? | C30: Apertura | D30: 0,003 | E30: Sí | F30: =HYPERLINK("#'H4 TEMÁTICA HOT SALE'!A128","H4 TEMÁTICA HOT SALE") -> H4 TEMÁTICA HOT SALE
A31: H27 | B31: ¿La urgencia funciona si va con un beneficio concreto? | C31: Apertura | D31: — | E31: Señal | F31: =HYPERLINK("#'H4 TEMÁTICA HOT SALE'!A152","H4 TEMÁTICA HOT SALE") -> H4 TEMÁTICA HOT SALE
A32: H28 | B32: Dentro de Flash Sale, ¿cuánto pesa el asunto? | C32: Apertura | D32: < 0,001 | E32: Sí | F32: =HYPERLINK("#'H4 TEMÁTICA HOT SALE'!A176","H4 TEMÁTICA HOT SALE") -> H4 TEMÁTICA HOT SALE
A33: H29 | B33: Los Hot Sale anteriores, ¿funcionaron? | C33: Apertura | D33: 0,022 | E33: Sí | F33: =HYPERLINK("#'H4 TEMÁTICA HOT SALE'!A210","H4 TEMÁTICA HOT SALE") -> H4 TEMÁTICA HOT SALE
A34: H30 | B34: ¿Qué pasó campaña por campaña en los Hot Sale anteriores? | C34: Apertura | D34: — | E34: Señal | F34: =HYPERLINK("#'H4 TEMÁTICA HOT SALE'!A234","H4 TEMÁTICA HOT SALE") -> H4 TEMÁTICA HOT SALE
A36: Cómo leer "¿Cambia el resultado?": Sí = la diferencia es real. No = puede ser azar. Señal = va en la dirección esperada pero hay pocos casos; se confirma con el A/B del Hot Sale.

Sheet H0 DATOS
A1: Antes de analizar · qué datos se usan y por qué se excluye el 15 %
A2: Las 576 filas del archivo, cuántas se usan y por qué se dejó cada una fuera. El detalle fila por fila está en FILAS EXCLUIDAS.
A4: Se analiza el 85 % del archivo: 489 de 576 filas
A5: Filas | B5: Filas | C5: % del archivo
A6: Se analizan | B6: =COUNT('DATOS LIMPIOS'!$G$5:$G$493) -> 489 | C6: =B6/B8*100 -> 84.895833
A7: Se excluyen | B7: =COUNTA('FILAS EXCLUIDAS'!$C$5:$C$200) -> 87 | C7: =B7/B8*100 -> 15.104167
A8: Total del archivo | B8: =B6+B7 -> 576 | C8: =B8/B8*100 -> 100
A18: Por qué se excluye cada fila: la mayoría tiene más clics que aperturas
A19: Motivo | B19: Filas | C19: Qué significa
A20: Imposible: más clics que aperturas | B20: =COUNTIF('FILAS EXCLUIDAS'!$C$5:$C$200,A20) -> 72 | C20: Más clics que personas que abrieron. Puede pasar si la columna cuenta clics repetidos de una misma persona, por eso se revisó todo con y sin ellas.
A21: Fecha fuera de la ventana ago-oct 2025 | B21: =COUNTIF('FILAS EXCLUIDAS'!$C$5:$C$200,A21) -> 7 | C21: Fechas de 1990, 2022 y 2026. El caso pide los últimos tres meses.
A22: Imposible: más aperturas que envíos | B22: =COUNTIF('FILAS EXCLUIDAS'!$C$5:$C$200,A22) -> 5 | C22: No puede abrir más gente de la que recibió el correo.
A23: Campos vacíos en métricas de cálculo | B23: =COUNTIF('FILAS EXCLUIDAS'!$C$5:$C$200,A23) -> 3 | C23: Sin envíos, aperturas o clics no se puede calcular ninguna tasa.
A25: Las ventas no se excluyen, pero tampoco se usan: conversión, ingresos y bajas se comportan como números al azar (hoja H2 CAMPAÑA). Por eso todo el análisis se mide en aperturas y clics.

Sheet H1 CALENDARIO
A1: Hipótesis de calendario · ¿cuándo se envía importa?
A2: Cada bloque es una hipótesis: la pregunta, la respuesta, la tabla (fórmulas sobre DATOS LIMPIOS) y su gráfica. "p" es la probabilidad de ver la diferencia por azar.
A4: H1 · ¿El mes cambia cuántas personas abren?
A5: No. Agosto, septiembre y octubre abren prácticamente igual. No hay estacionalidad que aprovechar en esta ventana.
A8: Tabla H1 · Apertura y CTR por mes de envío
A9: Mes | B9: Campañas | C9: Apertura (%) | D9: CTR (%) | E9: Promedio general de apertura (%)
A10: Agosto | B10: =COUNTIFS('DATOS LIMPIOS'!$T$5:$T$493,"Agosto") -> 159 | C10: =AVERAGEIFS('DATOS LIMPIOS'!$M$5:$M$493,'DATOS LIMPIOS'!$T$5:$T$493,"Agosto") -> 29.514345 | D10: =AVERAGEIFS('DATOS LIMPIOS'!$N$5:$N$493,'DATOS LIMPIOS'!$T$5:$T$493,"Agosto") -> 10.016983 | E10: =AVERAGE('DATOS LIMPIOS'!$M$5:$M$493) -> 29.186614
A11: Septiembre | B11: =COUNTIFS('DATOS LIMPIOS'!$T$5:$T$493,"Septiembre") -> 167 | C11: =AVERAGEIFS('DATOS LIMPIOS'!$M$5:$M$493,'DATOS LIMPIOS'!$T$5:$T$493,"Septiembre") -> 28.665371 | D11: =AVERAGEIFS('DATOS LIMPIOS'!$N$5:$N$493,'DATOS LIMPIOS'!$T$5:$T$493,"Septiembre") -> 9.6054365 | E11: =AVERAGE('DATOS LIMPIOS'!$M$5:$M$493) -> 29.186614
A12: Octubre | B12: =COUNTIFS('DATOS LIMPIOS'!$T$5:$T$493,"Octubre") -> 163 | C12: =AVERAGEIFS('DATOS LIMPIOS'!$M$5:$M$493,'DATOS LIMPIOS'!$T$5:$T$493,"Octubre") -> 29.400958 | D12: =AVERAGEIFS('DATOS LIMPIOS'!$N$5:$N$493,'DATOS LIMPIOS'!$T$5:$T$493,"Octubre") -> 9.7492145 | E12: =AVERAGE('DATOS LIMPIOS'!$M$5:$M$493) -> 29.186614
A14: ¿Cambia el resultado? No | D14: p = 0,823 (calculado en Python)
A28: H2 · ¿El día de la semana cambia cuántas personas abren?
A29: No. Todos los días quedan cerca del promedio. El domingo se ve más alto, pero son muy pocas campañas: con tan pocas, el promedio se mueve por azar.
A32: Tabla H2 · Apertura y CTR por día de la semana
A33: Día | B33: Campañas | C33: Apertura (%) | D33: CTR (%) | E33: Promedio general de apertura (%)
A34: Lunes | B34: =COUNTIFS('DATOS LIMPIOS'!$U$5:$U$493,"Lunes") -> 115 | C34: =AVERAGEIFS('DATOS LIMPIOS'!$M$5:$M$493,'DATOS LIMPIOS'!$U$5:$U$493,"Lunes") -> 29.509194 | D34: =AVERAGEIFS('DATOS LIMPIOS'!$N$5:$N$493,'DATOS LIMPIOS'!$U$5:$U$493,"Lunes") -> 9.9843773 | E34: =AVERAGE('DATOS LIMPIOS'!$M$5:$M$493) -> 29.186614
A35: Martes | B35: =COUNTIFS('DATOS LIMPIOS'!$U$5:$U$493,"Martes") -> 93 | C35: =AVERAGEIFS('DATOS LIMPIOS'!$M$5:$M$493,'DATOS LIMPIOS'!$U$5:$U$493,"Martes") -> 28.853982 | D35: =AVERAGEIFS('DATOS LIMPIOS'!$N$5:$N$493,'DATOS LIMPIOS'!$U$5:$U$493,"Martes") -> 10.172968 | E35: =AVERAGE('DATOS LIMPIOS'!$M$5:$M$493) -> 29.186614
A36: Miércoles | B36: =COUNTIFS('DATOS LIMPIOS'!$U$5:$U$493,"Miércoles") -> 98 | C36: =AVERAGEIFS('DATOS LIMPIOS'!$M$5:$M$493,'DATOS LIMPIOS'!$U$5:$U$493,"Miércoles") -> 29.805531 | D36: =AVERAGEIFS('DATOS LIMPIOS'!$N$5:$N$493,'DATOS LIMPIOS'!$U$5:$U$493,"Miércoles") -> 9.9605132 | E36: =AVERAGE('DATOS LIMPIOS'!$M$5:$M$493) -> 29.186614
A37: Jueves | B37: =COUNTIFS('DATOS LIMPIOS'!$U$5:$U$493,"Jueves") -> 62 | C37: =AVERAGEIFS('DATOS LIMPIOS'!$M$5:$M$493,'DATOS LIMPIOS'!$U$5:$U$493,"Jueves") -> 28.922959 | D37: =AVERAGEIFS('DATOS LIMPIOS'!$N$5:$N$493,'DATOS LIMPIOS'!$U$5:$U$493,"Jueves") -> 8.6545725 | E37: =AVERAGE('DATOS LIMPIOS'!$M$5:$M$493) -> 29.186614
A38: Viernes | B38: =COUNTIFS('DATOS LIMPIOS'!$U$5:$U$493,"Viernes") -> 46 | C38: =AVERAGEIFS('DATOS LIMPIOS'!$M$5:$M$493,'DATOS LIMPIOS'!$U$5:$U$493,"Viernes") -> 27.798718 | D38: =AVERAGEIFS('DATOS LIMPIOS'!$N$5:$N$493,'DATOS LIMPIOS'!$U$5:$U$493,"Viernes") -> 9.4066366 | E38: =AVERAGE('DATOS LIMPIOS'!$M$5:$M$493) -> 29.186614
A39: Sábado | B39: =COUNTIFS('DATOS LIMPIOS'!$U$5:$U$493,"Sábado") -> 64 | C39: =AVERAGEIFS('DATOS LIMPIOS'!$M$5:$M$493,'DATOS LIMPIOS'!$U$5:$U$493,"Sábado") -> 28.625989 | D39: =AVERAGEIFS('DATOS LIMPIOS'!$N$5:$N$493,'DATOS LIMPIOS'!$U$5:$U$493,"Sábado") -> 9.6393947 | E39: =AVERAGE('DATOS LIMPIOS'!$M$5:$M$493) -> 29.186614
A40: Domingo | B40: =COUNTIFS('DATOS LIMPIOS'!$U$5:$U$493,"Domingo") -> 11 | C40: =AVERAGEIFS('DATOS LIMPIOS'!$M$5:$M$493,'DATOS LIMPIOS'!$U$5:$U$493,"Domingo") -> 33.664234 | D40: =AVERAGEIFS('DATOS LIMPIOS'!$N$5:$N$493,'DATOS LIMPIOS'!$U$5:$U$493,"Domingo") -> 11.75458 | E40: =AVERAGE('DATOS LIMPIOS'!$M$5:$M$493) -> 29.186614
A42: ¿Cambia el resultado? No | D42: p = 0,860 (calculado en Python)
A52: H3 · ¿La hora de envío cambia cuántas personas abren?
A53: No. Ninguna hora se separa del promedio de forma real.
A56: Tabla H3 · Apertura y CTR por hora de envío
A57: Hora | B57: Campañas | C57: Apertura (%) | D57: CTR (%) | E57: Promedio general de apertura (%)
A58: 8 | B58: =COUNTIFS('DATOS LIMPIOS'!$V$5:$V$493,8) -> 31 | C58: =AVERAGEIFS('DATOS LIMPIOS'!$M$5:$M$493,'DATOS LIMPIOS'!$V$5:$V$493,8) -> 28.287787 | D58: =AVERAGEIFS('DATOS LIMPIOS'!$N$5:$N$493,'DATOS LIMPIOS'!$V$5:$V$493,8) -> 8.2129061 | E58: =AVERAGE('DATOS LIMPIOS'!$M$5:$M$493) -> 29.186614
A59: 9 | B59: =COUNTIFS('DATOS LIMPIOS'!$V$5:$V$493,9) -> 36 | C59: =AVERAGEIFS('DATOS LIMPIOS'!$M$5:$M$493,'DATOS LIMPIOS'!$V$5:$V$493,9) -> 28.997432 | D59: =AVERAGEIFS('DATOS LIMPIOS'!$N$5:$N$493,'DATOS LIMPIOS'!$V$5:$V$493,9) -> 9.6156747 | E59: =AVERAGE('DATOS LIMPIOS'!$M$5:$M$493) -> 29.186614
A60: 10 | B60: =COUNTIFS('DATOS LIMPIOS'!$V$5:$V$493,10) -> 97 | C60: =AVERAGEIFS('DATOS LIMPIOS'!$M$5:$M$493,'DATOS LIMPIOS'!$V$5:$V$493,10) -> 28.945982 | D60: =AVERAGEIFS('DATOS LIMPIOS'!$N$5:$N$493,'DATOS LIMPIOS'!$V$5:$V$493,10) -> 10.274592 | E60: =AVERAGE('DATOS LIMPIOS'!$M$5:$M$493) -> 29.186614
A61: 11 | B61: =COUNTIFS('DATOS LIMPIOS'!$V$5:$V$493,11) -> 89 | C61: =AVERAGEIFS('DATOS LIMPIOS'!$M$5:$M$493,'DATOS LIMPIOS'!$V$5:$V$493,11) -> 28.113088 | D61: =AVERAGEIFS('DATOS LIMPIOS'!$N$5:$N$493,'DATOS LIMPIOS'!$V$5:$V$493,11) -> 9.5593715 | E61: =AVERAGE('DATOS LIMPIOS'!$M$5:$M$493) -> 29.186614
A62: 12 | B62: =COUNTIFS('DATOS LIMPIOS'!$V$5:$V$493,12) -> 30 | C62: =AVERAGEIFS('DATOS LIMPIOS'!$M$5:$M$493,'DATOS LIMPIOS'!$V$5:$V$493,12) -> 32.530275 | D62: =AVERAGEIFS('DATOS LIMPIOS'!$N$5:$N$493,'DATOS LIMPIOS'!$V$5:$V$493,12) -> 9.7455376 | E62: =AVERAGE('DATOS LIMPIOS'!$M$5:$M$493) -> 29.186614
A63: 13 | B63: =COUNTIFS('DATOS LIMPIOS'!$V$5:$V$493,13) -> 69 | C63: =AVERAGEIFS('DATOS LIMPIOS'!$M$5:$M$493,'DATOS LIMPIOS'!$V$5:$V$493,13) -> 28.707113 | D63: =AVERAGEIFS('DATOS LIMPIOS'!$N$5:$N$493,'DATOS LIMPIOS'!$V$5:$V$493,13) -> 9.5853681 | E63: =AVERAGE('DATOS LIMPIOS'!$M$5:$M$493) -> 29.186614
A64: 14 | B64: =COUNTIFS('DATOS LIMPIOS'!$V$5:$V$493,14) -> 37 | C64: =AVERAGEIFS('DATOS LIMPIOS'!$M$5:$M$493,'DATOS LIMPIOS'!$V$5:$V$493,14) -> 27.847081 | D64: =AVERAGEIFS('DATOS LIMPIOS'!$N$5:$N$493,'DATOS LIMPIOS'!$V$5:$V$493,14) -> 9.810471 | E64: =AVERAGE('DATOS LIMPIOS'!$M$5:$M$493) -> 29.186614
A65: 15 | B65: =COUNTIFS('DATOS LIMPIOS'!$V$5:$V$493,15) -> 65 | C65: =AVERAGEIFS('DATOS LIMPIOS'!$M$5:$M$493,'DATOS LIMPIOS'!$V$5:$V$493,15) -> 31.017355 | D65: =AVERAGEIFS('DATOS LIMPIOS'!$N$5:$N$493,'DATOS LIMPIOS'!$V$5:$V$493,15) -> 10.467229 | E65: =AVERAGE('DATOS LIMPIOS'!$M$5:$M$493) -> 29.186614
A66: 16 | B66: =COUNTIFS('DATOS LIMPIOS'!$V$5:$V$493,16) -> 35 | C66: =AVERAGEIFS('DATOS LIMPIOS'!$M$5:$M$493,'DATOS LIMPIOS'!$V$5:$V$493,16) -> 29.669457 | D66: =AVERAGEIFS('DATOS LIMPIOS'!$N$5:$N$493,'DATOS LIMPIOS'!$V$5:$V$493,16) -> 9.7323544 | E66: =AVERAGE('DATOS LIMPIOS'!$M$5:$M$493) -> 29.186614
A68: ¿Cambia el resultado? No | D68: p = 0,750 (calculado en Python)
A76: H4 · ¿Las fechas de pago (quincena) cambian cuántas personas abren?
A77: No en aperturas. En clics, la quincena sale un poco más baja, pero va al revés de lo esperado y no es estable: se cae al mover un día la definición. Se toma como ruido.
A80: Tabla H4 · Apertura y CTR según el momento del mes (fechas de pago)
A81: Momento del mes | B81: Campañas | C81: Apertura (%) | D81: CTR (%) | E81: Promedio general de apertura (%)
A82: Quincena | B82: =COUNTIFS('DATOS LIMPIOS'!$W$5:$W$493,"Quincena") -> 92 | C82: =AVERAGEIFS('DATOS LIMPIOS'!$M$5:$M$493,'DATOS LIMPIOS'!$W$5:$W$493,"Quincena") -> 28.40228 | D82: =AVERAGEIFS('DATOS LIMPIOS'!$N$5:$N$493,'DATOS LIMPIOS'!$W$5:$W$493,"Quincena") -> 8.6600006 | E82: =AVERAGE('DATOS LIMPIOS'!$M$5:$M$493) -> 29.186614
A83: Días después del pago | B83: =COUNTIFS('DATOS LIMPIOS'!$W$5:$W$493,"Días después del pago") -> 131 | C83: =AVERAGEIFS('DATOS LIMPIOS'!$M$5:$M$493,'DATOS LIMPIOS'!$W$5:$W$493,"Días después del pago") -> 29.94016 | D83: =AVERAGEIFS('DATOS LIMPIOS'!$N$5:$N$493,'DATOS LIMPIOS'!$W$5:$W$493,"Días después del pago") -> 9.8591375 | E83: =AVERAGE('DATOS LIMPIOS'!$M$5:$M$493) -> 29.186614
A84: Resto del mes | B84: =COUNTIFS('DATOS LIMPIOS'!$W$5:$W$493,"Resto del mes") -> 266 | C84: =AVERAGEIFS('DATOS LIMPIOS'!$M$5:$M$493,'DATOS LIMPIOS'!$W$5:$W$493,"Resto del mes") -> 29.086779 | D84: =AVERAGEIFS('DATOS LIMPIOS'!$N$5:$N$493,'DATOS LIMPIOS'!$W$5:$W$493,"Resto del mes") -> 10.14159 | E84: =AVERAGE('DATOS LIMPIOS'!$M$5:$M$493) -> 29.186614
A86: ¿Cambia el resultado? No | D86: p = 0,659 (calculado en Python)
A100: H5 · ¿Las fechas de Colombia cambian cuántas personas abren?
A101: No. Se miraron los 3 días antes y el día después de cada fecha, comparando cada campaña con lo que suele abrir su mismo asunto. Una campaña normal se mueve unos 9 puntos para arriba o para abajo; ninguna fecha se sale de eso.
A104: Tabla H5 · Diferencia de apertura alrededor de cada fecha de Colombia, contra lo que suele abrir el mismo asunto
A105: Fecha | B105: Campañas en la ventana | C105: Diferencia (puntos)
A106: Batalla de Boyacá (festivo) | B106: =COUNTIFS('DATOS LIMPIOS'!$S$5:$S$493,">="&(DATE(2025,8,7)-3),'DATOS LIMPIOS'!$S$5:$S$493,"<="&(DATE(2025,8,7)+1)) -> 57 | C106: =AVERAGEIFS('DATOS LIMPIOS'!$AE$5:$AE$493,'DATOS LIMPIOS'!$S$5:$S$493,">="&(DATE(2025,8,7)-3),'DATOS LIMPIOS'!$S$5:$S$493,"<="&(DATE(2025,8,7)+1)) -> 1.7606372
A107: La Asunción (festivo) | B107: =COUNTIFS('DATOS LIMPIOS'!$S$5:$S$493,">="&(DATE(2025,8,18)-3),'DATOS LIMPIOS'!$S$5:$S$493,"<="&(DATE(2025,8,18)+1)) -> 34 | C107: =AVERAGEIFS('DATOS LIMPIOS'!$AE$5:$AE$493,'DATOS LIMPIOS'!$S$5:$S$493,">="&(DATE(2025,8,18)-3),'DATOS LIMPIOS'!$S$5:$S$493,"<="&(DATE(2025,8,18)+1)) -> 0.47432595
A108: Amor y Amistad | B108: =COUNTIFS('DATOS LIMPIOS'!$S$5:$S$493,">="&(DATE(2025,9,20)-3),'DATOS LIMPIOS'!$S$5:$S$493,"<="&(DATE(2025,9,20)+1)) -> 28 | C108: =AVERAGEIFS('DATOS LIMPIOS'!$AE$5:$AE$493,'DATOS LIMPIOS'!$S$5:$S$493,">="&(DATE(2025,9,20)-3),'DATOS LIMPIOS'!$S$5:$S$493,"<="&(DATE(2025,9,20)+1)) -> -1.9271646
A109: Día de la Raza (festivo) | B109: =COUNTIFS('DATOS LIMPIOS'!$S$5:$S$493,">="&(DATE(2025,10,13)-3),'DATOS LIMPIOS'!$S$5:$S$493,"<="&(DATE(2025,10,13)+1)) -> 27 | C109: =AVERAGEIFS('DATOS LIMPIOS'!$AE$5:$AE$493,'DATOS LIMPIOS'!$S$5:$S$493,">="&(DATE(2025,10,13)-3),'DATOS LIMPIOS'!$S$5:$S$493,"<="&(DATE(2025,10,13)+1)) -> 2.381749
A110: Halloween | B110: =COUNTIFS('DATOS LIMPIOS'!$S$5:$S$493,">="&(DATE(2025,10,31)-3),'DATOS LIMPIOS'!$S$5:$S$493,"<="&(DATE(2025,10,31)+1)) -> 30 | C110: =AVERAGEIFS('DATOS LIMPIOS'!$AE$5:$AE$493,'DATOS LIMPIOS'!$S$5:$S$493,">="&(DATE(2025,10,31)-3),'DATOS LIMPIOS'!$S$5:$S$493,"<="&(DATE(2025,10,31)+1)) -> 0.75495911
A112: ¿Cambia el resultado? No
A113: Lo que sí se vio: las campañas de fiestas y regalos salieron parejas los tres meses, sin un pico antes de Amor y Amistad.
A124: H6 · ¿Los días con muchos envíos (20 o más campañas) abren menos?
A125: No. Los días masivos abren casi igual que los demás.
A128: Tabla H6 · Apertura y CTR en días masivos y días normales
A129: Tipo de día | B129: Campañas | C129: Apertura (%) | D129: CTR (%) | E129: Promedio general de apertura (%)
A130: Día masivo | B130: =COUNTIFS('DATOS LIMPIOS'!$Y$5:$Y$493,"Sí") -> 400 | C130: =AVERAGEIFS('DATOS LIMPIOS'!$M$5:$M$493,'DATOS LIMPIOS'!$Y$5:$Y$493,"Sí") -> 28.956084 | D130: =AVERAGEIFS('DATOS LIMPIOS'!$N$5:$N$493,'DATOS LIMPIOS'!$Y$5:$Y$493,"Sí") -> 9.6653749 | E130: =AVERAGE('DATOS LIMPIOS'!$M$5:$M$493) -> 29.186614
A131: Día normal | B131: =COUNTIFS('DATOS LIMPIOS'!$Y$5:$Y$493,"No") -> 89 | C131: =AVERAGEIFS('DATOS LIMPIOS'!$M$5:$M$493,'DATOS LIMPIOS'!$Y$5:$Y$493,"No") -> 30.2227 | D131: =AVERAGEIFS('DATOS LIMPIOS'!$N$5:$N$493,'DATOS LIMPIOS'!$Y$5:$Y$493,"No") -> 10.334609 | E131: =AVERAGE('DATOS LIMPIOS'!$M$5:$M$493) -> 29.186614
A133: ¿Cambia el resultado? No | D133: p = 0,373 (calculado en Python)
A148: H7 · ¿Hay algún día o semana que se salga de lo normal?
A149: No. Así se ve cada día de los tres meses: cuanto más azul, más se abrió ese día. No hay una semana ni un día del mes que se repita como mejor. La línea de la derecha muestra que la apertura sube y baja alrededor del promedio sin una tendencia.
A152: Tabla H7 · Apertura promedio de cada día, agosto a octubre (cuanto más azul, más se abrió)
A153: Semana | B153: Lun | C153: Mar | D153: Mié | E153: Jue | F153: Vie | G153: Sáb | H153: Dom
A154: Semana del 28 jul | F154: =IFERROR(AVERAGEIF('DATOS LIMPIOS'!$S$5:$S$493,DATE(2025,8,1),'DATOS LIMPIOS'!$M$5:$M$493),"") -> 38.43907 | G154: =IFERROR(AVERAGEIF('DATOS LIMPIOS'!$S$5:$S$493,DATE(2025,8,2),'DATOS LIMPIOS'!$M$5:$M$493),"") -> 25.911019 | H154: =IFERROR(AVERAGEIF('DATOS LIMPIOS'!$S$5:$S$493,DATE(2025,8,3),'DATOS LIMPIOS'!$M$5:$M$493),"") -> 17.337091
A155: Semana del 4 ago | B155: =IFERROR(AVERAGEIF('DATOS LIMPIOS'!$S$5:$S$493,DATE(2025,8,4),'DATOS LIMPIOS'!$M$5:$M$493),"") -> 30.002154 | C155: =IFERROR(AVERAGEIF('DATOS LIMPIOS'!$S$5:$S$493,DATE(2025,8,5),'DATOS LIMPIOS'!$M$5:$M$493),"") -> 39.372366 | D155: =IFERROR(AVERAGEIF('DATOS LIMPIOS'!$S$5:$S$493,DATE(2025,8,6),'DATOS LIMPIOS'!$M$5:$M$493),"") -> 32.222586 | E155: =IFERROR(AVERAGEIF('DATOS LIMPIOS'!$S$5:$S$493,DATE(2025,8,7),'DATOS LIMPIOS'!$M$5:$M$493),"") -> 30.585723 | F155: =IFERROR(AVERAGEIF('DATOS LIMPIOS'!$S$5:$S$493,DATE(2025,8,8),'DATOS LIMPIOS'!$M$5:$M$493),"") -> 21.477304 | G155: =IFERROR(AVERAGEIF('DATOS LIMPIOS'!$S$5:$S$493,DATE(2025,8,9),'DATOS LIMPIOS'!$M$5:$M$493),"") -> 38.550955 | H155: =IFERROR(AVERAGEIF('DATOS LIMPIOS'!$S$5:$S$493,DATE(2025,8,10),'DATOS LIMPIOS'!$M$5:$M$493),"") -> 37.196595
A156: Semana del 11 ago | B156: =IFERROR(AVERAGEIF('DATOS LIMPIOS'!$S$5:$S$493,DATE(2025,8,11),'DATOS LIMPIOS'!$M$5:$M$493),"") | C156: =IFERROR(AVERAGEIF('DATOS LIMPIOS'!$S$5:$S$493,DATE(2025,8,12),'DATOS LIMPIOS'!$M$5:$M$493),"") -> 12.293602 | D156: =IFERROR(AVERAGEIF('DATOS LIMPIOS'!$S$5:$S$493,DATE(2025,8,13),'DATOS LIMPIOS'!$M$5:$M$493),"") -> 36.635297 | E156: =IFERROR(AVERAGEIF('DATOS LIMPIOS'!$S$5:$S$493,DATE(2025,8,14),'DATOS LIMPIOS'!$M$5:$M$493),"") -> 25.951159 | F156: =IFERROR(AVERAGEIF('DATOS LIMPIOS'!$S$5:$S$493,DATE(2025,8,15),'DATOS LIMPIOS'!$M$5:$M$493),"") -> 26.98677 | G156: =IFERROR(AVERAGEIF('DATOS LIMPIOS'!$S$5:$S$493,DATE(2025,8,16),'DATOS LIMPIOS'!$M$5:$M$493),"") -> 26.396659 | H156: =IFERROR(AVERAGEIF('DATOS LIMPIOS'!$S$5:$S$493,DATE(2025,8,17),'DATOS LIMPIOS'!$M$5:$M$493),"") -> 29.812565
A157: Semana del 18 ago | B157: =IFERROR(AVERAGEIF('DATOS LIMPIOS'!$S$5:$S$493,DATE(2025,8,18),'DATOS LIMPIOS'!$M$5:$M$493),"") -> 48.806168 | C157: =IFERROR(AVERAGEIF('DATOS LIMPIOS'!$S$5:$S$493,DATE(2025,8,19),'DATOS LIMPIOS'!$M$5:$M$493),"") -> 31.709759 | D157: =IFERROR(AVERAGEIF('DATOS LIMPIOS'!$S$5:$S$493,DATE(2025,8,20),'DATOS LIMPIOS'!$M$5:$M$493),"") -> 19.789609 | E157: =IFERROR(AVERAGEIF('DATOS LIMPIOS'!$S$5:$S$493,DATE(2025,8,21),'DATOS LIMPIOS'!$M$5:$M$493),"") -> 23.07818 | F157: =IFERROR(AVERAGEIF('DATOS LIMPIOS'!$S$5:$S$493,DATE(2025,8,22),'DATOS LIMPIOS'!$M$5:$M$493),"") -> 32.308634 | G157: =IFERROR(AVERAGEIF('DATOS LIMPIOS'!$S$5:$S$493,DATE(2025,8,23),'DATOS LIMPIOS'!$M$5:$M$493),"") -> 26.247207 | H157: =IFERROR(AVERAGEIF('DATOS LIMPIOS'!$S$5:$S$493,DATE(2025,8,24),'DATOS LIMPIOS'!$M$5:$M$493),"")
A158: Semana del 25 ago | B158: =IFERROR(AVERAGEIF('DATOS LIMPIOS'!$S$5:$S$493,DATE(2025,8,25),'DATOS LIMPIOS'!$M$5:$M$493),"") -> 18.799678 | C158: =IFERROR(AVERAGEIF('DATOS LIMPIOS'!$S$5:$S$493,DATE(2025,8,26),'DATOS LIMPIOS'!$M$5:$M$493),"") -> 42.065659 | D158: =IFERROR(AVERAGEIF('DATOS LIMPIOS'!$S$5:$S$493,DATE(2025,8,27),'DATOS LIMPIOS'!$M$5:$M$493),"") -> 20.87768 | E158: =IFERROR(AVERAGEIF('DATOS LIMPIOS'!$S$5:$S$493,DATE(2025,8,28),'DATOS LIMPIOS'!$M$5:$M$493),"") | F158: =IFERROR(AVERAGEIF('DATOS LIMPIOS'!$S$5:$S$493,DATE(2025,8,29),'DATOS LIMPIOS'!$M$5:$M$493),"") -> 21.589775 | G158: =IFERROR(AVERAGEIF('DATOS LIMPIOS'!$S$5:$S$493,DATE(2025,8,30),'DATOS LIMPIOS'!$M$5:$M$493),"") -> 44.773187 | H158: =IFERROR(AVERAGEIF('DATOS LIMPIOS'!$S$5:$S$493,DATE(2025,8,31),'DATOS LIMPIOS'!$M$5:$M$493),"")
A159: Semana del 1 sep | B159: =IFERROR(AVERAGEIF('DATOS LIMPIOS'!$S$5:$S$493,DATE(2025,9,1),'DATOS LIMPIOS'!$M$5:$M$493),"") -> 30.008081 | C159: =IFERROR(AVERAGEIF('DATOS LIMPIOS'!$S$5:$S$493,DATE(2025,9,2),'DATOS LIMPIOS'!$M$5:$M$493),"") -> 6.0113878 | D159: =IFERROR(AVERAGEIF('DATOS LIMPIOS'!$S$5:$S$493,DATE(2025,9,3),'DATOS LIMPIOS'!$M$5:$M$493),"") -> 34.180304 | E159: =IFERROR(AVERAGEIF('DATOS LIMPIOS'!$S$5:$S$493,DATE(2025,9,4),'DATOS LIMPIOS'!$M$5:$M$493),"") -> 43.357049 | F159: =IFERROR(AVERAGEIF('DATOS LIMPIOS'!$S$5:$S$493,DATE(2025,9,5),'DATOS LIMPIOS'!$M$5:$M$493),"") -> 16.388552 | G159: =IFERROR(AVERAGEIF('DATOS LIMPIOS'!$S$5:$S$493,DATE(2025,9,6),'DATOS LIMPIOS'!$M$5:$M$493),"") -> 32.076377 | H159: =IFERROR(AVERAGEIF('DATOS LIMPIOS'!$S$5:$S$493,DATE(2025,9,7),'DATOS LIMPIOS'!$M$5:$M$493),"") -> 38.204192
A160: Semana del 8 sep | B160: =IFERROR(AVERAGEIF('DATOS LIMPIOS'!$S$5:$S$493,DATE(2025,9,8),'DATOS LIMPIOS'!$M$5:$M$493),"") -> 26.71583 | C160: =IFERROR(AVERAGEIF('DATOS LIMPIOS'!$S$5:$S$493,DATE(2025,9,9),'DATOS LIMPIOS'!$M$5:$M$493),"") -> 27.03 | D160: =IFERROR(AVERAGEIF('DATOS LIMPIOS'!$S$5:$S$493,DATE(2025,9,10),'DATOS LIMPIOS'!$M$5:$M$493),"") -> 37.537983 | E160: =IFERROR(AVERAGEIF('DATOS LIMPIOS'!$S$5:$S$493,DATE(2025,9,11),'DATOS LIMPIOS'!$M$5:$M$493),"") -> 27.746593 | F160: =IFERROR(AVERAGEIF('DATOS LIMPIOS'!$S$5:$S$493,DATE(2025,9,12),'DATOS LIMPIOS'!$M$5:$M$493),"") -> 38.629987 | G160: =IFERROR(AVERAGEIF('DATOS LIMPIOS'!$S$5:$S$493,DATE(2025,9,13),'DATOS LIMPIOS'!$M$5:$M$493),"") -> 24.663578 | H160: =IFERROR(AVERAGEIF('DATOS LIMPIOS'!$S$5:$S$493,DATE(2025,9,14),'DATOS LIMPIOS'!$M$5:$M$493),"")
A161: Semana del 15 sep | B161: =IFERROR(AVERAGEIF('DATOS LIMPIOS'!$S$5:$S$493,DATE(2025,9,15),'DATOS LIMPIOS'!$M$5:$M$493),"") | C161: =IFERROR(AVERAGEIF('DATOS LIMPIOS'!$S$5:$S$493,DATE(2025,9,16),'DATOS LIMPIOS'!$M$5:$M$493),"") -> 28.442443 | D161: =IFERROR(AVERAGEIF('DATOS LIMPIOS'!$S$5:$S$493,DATE(2025,9,17),'DATOS LIMPIOS'!$M$5:$M$493),"") -> 28.680104 | E161: =IFERROR(AVERAGEIF('DATOS LIMPIOS'!$S$5:$S$493,DATE(2025,9,18),'DATOS LIMPIOS'!$M$5:$M$493),"") -> 33.766981 | F161: =IFERROR(AVERAGEIF('DATOS LIMPIOS'!$S$5:$S$493,DATE(2025,9,19),'DATOS LIMPIOS'!$M$5:$M$493),"") -> 30.955186 | G161: =IFERROR(AVERAGEIF('DATOS LIMPIOS'!$S$5:$S$493,DATE(2025,9,20),'DATOS LIMPIOS'!$M$5:$M$493),"") | H161: =IFERROR(AVERAGEIF('DATOS LIMPIOS'!$S$5:$S$493,DATE(2025,9,21),'DATOS LIMPIOS'!$M$5:$M$493),"")
A162: Semana del 22 sep | B162: =IFERROR(AVERAGEIF('DATOS LIMPIOS'!$S$5:$S$493,DATE(2025,9,22),'DATOS LIMPIOS'!$M$5:$M$493),"") -> 30.3422 | C162: =IFERROR(AVERAGEIF('DATOS LIMPIOS'!$S$5:$S$493,DATE(2025,9,23),'DATOS LIMPIOS'!$M$5:$M$493),"") -> 41.064859 | D162: =IFERROR(AVERAGEIF('DATOS LIMPIOS'!$S$5:$S$493,DATE(2025,9,24),'DATOS LIMPIOS'!$M$5:$M$493),"") -> 40.777103 | E162: =IFERROR(AVERAGEIF('DATOS LIMPIOS'!$S$5:$S$493,DATE(2025,9,25),'DATOS LIMPIOS'!$M$5:$M$493),"") -> 48.880377 | F162: =IFERROR(AVERAGEIF('DATOS LIMPIOS'!$S$5:$S$493,DATE(2025,9,26),'DATOS LIMPIOS'!$M$5:$M$493),"") -> 19.669684 | G162: =IFERROR(AVERAGEIF('DATOS LIMPIOS'!$S$5:$S$493,DATE(2025,9,27),'DATOS LIMPIOS'!$M$5:$M$493),"") -> 11.07795 | H162: =IFERROR(AVERAGEIF('DATOS LIMPIOS'!$S$5:$S$493,DATE(2025,9,28),'DATOS LIMPIOS'!$M$5:$M$493),"") -> 24.873415
A163: Semana del 29 sep | B163: =IFERROR(AVERAGEIF('DATOS LIMPIOS'!$S$5:$S$493,DATE(2025,9,29),'DATOS LIMPIOS'!$M$5:$M$493),"") -> 17.5566 | C163: =IFERROR(AVERAGEIF('DATOS LIMPIOS'!$S$5:$S$493,DATE(2025,9,30),'DATOS LIMPIOS'!$M$5:$M$493),"") | D163: =IFERROR(AVERAGEIF('DATOS LIMPIOS'!$S$5:$S$493,DATE(2025,10,1),'DATOS LIMPIOS'!$M$5:$M$493),"") -> 27.153846 | E163: =IFERROR(AVERAGEIF('DATOS LIMPIOS'!$S$5:$S$493,DATE(2025,10,2),'DATOS LIMPIOS'!$M$5:$M$493),"") -> 19.57308 | F163: =IFERROR(AVERAGEIF('DATOS LIMPIOS'!$S$5:$S$493,DATE(2025,10,3),'DATOS LIMPIOS'!$M$5:$M$493),"") -> 43.952852 | G163: =IFERROR(AVERAGEIF('DATOS LIMPIOS'!$S$5:$S$493,DATE(2025,10,4),'DATOS LIMPIOS'!$M$5:$M$493),"") -> 20.609853 | H163: =IFERROR(AVERAGEIF('DATOS LIMPIOS'!$S$5:$S$493,DATE(2025,10,5),'DATOS LIMPIOS'!$M$5:$M$493),"") -> 36.434354
A164: Semana del 6 oct | B164: =IFERROR(AVERAGEIF('DATOS LIMPIOS'!$S$5:$S$493,DATE(2025,10,6),'DATOS LIMPIOS'!$M$5:$M$493),"") -> 32.601081 | C164: =IFERROR(AVERAGEIF('DATOS LIMPIOS'!$S$5:$S$493,DATE(2025,10,7),'DATOS LIMPIOS'!$M$5:$M$493),"") -> 15.952103 | D164: =IFERROR(AVERAGEIF('DATOS LIMPIOS'!$S$5:$S$493,DATE(2025,10,8),'DATOS LIMPIOS'!$M$5:$M$493),"") -> 28.999873 | E164: =IFERROR(AVERAGEIF('DATOS LIMPIOS'!$S$5:$S$493,DATE(2025,10,9),'DATOS LIMPIOS'!$M$5:$M$493),"") -> 28.700714 | F164: =IFERROR(AVERAGEIF('DATOS LIMPIOS'!$S$5:$S$493,DATE(2025,10,10),'DATOS LIMPIOS'!$M$5:$M$493),"") -> 23.971155 | G164: =IFERROR(AVERAGEIF('DATOS LIMPIOS'!$S$5:$S$493,DATE(2025,10,11),'DATOS LIMPIOS'!$M$5:$M$493),"") -> 41.835409 | H164: =IFERROR(AVERAGEIF('DATOS LIMPIOS'!$S$5:$S$493,DATE(2025,10,12),'DATOS LIMPIOS'!$M$5:$M$493),"") -> 30.4229
A165: Semana del 13 oct | B165: =IFERROR(AVERAGEIF('DATOS LIMPIOS'!$S$5:$S$493,DATE(2025,10,13),'DATOS LIMPIOS'!$M$5:$M$493),"") -> 31.836182 | C165: =IFERROR(AVERAGEIF('DATOS LIMPIOS'!$S$5:$S$493,DATE(2025,10,14),'DATOS LIMPIOS'!$M$5:$M$493),"") -> 14.962144 | D165: =IFERROR(AVERAGEIF('DATOS LIMPIOS'!$S$5:$S$493,DATE(2025,10,15),'DATOS LIMPIOS'!$M$5:$M$493),"") -> 11.75427 | E165: =IFERROR(AVERAGEIF('DATOS LIMPIOS'!$S$5:$S$493,DATE(2025,10,16),'DATOS LIMPIOS'!$M$5:$M$493),"") -> 44.964956 | F165: =IFERROR(AVERAGEIF('DATOS LIMPIOS'!$S$5:$S$493,DATE(2025,10,17),'DATOS LIMPIOS'!$M$5:$M$493),"") -> 28.812921 | G165: =IFERROR(AVERAGEIF('DATOS LIMPIOS'!$S$5:$S$493,DATE(2025,10,18),'DATOS LIMPIOS'!$M$5:$M$493),"") -> 29.376163 | H165: =IFERROR(AVERAGEIF('DATOS LIMPIOS'!$S$5:$S$493,DATE(2025,10,19),'DATOS LIMPIOS'!$M$5:$M$493),"") -> 45.54717
A166: Semana del 20 oct | B166: =IFERROR(AVERAGEIF('DATOS LIMPIOS'!$S$5:$S$493,DATE(2025,10,20),'DATOS LIMPIOS'!$M$5:$M$493),"") -> 26.459378 | C166: =IFERROR(AVERAGEIF('DATOS LIMPIOS'!$S$5:$S$493,DATE(2025,10,21),'DATOS LIMPIOS'!$M$5:$M$493),"") | D166: =IFERROR(AVERAGEIF('DATOS LIMPIOS'!$S$5:$S$493,DATE(2025,10,22),'DATOS LIMPIOS'!$M$5:$M$493),"") -> 18.074807 | E166: =IFERROR(AVERAGEIF('DATOS LIMPIOS'!$S$5:$S$493,DATE(2025,10,23),'DATOS LIMPIOS'!$M$5:$M$493),"") | F166: =IFERROR(AVERAGEIF('DATOS LIMPIOS'!$S$5:$S$493,DATE(2025,10,24),'DATOS LIMPIOS'!$M$5:$M$493),"") -> 27.584787 | G166: =IFERROR(AVERAGEIF('DATOS LIMPIOS'!$S$5:$S$493,DATE(2025,10,25),'DATOS LIMPIOS'!$M$5:$M$493),"") -> 46.204442 | H166: =IFERROR(AVERAGEIF('DATOS LIMPIOS'!$S$5:$S$493,DATE(2025,10,26),'DATOS LIMPIOS'!$M$5:$M$493),"") -> 35.839748
A167: Semana del 27 oct | B167: =IFERROR(AVERAGEIF('DATOS LIMPIOS'!$S$5:$S$493,DATE(2025,10,27),'DATOS LIMPIOS'!$M$5:$M$493),"") -> 29.514028 | C167: =IFERROR(AVERAGEIF('DATOS LIMPIOS'!$S$5:$S$493,DATE(2025,10,28),'DATOS LIMPIOS'!$M$5:$M$493),"") -> 33.664588 | D167: =IFERROR(AVERAGEIF('DATOS LIMPIOS'!$S$5:$S$493,DATE(2025,10,29),'DATOS LIMPIOS'!$M$5:$M$493),"") -> 29.573956 | E167: =IFERROR(AVERAGEIF('DATOS LIMPIOS'!$S$5:$S$493,DATE(2025,10,30),'DATOS LIMPIOS'!$M$5:$M$493),"") -> 47.78522 | F167: =IFERROR(AVERAGEIF('DATOS LIMPIOS'!$S$5:$S$493,DATE(2025,10,31),'DATOS LIMPIOS'!$M$5:$M$493),"")
A169: ¿Cambia el resultado? No
A170: Cada celda es la apertura promedio de las campañas de ese día. Las celdas vacías son días sin campañas o fuera del periodo; en la gráfica aparecen como huecos.

Sheet H2 CAMPAÑA
A1: Hipótesis de campaña · ¿el tipo, el objetivo o el tamaño importan?
A2: Mismo formato: pregunta, respuesta, tabla con fórmulas y gráfica.
A4: H8 · ¿El tipo de campaña cambia cuántas personas abren?
A5: No. Flash Sale, Newsletter, lanzamientos y los demás abren parecido. Lo que cambia es el asunto dentro de cada tipo (hoja H3).
A8: Tabla H8 · Apertura y CTR por tipo de campaña
A9: Tipo de campaña | B9: Campañas | C9: Apertura (%) | D9: CTR (%) | E9: Promedio general de apertura (%)
A10: Customer Appreciation | B10: =COUNTIF('DATOS LIMPIOS'!$B$5:$B$493,"Customer Appreciation") -> 73 | C10: =AVERAGEIF('DATOS LIMPIOS'!$B$5:$B$493,"Customer Appreciation",'DATOS LIMPIOS'!$M$5:$M$493) -> 31.113651 | D10: =AVERAGEIF('DATOS LIMPIOS'!$B$5:$B$493,"Customer Appreciation",'DATOS LIMPIOS'!$N$5:$N$493) -> 9.9969928 | E10: =AVERAGE('DATOS LIMPIOS'!$M$5:$M$493) -> 29.186614
A11: Exclusive Offers | B11: =COUNTIF('DATOS LIMPIOS'!$B$5:$B$493,"Exclusive Offers") -> 79 | C11: =AVERAGEIF('DATOS LIMPIOS'!$B$5:$B$493,"Exclusive Offers",'DATOS LIMPIOS'!$M$5:$M$493) -> 27.021448 | D11: =AVERAGEIF('DATOS LIMPIOS'!$B$5:$B$493,"Exclusive Offers",'DATOS LIMPIOS'!$N$5:$N$493) -> 9.2971825 | E11: =AVERAGE('DATOS LIMPIOS'!$M$5:$M$493) -> 29.186614
A12: Flash Sale | B12: =COUNTIF('DATOS LIMPIOS'!$B$5:$B$493,"Flash Sale") -> 81 | C12: =AVERAGEIF('DATOS LIMPIOS'!$B$5:$B$493,"Flash Sale",'DATOS LIMPIOS'!$M$5:$M$493) -> 29.440902 | D12: =AVERAGEIF('DATOS LIMPIOS'!$B$5:$B$493,"Flash Sale",'DATOS LIMPIOS'!$N$5:$N$493) -> 9.205166 | E12: =AVERAGE('DATOS LIMPIOS'!$M$5:$M$493) -> 29.186614
A13: Holiday Discounts | B13: =COUNTIF('DATOS LIMPIOS'!$B$5:$B$493,"Holiday Discounts") -> 79 | C13: =AVERAGEIF('DATOS LIMPIOS'!$B$5:$B$493,"Holiday Discounts",'DATOS LIMPIOS'!$M$5:$M$493) -> 30.711144 | D13: =AVERAGEIF('DATOS LIMPIOS'!$B$5:$B$493,"Holiday Discounts",'DATOS LIMPIOS'!$N$5:$N$493) -> 9.055774 | E13: =AVERAGE('DATOS LIMPIOS'!$M$5:$M$493) -> 29.186614
A14: New Product Launch | B14: =COUNTIF('DATOS LIMPIOS'!$B$5:$B$493,"New Product Launch") -> 84 | C14: =AVERAGEIF('DATOS LIMPIOS'!$B$5:$B$493,"New Product Launch",'DATOS LIMPIOS'!$M$5:$M$493) -> 29.458248 | D14: =AVERAGEIF('DATOS LIMPIOS'!$B$5:$B$493,"New Product Launch",'DATOS LIMPIOS'!$N$5:$N$493) -> 10.443531 | E14: =AVERAGE('DATOS LIMPIOS'!$M$5:$M$493) -> 29.186614
A15: Newsletter | B15: =COUNTIF('DATOS LIMPIOS'!$B$5:$B$493,"Newsletter") -> 93 | C15: =AVERAGEIF('DATOS LIMPIOS'!$B$5:$B$493,"Newsletter",'DATOS LIMPIOS'!$M$5:$M$493) -> 27.751365 | D15: =AVERAGEIF('DATOS LIMPIOS'!$B$5:$B$493,"Newsletter",'DATOS LIMPIOS'!$N$5:$N$493) -> 10.574097 | E15: =AVERAGE('DATOS LIMPIOS'!$M$5:$M$493) -> 29.186614
A17: ¿Cambia el resultado? No | D17: p = 0,211 (calculado en Python)
A28: H9 · ¿El objetivo de la campaña (vender, educar, lanzar, fidelizar) cambia el resultado?
A29: No. Los cuatro objetivos abren y clican parecido.
A32: Tabla H9 · Apertura y CTR por objetivo de la campaña
A33: Objetivo | B33: Campañas | C33: Apertura (%) | D33: CTR (%) | E33: Promedio general de apertura (%)
A34: Vender | B34: =COUNTIFS('DATOS LIMPIOS'!$Z$5:$Z$493,"Vender") -> 239 | C34: =AVERAGEIFS('DATOS LIMPIOS'!$M$5:$M$493,'DATOS LIMPIOS'!$Z$5:$Z$493,"Vender") -> 29.061037 | D34: =AVERAGEIFS('DATOS LIMPIOS'!$N$5:$N$493,'DATOS LIMPIOS'!$Z$5:$Z$493,"Vender") -> 9.1862009 | E34: =AVERAGE('DATOS LIMPIOS'!$M$5:$M$493) -> 29.186614
A35: Educar | B35: =COUNTIFS('DATOS LIMPIOS'!$Z$5:$Z$493,"Educar") -> 93 | C35: =AVERAGEIFS('DATOS LIMPIOS'!$M$5:$M$493,'DATOS LIMPIOS'!$Z$5:$Z$493,"Educar") -> 27.751365 | D35: =AVERAGEIFS('DATOS LIMPIOS'!$N$5:$N$493,'DATOS LIMPIOS'!$Z$5:$Z$493,"Educar") -> 10.574097 | E35: =AVERAGE('DATOS LIMPIOS'!$M$5:$M$493) -> 29.186614
A36: Lanzar | B36: =COUNTIFS('DATOS LIMPIOS'!$Z$5:$Z$493,"Lanzar") -> 84 | C36: =AVERAGEIFS('DATOS LIMPIOS'!$M$5:$M$493,'DATOS LIMPIOS'!$Z$5:$Z$493,"Lanzar") -> 29.458248 | D36: =AVERAGEIFS('DATOS LIMPIOS'!$N$5:$N$493,'DATOS LIMPIOS'!$Z$5:$Z$493,"Lanzar") -> 10.443531 | E36: =AVERAGE('DATOS LIMPIOS'!$M$5:$M$493) -> 29.186614
A37: Fidelizar | B37: =COUNTIFS('DATOS LIMPIOS'!$Z$5:$Z$493,"Fidelizar") -> 73 | C37: =AVERAGEIFS('DATOS LIMPIOS'!$M$5:$M$493,'DATOS LIMPIOS'!$Z$5:$Z$493,"Fidelizar") -> 31.113651 | D37: =AVERAGEIFS('DATOS LIMPIOS'!$N$5:$N$493,'DATOS LIMPIOS'!$Z$5:$Z$493,"Fidelizar") -> 9.9969928 | E37: =AVERAGE('DATOS LIMPIOS'!$M$5:$M$493) -> 29.186614
A39: ¿Cambia el resultado? No | D39: p = 0,357 (calculado en Python)
A52: H10 · ¿El tamaño del envío cambia cuántas personas abren?
A53: No. Las campañas pequeñas y las grandes abren casi igual.
A56: Tabla H10 · Apertura y CTR según el tamaño del envío
A57: Tamaño del envío | B57: Campañas | C57: Apertura (%) | D57: CTR (%) | E57: Promedio general de apertura (%)
A58: Menos de 100 mil | B58: =COUNTIFS('DATOS LIMPIOS'!$AA$5:$AA$493,"Menos de 100 mil") -> 98 | C58: =AVERAGEIFS('DATOS LIMPIOS'!$M$5:$M$493,'DATOS LIMPIOS'!$AA$5:$AA$493,"Menos de 100 mil") -> 29.980769 | D58: =AVERAGEIFS('DATOS LIMPIOS'!$N$5:$N$493,'DATOS LIMPIOS'!$AA$5:$AA$493,"Menos de 100 mil") -> 9.9605207 | E58: =AVERAGE('DATOS LIMPIOS'!$M$5:$M$493) -> 29.186614
A59: 100 a 200 mil | B59: =COUNTIFS('DATOS LIMPIOS'!$AA$5:$AA$493,"100 a 200 mil") -> 107 | C59: =AVERAGEIFS('DATOS LIMPIOS'!$M$5:$M$493,'DATOS LIMPIOS'!$AA$5:$AA$493,"100 a 200 mil") -> 29.609856 | D59: =AVERAGEIFS('DATOS LIMPIOS'!$N$5:$N$493,'DATOS LIMPIOS'!$AA$5:$AA$493,"100 a 200 mil") -> 9.6964825 | E59: =AVERAGE('DATOS LIMPIOS'!$M$5:$M$493) -> 29.186614
A60: 200 a 300 mil | B60: =COUNTIFS('DATOS LIMPIOS'!$AA$5:$AA$493,"200 a 300 mil") -> 90 | C60: =AVERAGEIFS('DATOS LIMPIOS'!$M$5:$M$493,'DATOS LIMPIOS'!$AA$5:$AA$493,"200 a 300 mil") -> 28.062716 | D60: =AVERAGEIFS('DATOS LIMPIOS'!$N$5:$N$493,'DATOS LIMPIOS'!$AA$5:$AA$493,"200 a 300 mil") -> 10.01458 | E60: =AVERAGE('DATOS LIMPIOS'!$M$5:$M$493) -> 29.186614
A61: 300 a 400 mil | B61: =COUNTIFS('DATOS LIMPIOS'!$AA$5:$AA$493,"300 a 400 mil") -> 100 | C61: =AVERAGEIFS('DATOS LIMPIOS'!$M$5:$M$493,'DATOS LIMPIOS'!$AA$5:$AA$493,"300 a 400 mil") -> 28.693134 | D61: =AVERAGEIFS('DATOS LIMPIOS'!$N$5:$N$493,'DATOS LIMPIOS'!$AA$5:$AA$493,"300 a 400 mil") -> 9.6839603 | E61: =AVERAGE('DATOS LIMPIOS'!$M$5:$M$493) -> 29.186614
A62: Más de 400 mil | B62: =COUNTIFS('DATOS LIMPIOS'!$AA$5:$AA$493,"Más de 400 mil") -> 94 | C62: =AVERAGEIFS('DATOS LIMPIOS'!$M$5:$M$493,'DATOS LIMPIOS'!$AA$5:$AA$493,"Más de 400 mil") -> 29.477939 | D62: =AVERAGEIFS('DATOS LIMPIOS'!$N$5:$N$493,'DATOS LIMPIOS'!$AA$5:$AA$493,"Más de 400 mil") -> 9.6017791 | E62: =AVERAGE('DATOS LIMPIOS'!$M$5:$M$493) -> 29.186614
A64: ¿Cambia el resultado? No | D64: p = 0,832 (calculado en Python)
A76: H11 · ¿Repetir el mismo asunto lo desgasta?
A77: No. En los asuntos usados 8 o más veces, el primer tercio de sus usos y el último abren igual. Repetir un asunto que gana no lo gasta.
A80: Tabla H11 · Apertura y CTR según el momento de uso del asunto (asuntos usados 8 o más veces)
A81: Momento de uso | B81: Campañas | C81: Apertura (%) | D81: CTR (%) | E81: Promedio general de apertura (%)
A82: Primer tercio | B82: =COUNTIFS('DATOS LIMPIOS'!$AD$5:$AD$493,"Primer tercio") -> 122 | C82: =AVERAGEIFS('DATOS LIMPIOS'!$M$5:$M$493,'DATOS LIMPIOS'!$AD$5:$AD$493,"Primer tercio") -> 30.869712 | D82: =AVERAGEIFS('DATOS LIMPIOS'!$N$5:$N$493,'DATOS LIMPIOS'!$AD$5:$AD$493,"Primer tercio") -> 9.9926913 | E82: =AVERAGE('DATOS LIMPIOS'!$M$5:$M$493) -> 29.186614
A83: Medio | B83: =COUNTIFS('DATOS LIMPIOS'!$AD$5:$AD$493,"Medio") -> 129 | C83: =AVERAGEIFS('DATOS LIMPIOS'!$M$5:$M$493,'DATOS LIMPIOS'!$AD$5:$AD$493,"Medio") -> 28.891211 | D83: =AVERAGEIFS('DATOS LIMPIOS'!$N$5:$N$493,'DATOS LIMPIOS'!$AD$5:$AD$493,"Medio") -> 9.4437399 | E83: =AVERAGE('DATOS LIMPIOS'!$M$5:$M$493) -> 29.186614
A84: Último tercio | B84: =COUNTIFS('DATOS LIMPIOS'!$AD$5:$AD$493,"Último tercio") -> 138 | C84: =AVERAGEIFS('DATOS LIMPIOS'!$M$5:$M$493,'DATOS LIMPIOS'!$AD$5:$AD$493,"Último tercio") -> 30.56545 | D84: =AVERAGEIFS('DATOS LIMPIOS'!$N$5:$N$493,'DATOS LIMPIOS'!$AD$5:$AD$493,"Último tercio") -> 10.257871 | E84: =AVERAGE('DATOS LIMPIOS'!$M$5:$M$493) -> 29.186614
A86: ¿Cambia el resultado? No | D86: p = 0,449 (calculado en Python)
A100: H12 · ¿Los ingresos y la conversión suben con los clics?
A101: No, y eso es una alerta: en una operación real los ingresos suben con los clics. Aquí la correlación es casi cero, así que la atribución de ventas del archivo no es confiable y no se evalúan campañas por ventas.
A104: Tabla H12 · Correlación entre ventas y actividad de la campaña (0 = no se mueven juntas)
A105: Relación | B105: Correlación (r)
A106: Ingresos vs clics | B106: =CORREL('DATOS LIMPIOS'!$I$5:$I$493,'DATOS LIMPIOS'!$L$5:$L$493) -> 0.037675972
A107: Ingresos vs correos enviados | B107: =CORREL('DATOS LIMPIOS'!$G$5:$G$493,'DATOS LIMPIOS'!$L$5:$L$493) -> 0.026256943
A108: Conversión vs clics | B108: =CORREL('DATOS LIMPIOS'!$I$5:$I$493,'DATOS LIMPIOS'!$J$5:$J$493) -> -0.021998604
A109: Desuscripción vs correos enviados | B109: =CORREL('DATOS LIMPIOS'!$G$5:$G$493,'DATOS LIMPIOS'!$K$5:$K$493) -> -0.0064832279
A111: ¿Cambia el resultado? No | D111: p = 0,406 (calculado en Python)

Sheet H3 ASUNTO
A1: El hallazgo principal · el asunto decide cuántas personas abren
A2: Las pruebas de que el asunto importa, y de cómo es un asunto que gana.
A4: H13 · ¿Qué explica más la apertura?
A5: El asunto explica casi la mitad de por qué unas campañas abren más que otras. El tipo de campaña, la hora, el día y el mes no llegan al 2 % cada uno.
A8: Tabla H13 · Qué parte de la diferencia en apertura explica cada factor
A9: Factor | B9: % que explica
A10: El asunto | B10: =(SUMPRODUCT(('DATOS LIMPIOS'!$M$5:$M$493-AVERAGE('DATOS LIMPIOS'!$M$5:$M$493))^2)-SUMPRODUCT(('DATOS LIMPIOS'!$M$5:$M$493-'DATOS LIMPIOS'!$Q$5:$Q$493)^2))/SUMPRODUCT(('DATOS LIMPIOS'!$M$5:$M$493-AVERAGE('DATOS LIMPIOS'!$M$5:$M$493))^2)*100 -> 47.410372
A11: El tipo de campaña | B11: =(SUMPRODUCT(('DATOS LIMPIOS'!$M$5:$M$493-AVERAGE('DATOS LIMPIOS'!$M$5:$M$493))^2)-SUMPRODUCT(('DATOS LIMPIOS'!$M$5:$M$493-'DATOS LIMPIOS'!$R$5:$R$493)^2))/SUMPRODUCT(('DATOS LIMPIOS'!$M$5:$M$493-AVERAGE('DATOS LIMPIOS'!$M$5:$M$493))^2)*100 -> 1.3828802
A12: La hora | B12: =SUMPRODUCT((AVERAGEIF('DATOS LIMPIOS'!$V$5:$V$493,'DATOS LIMPIOS'!$V$5:$V$493,'DATOS LIMPIOS'!$M$5:$M$493)-AVERAGE('DATOS LIMPIOS'!$M$5:$M$493))^2)/SUMPRODUCT(('DATOS LIMPIOS'!$M$5:$M$493-AVERAGE('DATOS LIMPIOS'!$M$5:$M$493))^2)*100 -> 1.0467798
A13: El día de la semana | B13: =SUMPRODUCT((AVERAGEIF('DATOS LIMPIOS'!$U$5:$U$493,'DATOS LIMPIOS'!$U$5:$U$493,'DATOS LIMPIOS'!$M$5:$M$493)-AVERAGE('DATOS LIMPIOS'!$M$5:$M$493))^2)/SUMPRODUCT(('DATOS LIMPIOS'!$M$5:$M$493-AVERAGE('DATOS LIMPIOS'!$M$5:$M$493))^2)*100 -> 0.52913858
A14: El mes | B14: =SUMPRODUCT((AVERAGEIF('DATOS LIMPIOS'!$T$5:$T$493,'DATOS LIMPIOS'!$T$5:$T$493,'DATOS LIMPIOS'!$M$5:$M$493)-AVERAGE('DATOS LIMPIOS'!$M$5:$M$493))^2)/SUMPRODUCT(('DATOS LIMPIOS'!$M$5:$M$493-AVERAGE('DATOS LIMPIOS'!$M$5:$M$493))^2)*100 -> 0.09407893
A15: El momento del mes | B15: =SUMPRODUCT((AVERAGEIF('DATOS LIMPIOS'!$W$5:$W$493,'DATOS LIMPIOS'!$W$5:$W$493,'DATOS LIMPIOS'!$M$5:$M$493)-AVERAGE('DATOS LIMPIOS'!$M$5:$M$493))^2)/SUMPRODUCT(('DATOS LIMPIOS'!$M$5:$M$493-AVERAGE('DATOS LIMPIOS'!$M$5:$M$493))^2)*100 -> 0.17975665
A17: ¿Cambia el resultado? Sí | D17: p = < 0,001 (calculado en Python)
A28: H14 · ¿El efecto del asunto es real o es suerte?
A29: Es real. Con dos meses se eligieron los 5 asuntos que más abrían y los 5 que menos, y se miró el tercer mes, que no se usó para elegir. Se hizo tres veces, una con cada mes. Si fuera suerte, los grupos se habrían acercado; siguieron igual de separados.
A32: Tabla H14 · Apertura en el mes de prueba de los 5 asuntos que ganaban y los 5 que perdían
A33: Mes de prueba | B33: Los 5 que ganaban | C33: Los 5 que perdían
A34: Prueba en agosto | B34: =SUMIFS(_calculos!$T$4:$T$69,_calculos!$S$4:$S$69,"5 mejores")/SUMIFS(_calculos!$U$4:$U$69,_calculos!$S$4:$S$69,"5 mejores") -> 39.033107 | C34: =SUMIFS(_calculos!$T$4:$T$69,_calculos!$S$4:$S$69,"5 peores")/SUMIFS(_calculos!$U$4:$U$69,_calculos!$S$4:$S$69,"5 peores") -> 20.596391
A35: Prueba en septiembre | B35: =SUMIFS(_calculos!$AB$4:$AB$69,_calculos!$AA$4:$AA$69,"5 mejores")/SUMIFS(_calculos!$AC$4:$AC$69,_calculos!$AA$4:$AA$69,"5 mejores") -> 38.936539 | C35: =SUMIFS(_calculos!$AB$4:$AB$69,_calculos!$AA$4:$AA$69,"5 peores")/SUMIFS(_calculos!$AC$4:$AC$69,_calculos!$AA$4:$AA$69,"5 peores") -> 16.313814
A36: Prueba en octubre | B36: =SUMIFS(_calculos!$AJ$4:$AJ$69,_calculos!$AI$4:$AI$69,"5 mejores")/SUMIFS(_calculos!$AK$4:$AK$69,_calculos!$AI$4:$AI$69,"5 mejores") -> 39.55018 | C36: =SUMIFS(_calculos!$AJ$4:$AJ$69,_calculos!$AI$4:$AI$69,"5 peores")/SUMIFS(_calculos!$AK$4:$AK$69,_calculos!$AI$4:$AI$69,"5 peores") -> 16.525879
A38: ¿Cambia el resultado? Sí
A52: H15 · ¿Qué estilo de asunto abre más: con cifra, recompensa, solo urgencia o pregunta?
A53: El asunto con una cifra concreta ("Hasta 50%") es el que más abre. Los de recompensa o sorpresa quedan en el promedio. Los que solo meten urgencia sin decir qué recibes ("¡Últimas horas!", "Por tiempo limitado") y la pregunta abierta son los que menos abren.
A56: Tabla H15 · Apertura y CTR según el estilo del asunto
A57: Estilo | B57: Campañas | C57: Apertura (%) | D57: CTR (%)
A58: Con cifra concreta | B58: =COUNTIF('DATOS LIMPIOS'!$AT$5:$AT$493,"Con cifra concreta") -> 21 | C58: =AVERAGEIF('DATOS LIMPIOS'!$AT$5:$AT$493,"Con cifra concreta",'DATOS LIMPIOS'!$M$5:$M$493) -> 41.593593 | D58: =AVERAGEIF('DATOS LIMPIOS'!$AT$5:$AT$493,"Con cifra concreta",'DATOS LIMPIOS'!$N$5:$N$493) -> 10.640008
A59: Recompensa o sorpresa | B59: =COUNTIF('DATOS LIMPIOS'!$AT$5:$AT$493,"Recompensa o sorpresa") -> 130 | C59: =AVERAGEIF('DATOS LIMPIOS'!$AT$5:$AT$493,"Recompensa o sorpresa",'DATOS LIMPIOS'!$M$5:$M$493) -> 29.134331 | D59: =AVERAGEIF('DATOS LIMPIOS'!$AT$5:$AT$493,"Recompensa o sorpresa",'DATOS LIMPIOS'!$N$5:$N$493) -> 9.5944867
A60: Otro: beneficio o novedad | B60: =COUNTIF('DATOS LIMPIOS'!$AT$5:$AT$493,"Otro: beneficio o novedad") -> 267 | C60: =AVERAGEIF('DATOS LIMPIOS'!$AT$5:$AT$493,"Otro: beneficio o novedad",'DATOS LIMPIOS'!$M$5:$M$493) -> 30.545098 | D60: =AVERAGEIF('DATOS LIMPIOS'!$AT$5:$AT$493,"Otro: beneficio o novedad",'DATOS LIMPIOS'!$N$5:$N$493) -> 10.270903
A61: Solo urgencia, sin cifra | B61: =COUNTIF('DATOS LIMPIOS'!$AT$5:$AT$493,"Solo urgencia, sin cifra") -> 61 | C61: =AVERAGEIF('DATOS LIMPIOS'!$AT$5:$AT$493,"Solo urgencia, sin cifra",'DATOS LIMPIOS'!$M$5:$M$493) -> 21.257416 | D61: =AVERAGEIF('DATOS LIMPIOS'!$AT$5:$AT$493,"Solo urgencia, sin cifra",'DATOS LIMPIOS'!$N$5:$N$493) -> 8.0652297
A62: Pregunta abierta | B62: =COUNTIF('DATOS LIMPIOS'!$AT$5:$AT$493,"Pregunta abierta") -> 10 | C62: =AVERAGEIF('DATOS LIMPIOS'!$AT$5:$AT$493,"Pregunta abierta",'DATOS LIMPIOS'!$M$5:$M$493) -> 15.908214 | D62: =AVERAGEIF('DATOS LIMPIOS'!$AT$5:$AT$493,"Pregunta abierta",'DATOS LIMPIOS'!$N$5:$N$493) -> 8.089655
A64: ¿Cambia el resultado? Sí | D64: p = < 0,001 (calculado en Python)
A65: Cómo se clasifica (columna AT de DATOS LIMPIOS, en este orden): si tiene un número es "con cifra"; si tiene signo de pregunta, "pregunta"; si tiene palabras de urgencia, "solo urgencia"; si habla de recompensa, regalo o sorpresa, "recompensa". Ojo: "con cifra" es un solo asunto y "pregunta" otro, así que son señales. "Solo urgencia" sí se sostiene comparando asunto por asunto dentro del mismo tipo (p = 0,008).
A76: H16 · ¿Empezar el asunto con una etiqueta ("Actualización", "Presentamos", "Oportunidades") resta?
A77: Sí, y mucho, en los tres meses. Esos asuntos dicen qué tipo de correo es, pero no qué hay adentro. Las palabras que cuentan como etiqueta están en la fórmula de la columna AH de DATOS LIMPIOS.
A80: Tabla H16 · Apertura de asuntos que dicen qué recibes contra los que empiezan con una etiqueta, por mes
A81: Mes | B81: Dice qué recibes | C81: Empieza con etiqueta
A82: Agosto | B82: =AVERAGEIFS('DATOS LIMPIOS'!$M$5:$M$493,'DATOS LIMPIOS'!$T$5:$T$493,"Agosto",'DATOS LIMPIOS'!$AH$5:$AH$493,"No") -> 32.555382 | C82: =AVERAGEIFS('DATOS LIMPIOS'!$M$5:$M$493,'DATOS LIMPIOS'!$T$5:$T$493,"Agosto",'DATOS LIMPIOS'!$AH$5:$AH$493,"Sí") -> 22.687529
A83: Septiembre | B83: =AVERAGEIFS('DATOS LIMPIOS'!$M$5:$M$493,'DATOS LIMPIOS'!$T$5:$T$493,"Septiembre",'DATOS LIMPIOS'!$AH$5:$AH$493,"No") -> 32.87815 | C83: =AVERAGEIFS('DATOS LIMPIOS'!$M$5:$M$493,'DATOS LIMPIOS'!$T$5:$T$493,"Septiembre",'DATOS LIMPIOS'!$AH$5:$AH$493,"Sí") -> 16.127339
A84: Octubre | B84: =AVERAGEIFS('DATOS LIMPIOS'!$M$5:$M$493,'DATOS LIMPIOS'!$T$5:$T$493,"Octubre",'DATOS LIMPIOS'!$AH$5:$AH$493,"No") -> 33.164494 | C84: =AVERAGEIFS('DATOS LIMPIOS'!$M$5:$M$493,'DATOS LIMPIOS'!$T$5:$T$493,"Octubre",'DATOS LIMPIOS'!$AH$5:$AH$493,"Sí") -> 19.532131
A86: ¿Cambia el resultado? Sí | D86: p = < 0,001 (calculado en Python)
A100: H17 · ¿Un preheader vago resta?
A101: Sí. Un preheader que se refiere a algo sin nombrarlo ("estas ofertas", "algo especial para ti") abre bastante menos que uno que dice qué hay.
A104: Tabla H17 · Apertura y CTR según el preheader
A105: Tipo de preheader | B105: Campañas | C105: Apertura (%) | D105: CTR (%)
A106: Preheader que concreta | B106: =COUNTIF('DATOS LIMPIOS'!$AN$5:$AN$493,"No") -> 428 | C106: =AVERAGEIF('DATOS LIMPIOS'!$AN$5:$AN$493,"No",'DATOS LIMPIOS'!$M$5:$M$493) -> 30.577433 | D106: =AVERAGEIF('DATOS LIMPIOS'!$AN$5:$AN$493,"No",'DATOS LIMPIOS'!$N$5:$N$493) -> 9.9521412
A107: Preheader vago ("estas ofertas", "algo especial") | B107: =COUNTIF('DATOS LIMPIOS'!$AN$5:$AN$493,"Sí") -> 61 | C107: =AVERAGEIF('DATOS LIMPIOS'!$AN$5:$AN$493,"Sí",'DATOS LIMPIOS'!$M$5:$M$493) -> 19.428075 | D107: =AVERAGEIF('DATOS LIMPIOS'!$AN$5:$AN$493,"Sí",'DATOS LIMPIOS'!$N$5:$N$493) -> 8.6297328
A109: ¿Cambia el resultado? Sí | D109: p = < 0,001 (calculado en Python)
A124: H18 · ¿Se ve en ejemplos concretos?
A125: Sí. Tres pares del mismo tipo de campaña (lanzamiento, newsletter y fidelización): en cada uno gana el que dice qué recibes.
A128: Tabla H18 · Apertura de tres pares de asuntos del mismo tipo de campaña (lanzamiento, newsletter y fidelización)
A129: Asunto | B129: Campañas | C129: Apertura (%)
A130: ¡El futuro de tu piel ha llegado! Nuevo Producto revolucionario | B130: =COUNTIF('DATOS LIMPIOS'!$E$5:$E$493,A130) -> 25 | C130: =AVERAGEIF('DATOS LIMPIOS'!$E$5:$E$493,A130,'DATOS LIMPIOS'!$M$5:$M$493) -> 36.132518
A131: Presentamos: Nuestro último lanzamiento de belleza ¡Imperdible! | B131: =COUNTIF('DATOS LIMPIOS'!$E$5:$E$493,A131) -> 33 | C131: =AVERAGEIF('DATOS LIMPIOS'!$E$5:$E$493,A131,'DATOS LIMPIOS'!$M$5:$M$493) -> 23.315841
A132: Lo último en L'Oréal: Mantente informad@ de las novedades | B132: =COUNTIF('DATOS LIMPIOS'!$E$5:$E$493,A132) -> 19 | C132: =AVERAGEIF('DATOS LIMPIOS'!$E$5:$E$493,A132,'DATOS LIMPIOS'!$M$5:$M$493) -> 36.827379
A133: Actualización de L'Oréal: ¿Qué hay de nuevo en el mundo beauty? | B133: =COUNTIF('DATOS LIMPIOS'!$E$5:$E$493,A133) -> 10 | C133: =AVERAGEIF('DATOS LIMPIOS'!$E$5:$E$493,A133,'DATOS LIMPIOS'!$M$5:$M$493) -> 15.908214
A134: ¡Tu lealtad tiene recompensa! Descúbrela, sorpresas para ti | B134: =COUNTIF('DATOS LIMPIOS'!$E$5:$E$493,A134) -> 16 | C134: =AVERAGEIF('DATOS LIMPIOS'!$E$5:$E$493,A134,'DATOS LIMPIOS'!$M$5:$M$493) -> 40.721428
A135: ¡Un pequeño detalle para agradecerte tu lealtad! L'Oréal | B135: =COUNTIF('DATOS LIMPIOS'!$E$5:$E$493,A135) -> 14 | C135: =AVERAGEIF('DATOS LIMPIOS'!$E$5:$E$493,A135,'DATOS LIMPIOS'!$M$5:$M$493) -> 20.724632
A137: ¿Cambia el resultado? Sí
A148: H19 · ¿Los asuntos que se abren también reciben clics?
A149: Sí. El asunto que abre bien casi siempre clica bien. No hay que elegir entre optimizar aperturas o clics.
A152: Tabla H19 · Relación entre la apertura y el CTR de los asuntos usados 8 o más veces
A153: Medida | B153: Valor
A154: Correlación entre apertura y CTR (asuntos usados 8+ veces) | B154: =CORREL(_calculos!C73:C94,_calculos!D73:D94) -> 0.73892623
A155: Asuntos en la gráfica | B155: =COUNT(_calculos!C73:C94) -> 22
A157: ¿Cambia el resultado? Sí | D157: p = < 0,001 (calculado en Python)
A172: H20 · ¿Cumplir las buenas prácticas de Mailchimp (máximo 60 caracteres, 9 palabras, 3 signos y 1 emoji) sube la apertura?
A173: No en estos datos. El largo y la puntuación no deciden. Lo que sí coincide con Mailchimp es su consejo de ser concreto y no genérico, que es justo lo que muestra H14.
A176: Tabla H20 · Apertura y CTR según si el asunto cumple las reglas de Mailchimp
A177: Asunto | B177: Campañas | C177: Apertura (%) | D177: CTR (%)
A178: Cumple las reglas de Mailchimp | B178: =COUNTIF('DATOS LIMPIOS'!$AR$5:$AR$493,"Sí") -> 263 | C178: =AVERAGEIF('DATOS LIMPIOS'!$AR$5:$AR$493,"Sí",'DATOS LIMPIOS'!$M$5:$M$493) -> 28.350908 | D178: =AVERAGEIF('DATOS LIMPIOS'!$AR$5:$AR$493,"Sí",'DATOS LIMPIOS'!$N$5:$N$493) -> 9.2991465
A179: No las cumple | B179: =COUNTIF('DATOS LIMPIOS'!$AR$5:$AR$493,"No") -> 226 | C179: =AVERAGEIF('DATOS LIMPIOS'!$AR$5:$AR$493,"No",'DATOS LIMPIOS'!$M$5:$M$493) -> 30.159138 | D179: =AVERAGEIF('DATOS LIMPIOS'!$AR$5:$AR$493,"No",'DATOS LIMPIOS'!$N$5:$N$493) -> 10.355109
A181: ¿Cambia el resultado? No | D181: p = 0,525 (calculado en Python)
A182: Fuente de las reglas: mailchimp.com/help/best-practices-for-email-subject-lines

Sheet H4 TEMÁTICA HOT SALE
A1: Campañas con temática Hot Sale · descuentos, tiempo límite y Flash Sale
A2: Lo más cercano a la campaña que vamos a proponer: los correos de descuento, cómo usan el tiempo límite y cómo les fue a los Hot Sale anteriores.
A4: Qué campañas se parecen a un Hot Sale: las que hablan de descuento en el asunto o en el preheader. Son 287 de las 489. Los bloques H21 a H25 miran solo esas campañas; los siguientes, el límite de tiempo y los Hot Sale anteriores.
A7: H21 · En las campañas de descuento, ¿qué tipo de campaña funciona mejor?
A8: Aquí sí hay diferencias entre tipos: los correos de agradecimiento con descuento abren más que las ofertas exclusivas. Pero el asunto explica mucho más: el 54 % de la diferencia, contra el 5 % del tipo.
A11: Tabla H21 · Campañas de descuento: apertura y CTR por tipo de campaña
A12: Tipo | B12: Campañas | C12: Apertura (%) | D12: CTR (%)
A13: Customer Appreciation | B13: =COUNTIFS('DATOS LIMPIOS'!$B$5:$B$493,"Customer Appreciation",'DATOS LIMPIOS'!$AI$5:$AI$493,"Sí") -> 48 | C13: =AVERAGEIFS('DATOS LIMPIOS'!$M$5:$M$493,'DATOS LIMPIOS'!$B$5:$B$493,"Customer Appreciation",'DATOS LIMPIOS'!$AI$5:$AI$493,"Sí") -> 35.67256 | D13: =AVERAGEIFS('DATOS LIMPIOS'!$N$5:$N$493,'DATOS LIMPIOS'!$B$5:$B$493,"Customer Appreciation",'DATOS LIMPIOS'!$AI$5:$AI$493,"Sí") -> 10.752666
A14: Exclusive Offers | B14: =COUNTIFS('DATOS LIMPIOS'!$B$5:$B$493,"Exclusive Offers",'DATOS LIMPIOS'!$AI$5:$AI$493,"Sí") -> 79 | C14: =AVERAGEIFS('DATOS LIMPIOS'!$M$5:$M$493,'DATOS LIMPIOS'!$B$5:$B$493,"Exclusive Offers",'DATOS LIMPIOS'!$AI$5:$AI$493,"Sí") -> 27.021448 | D14: =AVERAGEIFS('DATOS LIMPIOS'!$N$5:$N$493,'DATOS LIMPIOS'!$B$5:$B$493,"Exclusive Offers",'DATOS LIMPIOS'!$AI$5:$AI$493,"Sí") -> 9.2971825
A15: Flash Sale | B15: =COUNTIFS('DATOS LIMPIOS'!$B$5:$B$493,"Flash Sale",'DATOS LIMPIOS'!$AI$5:$AI$493,"Sí") -> 81 | C15: =AVERAGEIFS('DATOS LIMPIOS'!$M$5:$M$493,'DATOS LIMPIOS'!$B$5:$B$493,"Flash Sale",'DATOS LIMPIOS'!$AI$5:$AI$493,"Sí") -> 29.440902 | D15: =AVERAGEIFS('DATOS LIMPIOS'!$N$5:$N$493,'DATOS LIMPIOS'!$B$5:$B$493,"Flash Sale",'DATOS LIMPIOS'!$AI$5:$AI$493,"Sí") -> 9.205166
A16: Holiday Discounts | B16: =COUNTIFS('DATOS LIMPIOS'!$B$5:$B$493,"Holiday Discounts",'DATOS LIMPIOS'!$AI$5:$AI$493,"Sí") -> 79 | C16: =AVERAGEIFS('DATOS LIMPIOS'!$M$5:$M$493,'DATOS LIMPIOS'!$B$5:$B$493,"Holiday Discounts",'DATOS LIMPIOS'!$AI$5:$AI$493,"Sí") -> 30.711144 | D16: =AVERAGEIFS('DATOS LIMPIOS'!$N$5:$N$493,'DATOS LIMPIOS'!$B$5:$B$493,"Holiday Discounts",'DATOS LIMPIOS'!$AI$5:$AI$493,"Sí") -> 9.055774
A18: ¿Cambia el resultado? Sí | D18: p = 0,002 (calculado en Python)
A31: H22 · En las campañas de descuento, ¿qué estilo de asunto funciona?
A32: El mismo patrón que en general, pero más marcado: el descuento con cifra es lo que más abre y el descuento con pura urgencia es lo que menos. Para un Hot Sale, el asunto tiene que decir cuánto y en qué.
A35: Tabla H22 · Campañas de descuento: apertura y CTR según el estilo del asunto
A36: Estilo | B36: Campañas | C36: Apertura (%) | D36: CTR (%)
A37: Con cifra concreta | B37: =COUNTIFS('DATOS LIMPIOS'!$AT$5:$AT$493,"Con cifra concreta",'DATOS LIMPIOS'!$AI$5:$AI$493,"Sí") -> 21 | C37: =AVERAGEIFS('DATOS LIMPIOS'!$M$5:$M$493,'DATOS LIMPIOS'!$AT$5:$AT$493,"Con cifra concreta",'DATOS LIMPIOS'!$AI$5:$AI$493,"Sí") -> 41.593593 | D37: =AVERAGEIFS('DATOS LIMPIOS'!$N$5:$N$493,'DATOS LIMPIOS'!$AT$5:$AT$493,"Con cifra concreta",'DATOS LIMPIOS'!$AI$5:$AI$493,"Sí") -> 10.640008
A38: Recompensa o sorpresa | B38: =COUNTIFS('DATOS LIMPIOS'!$AT$5:$AT$493,"Recompensa o sorpresa",'DATOS LIMPIOS'!$AI$5:$AI$493,"Sí") -> 110 | C38: =AVERAGEIFS('DATOS LIMPIOS'!$M$5:$M$493,'DATOS LIMPIOS'!$AT$5:$AT$493,"Recompensa o sorpresa",'DATOS LIMPIOS'!$AI$5:$AI$493,"Sí") -> 30.707806 | D38: =AVERAGEIFS('DATOS LIMPIOS'!$N$5:$N$493,'DATOS LIMPIOS'!$AT$5:$AT$493,"Recompensa o sorpresa",'DATOS LIMPIOS'!$AI$5:$AI$493,"Sí") -> 9.9172538
A39: Otro: beneficio o novedad | B39: =COUNTIFS('DATOS LIMPIOS'!$AT$5:$AT$493,"Otro: beneficio o novedad",'DATOS LIMPIOS'!$AI$5:$AI$493,"Sí") -> 95 | C39: =AVERAGEIFS('DATOS LIMPIOS'!$M$5:$M$493,'DATOS LIMPIOS'!$AT$5:$AT$493,"Otro: beneficio o novedad",'DATOS LIMPIOS'!$AI$5:$AI$493,"Sí") -> 32.735202 | D39: =AVERAGEIFS('DATOS LIMPIOS'!$N$5:$N$493,'DATOS LIMPIOS'!$AT$5:$AT$493,"Otro: beneficio o novedad",'DATOS LIMPIOS'!$AI$5:$AI$493,"Sí") -> 9.5296091
A40: Solo urgencia, sin cifra | B40: =COUNTIFS('DATOS LIMPIOS'!$AT$5:$AT$493,"Solo urgencia, sin cifra",'DATOS LIMPIOS'!$AI$5:$AI$493,"Sí") -> 61 | C40: =AVERAGEIFS('DATOS LIMPIOS'!$M$5:$M$493,'DATOS LIMPIOS'!$AT$5:$AT$493,"Solo urgencia, sin cifra",'DATOS LIMPIOS'!$AI$5:$AI$493,"Sí") -> 21.257416 | D40: =AVERAGEIFS('DATOS LIMPIOS'!$N$5:$N$493,'DATOS LIMPIOS'!$AT$5:$AT$493,"Solo urgencia, sin cifra",'DATOS LIMPIOS'!$AI$5:$AI$493,"Sí") -> 8.0652297
A42: ¿Cambia el resultado? Sí | D42: p = < 0,001 (calculado en Python)
A55: H23 · En las campañas de descuento, ¿importan las fechas de pago (quincena)?
A56: No. Aunque uno pensaría que los descuentos funcionan mejor cuando la gente recibe su sueldo, en estos datos la quincena no cambia cuántas personas abren un correo de descuento.
A59: Tabla H23 · Campañas de descuento: apertura y CTR según el momento del mes
A60: Momento del mes | B60: Campañas | C60: Apertura (%) | D60: CTR (%)
A61: Quincena | B61: =COUNTIFS('DATOS LIMPIOS'!$W$5:$W$493,"Quincena",'DATOS LIMPIOS'!$AI$5:$AI$493,"Sí") -> 59 | C61: =AVERAGEIFS('DATOS LIMPIOS'!$M$5:$M$493,'DATOS LIMPIOS'!$W$5:$W$493,"Quincena",'DATOS LIMPIOS'!$AI$5:$AI$493,"Sí") -> 28.696124 | D61: =AVERAGEIFS('DATOS LIMPIOS'!$N$5:$N$493,'DATOS LIMPIOS'!$W$5:$W$493,"Quincena",'DATOS LIMPIOS'!$AI$5:$AI$493,"Sí") -> 8.6609899
A62: Días después del pago | B62: =COUNTIFS('DATOS LIMPIOS'!$W$5:$W$493,"Días después del pago",'DATOS LIMPIOS'!$AI$5:$AI$493,"Sí") -> 78 | C62: =AVERAGEIFS('DATOS LIMPIOS'!$M$5:$M$493,'DATOS LIMPIOS'!$W$5:$W$493,"Días después del pago",'DATOS LIMPIOS'!$AI$5:$AI$493,"Sí") -> 30.9985 | D62: =AVERAGEIFS('DATOS LIMPIOS'!$N$5:$N$493,'DATOS LIMPIOS'!$W$5:$W$493,"Días después del pago",'DATOS LIMPIOS'!$AI$5:$AI$493,"Sí") -> 9.4686403
A63: Resto del mes | B63: =COUNTIFS('DATOS LIMPIOS'!$W$5:$W$493,"Resto del mes",'DATOS LIMPIOS'!$AI$5:$AI$493,"Sí") -> 150 | C63: =AVERAGEIFS('DATOS LIMPIOS'!$M$5:$M$493,'DATOS LIMPIOS'!$W$5:$W$493,"Resto del mes",'DATOS LIMPIOS'!$AI$5:$AI$493,"Sí") -> 30.312776 | D63: =AVERAGEIFS('DATOS LIMPIOS'!$N$5:$N$493,'DATOS LIMPIOS'!$W$5:$W$493,"Resto del mes",'DATOS LIMPIOS'!$AI$5:$AI$493,"Sí") -> 9.7471841
A65: ¿Cambia el resultado? No | D65: p = 0,613 (calculado en Python)
A79: H24 · En las campañas de descuento, ¿importa el día de la semana?
A80: No. Ningún día de la semana hace que un correo de descuento abra más.
A83: Tabla H24 · Campañas de descuento: apertura y CTR por día de la semana
A84: Día | B84: Campañas | C84: Apertura (%) | D84: CTR (%)
A85: Lunes | B85: =COUNTIFS('DATOS LIMPIOS'!$U$5:$U$493,"Lunes",'DATOS LIMPIOS'!$AI$5:$AI$493,"Sí") -> 62 | C85: =AVERAGEIFS('DATOS LIMPIOS'!$M$5:$M$493,'DATOS LIMPIOS'!$U$5:$U$493,"Lunes",'DATOS LIMPIOS'!$AI$5:$AI$493,"Sí") -> 32.188424 | D85: =AVERAGEIFS('DATOS LIMPIOS'!$N$5:$N$493,'DATOS LIMPIOS'!$U$5:$U$493,"Lunes",'DATOS LIMPIOS'!$AI$5:$AI$493,"Sí") -> 9.7230436
A86: Martes | B86: =COUNTIFS('DATOS LIMPIOS'!$U$5:$U$493,"Martes",'DATOS LIMPIOS'!$AI$5:$AI$493,"Sí") -> 61 | C86: =AVERAGEIFS('DATOS LIMPIOS'!$M$5:$M$493,'DATOS LIMPIOS'!$U$5:$U$493,"Martes",'DATOS LIMPIOS'!$AI$5:$AI$493,"Sí") -> 29.75947 | D86: =AVERAGEIFS('DATOS LIMPIOS'!$N$5:$N$493,'DATOS LIMPIOS'!$U$5:$U$493,"Martes",'DATOS LIMPIOS'!$AI$5:$AI$493,"Sí") -> 9.9026915
A87: Miércoles | B87: =COUNTIFS('DATOS LIMPIOS'!$U$5:$U$493,"Miércoles",'DATOS LIMPIOS'!$AI$5:$AI$493,"Sí") -> 51 | C87: =AVERAGEIFS('DATOS LIMPIOS'!$M$5:$M$493,'DATOS LIMPIOS'!$U$5:$U$493,"Miércoles",'DATOS LIMPIOS'!$AI$5:$AI$493,"Sí") -> 31.232565 | D87: =AVERAGEIFS('DATOS LIMPIOS'!$N$5:$N$493,'DATOS LIMPIOS'!$U$5:$U$493,"Miércoles",'DATOS LIMPIOS'!$AI$5:$AI$493,"Sí") -> 9.7460809
A88: Jueves | B88: =COUNTIFS('DATOS LIMPIOS'!$U$5:$U$493,"Jueves",'DATOS LIMPIOS'!$AI$5:$AI$493,"Sí") -> 40 | C88: =AVERAGEIFS('DATOS LIMPIOS'!$M$5:$M$493,'DATOS LIMPIOS'!$U$5:$U$493,"Jueves",'DATOS LIMPIOS'!$AI$5:$AI$493,"Sí") -> 30.176602 | D88: =AVERAGEIFS('DATOS LIMPIOS'!$N$5:$N$493,'DATOS LIMPIOS'!$U$5:$U$493,"Jueves",'DATOS LIMPIOS'!$AI$5:$AI$493,"Sí") -> 9.1106082
A89: Viernes | B89: =COUNTIFS('DATOS LIMPIOS'!$U$5:$U$493,"Viernes",'DATOS LIMPIOS'!$AI$5:$AI$493,"Sí") -> 23 | C89: =AVERAGEIFS('DATOS LIMPIOS'!$M$5:$M$493,'DATOS LIMPIOS'!$U$5:$U$493,"Viernes",'DATOS LIMPIOS'!$AI$5:$AI$493,"Sí") -> 28.060257 | D89: =AVERAGEIFS('DATOS LIMPIOS'!$N$5:$N$493,'DATOS LIMPIOS'!$U$5:$U$493,"Viernes",'DATOS LIMPIOS'!$AI$5:$AI$493,"Sí") -> 8.4225011
A90: Sábado | B90: =COUNTIFS('DATOS LIMPIOS'!$U$5:$U$493,"Sábado",'DATOS LIMPIOS'!$AI$5:$AI$493,"Sí") -> 43 | C90: =AVERAGEIFS('DATOS LIMPIOS'!$M$5:$M$493,'DATOS LIMPIOS'!$U$5:$U$493,"Sábado",'DATOS LIMPIOS'!$AI$5:$AI$493,"Sí") -> 27.20283 | D90: =AVERAGEIFS('DATOS LIMPIOS'!$N$5:$N$493,'DATOS LIMPIOS'!$U$5:$U$493,"Sábado",'DATOS LIMPIOS'!$AI$5:$AI$493,"Sí") -> 8.6127331
A91: Domingo | B91: =COUNTIFS('DATOS LIMPIOS'!$U$5:$U$493,"Domingo",'DATOS LIMPIOS'!$AI$5:$AI$493,"Sí") -> 7 | C91: =AVERAGEIFS('DATOS LIMPIOS'!$M$5:$M$493,'DATOS LIMPIOS'!$U$5:$U$493,"Domingo",'DATOS LIMPIOS'!$AI$5:$AI$493,"Sí") -> 33.118311 | D91: =AVERAGEIFS('DATOS LIMPIOS'!$N$5:$N$493,'DATOS LIMPIOS'!$U$5:$U$493,"Domingo",'DATOS LIMPIOS'!$AI$5:$AI$493,"Sí") -> 11.313939
A93: ¿Cambia el resultado? No | D93: p = 0,474 (calculado en Python)
A103: H25 · En las campañas de descuento, ¿importa la hora de envío?
A104: No. Ninguna hora se separa del resto.
A107: Tabla H25 · Campañas de descuento: apertura y CTR por hora de envío
A108: Hora | B108: Campañas | C108: Apertura (%) | D108: CTR (%)
A109: 8 | B109: =COUNTIFS('DATOS LIMPIOS'!$V$5:$V$493,8,'DATOS LIMPIOS'!$AI$5:$AI$493,"Sí") -> 16 | C109: =AVERAGEIFS('DATOS LIMPIOS'!$M$5:$M$493,'DATOS LIMPIOS'!$V$5:$V$493,8,'DATOS LIMPIOS'!$AI$5:$AI$493,"Sí") -> 28.996585 | D109: =AVERAGEIFS('DATOS LIMPIOS'!$N$5:$N$493,'DATOS LIMPIOS'!$V$5:$V$493,8,'DATOS LIMPIOS'!$AI$5:$AI$493,"Sí") -> 7.643366
A110: 9 | B110: =COUNTIFS('DATOS LIMPIOS'!$V$5:$V$493,9,'DATOS LIMPIOS'!$AI$5:$AI$493,"Sí") -> 18 | C110: =AVERAGEIFS('DATOS LIMPIOS'!$M$5:$M$493,'DATOS LIMPIOS'!$V$5:$V$493,9,'DATOS LIMPIOS'!$AI$5:$AI$493,"Sí") -> 30.68477 | D110: =AVERAGEIFS('DATOS LIMPIOS'!$N$5:$N$493,'DATOS LIMPIOS'!$V$5:$V$493,9,'DATOS LIMPIOS'!$AI$5:$AI$493,"Sí") -> 9.1914213
A111: 10 | B111: =COUNTIFS('DATOS LIMPIOS'!$V$5:$V$493,10,'DATOS LIMPIOS'!$AI$5:$AI$493,"Sí") -> 49 | C111: =AVERAGEIFS('DATOS LIMPIOS'!$M$5:$M$493,'DATOS LIMPIOS'!$V$5:$V$493,10,'DATOS LIMPIOS'!$AI$5:$AI$493,"Sí") -> 30.915001 | D111: =AVERAGEIFS('DATOS LIMPIOS'!$N$5:$N$493,'DATOS LIMPIOS'!$V$5:$V$493,10,'DATOS LIMPIOS'!$AI$5:$AI$493,"Sí") -> 10.136859
A112: 11 | B112: =COUNTIFS('DATOS LIMPIOS'!$V$5:$V$493,11,'DATOS LIMPIOS'!$AI$5:$AI$493,"Sí") -> 59 | C112: =AVERAGEIFS('DATOS LIMPIOS'!$M$5:$M$493,'DATOS LIMPIOS'!$V$5:$V$493,11,'DATOS LIMPIOS'!$AI$5:$AI$493,"Sí") -> 27.703452 | D112: =AVERAGEIFS('DATOS LIMPIOS'!$N$5:$N$493,'DATOS LIMPIOS'!$V$5:$V$493,11,'DATOS LIMPIOS'!$AI$5:$AI$493,"Sí") -> 9.061325
A113: 12 | B113: =COUNTIFS('DATOS LIMPIOS'!$V$5:$V$493,12,'DATOS LIMPIOS'!$AI$5:$AI$493,"Sí") -> 17 | C113: =AVERAGEIFS('DATOS LIMPIOS'!$M$5:$M$493,'DATOS LIMPIOS'!$V$5:$V$493,12,'DATOS LIMPIOS'!$AI$5:$AI$493,"Sí") -> 37.091232 | D113: =AVERAGEIFS('DATOS LIMPIOS'!$N$5:$N$493,'DATOS LIMPIOS'!$V$5:$V$493,12,'DATOS LIMPIOS'!$AI$5:$AI$493,"Sí") -> 10.296306
A114: 13 | B114: =COUNTIFS('DATOS LIMPIOS'!$V$5:$V$493,13,'DATOS LIMPIOS'!$AI$5:$AI$493,"Sí") -> 40 | C114: =AVERAGEIFS('DATOS LIMPIOS'!$M$5:$M$493,'DATOS LIMPIOS'!$V$5:$V$493,13,'DATOS LIMPIOS'!$AI$5:$AI$493,"Sí") -> 29.167678 | D114: =AVERAGEIFS('DATOS LIMPIOS'!$N$5:$N$493,'DATOS LIMPIOS'!$V$5:$V$493,13,'DATOS LIMPIOS'!$AI$5:$AI$493,"Sí") -> 9.3819118
A115: 14 | B115: =COUNTIFS('DATOS LIMPIOS'!$V$5:$V$493,14,'DATOS LIMPIOS'!$AI$5:$AI$493,"Sí") -> 24 | C115: =AVERAGEIFS('DATOS LIMPIOS'!$M$5:$M$493,'DATOS LIMPIOS'!$V$5:$V$493,14,'DATOS LIMPIOS'!$AI$5:$AI$493,"Sí") -> 27.253713 | D115: =AVERAGEIFS('DATOS LIMPIOS'!$N$5:$N$493,'DATOS LIMPIOS'!$V$5:$V$493,14,'DATOS LIMPIOS'!$AI$5:$AI$493,"Sí") -> 9.2860913
A116: 15 | B116: =COUNTIFS('DATOS LIMPIOS'!$V$5:$V$493,15,'DATOS LIMPIOS'!$AI$5:$AI$493,"Sí") -> 43 | C116: =AVERAGEIFS('DATOS LIMPIOS'!$M$5:$M$493,'DATOS LIMPIOS'!$V$5:$V$493,15,'DATOS LIMPIOS'!$AI$5:$AI$493,"Sí") -> 33.654978 | D116: =AVERAGEIFS('DATOS LIMPIOS'!$N$5:$N$493,'DATOS LIMPIOS'!$V$5:$V$493,15,'DATOS LIMPIOS'!$AI$5:$AI$493,"Sí") -> 10.241312
A117: 16 | B117: =COUNTIFS('DATOS LIMPIOS'!$V$5:$V$493,16,'DATOS LIMPIOS'!$AI$5:$AI$493,"Sí") -> 21 | C117: =AVERAGEIFS('DATOS LIMPIOS'!$M$5:$M$493,'DATOS LIMPIOS'!$V$5:$V$493,16,'DATOS LIMPIOS'!$AI$5:$AI$493,"Sí") -> 28.273788 | D117: =AVERAGEIFS('DATOS LIMPIOS'!$N$5:$N$493,'DATOS LIMPIOS'!$V$5:$V$493,16,'DATOS LIMPIOS'!$AI$5:$AI$493,"Sí") -> 8.5242856
A119: ¿Cambia el resultado? No | D119: p = 0,155 (calculado en Python)
A127: H26 · ¿Poner el límite de tiempo en el asunto ("solo por hoy", "últimas horas") ayuda?
A128: No: resta. Entre los correos de descuento, los que ponen el tiempo en el asunto abren unos 12 de cada 100 menos y también tienen menos clics. Los que dicen qué recibes en el asunto y dejan el tiempo para el preheader son los mejores del grupo.
A131: Tabla H26 · Apertura y CTR según dónde va el límite de tiempo
A132: Cómo se comunica el descuento | B132: Campañas | C132: Apertura (%) | D132: CTR (%)
A133: Descuento sin tiempo límite | B133: =COUNTIF('DATOS LIMPIOS'!$AL$5:$AL$493,"Descuento sin tiempo límite") -> 206 | C133: =AVERAGEIF('DATOS LIMPIOS'!$AL$5:$AL$493,"Descuento sin tiempo límite",'DATOS LIMPIOS'!$M$5:$M$493) -> 32.142247 | D133: =AVERAGEIF('DATOS LIMPIOS'!$AL$5:$AL$493,"Descuento sin tiempo límite",'DATOS LIMPIOS'!$N$5:$N$493) -> 9.5029647
A134: Descuento con tiempo límite solo en el preheader | B134: =COUNTIF('DATOS LIMPIOS'!$AL$5:$AL$493,"Descuento con tiempo límite solo en el preheader") -> 21 | C134: =AVERAGEIF('DATOS LIMPIOS'!$AL$5:$AL$493,"Descuento con tiempo límite solo en el preheader",'DATOS LIMPIOS'!$M$5:$M$493) -> 37.55579 | D134: =AVERAGEIF('DATOS LIMPIOS'!$AL$5:$AL$493,"Descuento con tiempo límite solo en el preheader",'DATOS LIMPIOS'!$N$5:$N$493) -> 13.070679
A135: Descuento con tiempo límite en el asunto | B135: =COUNTIF('DATOS LIMPIOS'!$AL$5:$AL$493,"Descuento con tiempo límite en el asunto") -> 60 | C135: =AVERAGEIF('DATOS LIMPIOS'!$AL$5:$AL$493,"Descuento con tiempo límite en el asunto",'DATOS LIMPIOS'!$M$5:$M$493) -> 20.79827 | D135: =AVERAGEIF('DATOS LIMPIOS'!$AL$5:$AL$493,"Descuento con tiempo límite en el asunto",'DATOS LIMPIOS'!$N$5:$N$493) -> 7.9922495
A136: Sin descuento | B136: =COUNTIF('DATOS LIMPIOS'!$AL$5:$AL$493,"Sin descuento") -> 202 | C136: =AVERAGEIF('DATOS LIMPIOS'!$AL$5:$AL$493,"Sin descuento",'DATOS LIMPIOS'!$M$5:$M$493) -> 27.793977 | D136: =AVERAGEIF('DATOS LIMPIOS'!$AL$5:$AL$493,"Sin descuento",'DATOS LIMPIOS'!$N$5:$N$493) -> 10.268813
A138: ¿Cambia el resultado? Sí | D138: p = 0,003 (calculado en Python)
A139: Comparación entre asuntos de descuento, dentro del mismo tipo de campaña. Las palabras de "tiempo límite" están en la fórmula de la columna AJ de DATOS LIMPIOS. Ojo: si se cuenta "YA" como urgencia, la diferencia se achica y deja de ser concluyente.
A151: H27 · ¿La urgencia funciona si va con un beneficio concreto?
A152: Depende de qué tan concreto sea. La urgencia sola es lo que peor abre. Agregar una palabra de beneficio genérica ("productos", "belleza") casi no ayuda. El único asunto con urgencia que gana es el que dice exactamente qué recibes: una cifra y "tus favoritos". El problema no es la urgencia; es la urgencia que no dice qué recibes.
A155: Tabla H27 · Apertura de asuntos con urgencia, según si dicen qué recibes
A156: Asunto con urgencia | B156: Campañas | C156: Apertura (%)
A157: Con tiempo límite en el asunto y sin beneficio concreto | B157: =COUNTIFS('DATOS LIMPIOS'!$AJ$5:$AJ$493,"Sí",'DATOS LIMPIOS'!$AM$5:$AM$493,"No",'DATOS LIMPIOS'!$AI$5:$AI$493,"Sí") -> 26 | C157: =AVERAGEIFS('DATOS LIMPIOS'!$M$5:$M$493,'DATOS LIMPIOS'!$AJ$5:$AJ$493,"Sí",'DATOS LIMPIOS'!$AM$5:$AM$493,"No",'DATOS LIMPIOS'!$AI$5:$AI$493,"Sí") -> 18.606849
A158: Con tiempo límite en el asunto y con beneficio concreto | B158: =COUNTIFS('DATOS LIMPIOS'!$AJ$5:$AJ$493,"Sí",'DATOS LIMPIOS'!$AM$5:$AM$493,"Sí",'DATOS LIMPIOS'!$AI$5:$AI$493,"Sí") -> 34 | C158: =AVERAGEIFS('DATOS LIMPIOS'!$M$5:$M$493,'DATOS LIMPIOS'!$AJ$5:$AJ$493,"Sí",'DATOS LIMPIOS'!$AM$5:$AM$493,"Sí",'DATOS LIMPIOS'!$AI$5:$AI$493,"Sí") -> 22.474062
A159: "¡Ahorra YA! Flash Sale: Hasta 50% en tus favoritos" | B159: =COUNTIF('DATOS LIMPIOS'!$E$5:$E$493,"¡Ahorra YA! Flash Sale: Hasta 50% en tus favoritos") -> 21 | C159: =AVERAGEIF('DATOS LIMPIOS'!$E$5:$E$493,"¡Ahorra YA! Flash Sale: Hasta 50% en tus favoritos",'DATOS LIMPIOS'!$M$5:$M$493) -> 41.593593
A161: ¿Cambia el resultado? Señal
A162: Señal, no prueba: hay pocos asuntos con urgencia y beneficio a la vez. Se confirma con el A/B del Hot Sale.
A175: H28 · Dentro de Flash Sale, ¿cuánto pesa el asunto?
A176: Todavía más que en general: en Flash Sale el asunto explica el 74 % de la diferencia en apertura (en general, el 47 %). El mismo tipo de oferta va de 11 a 50 de cada 100 según cómo se diga. Los que pierden solo meten prisa; el que gana con muchos usos dice la cifra y "tus favoritos".
A179: Tabla H28 · Asuntos de Flash Sale, de mayor a menor apertura
A180: Asunto | B180: Campañas | C180: Apertura (%) | D180: CTR (%)
A181: =_calculos!B98 -> Prepárate para un Ahorro Épico: ¡Flash Sale en toda la tienda! | B181: =_calculos!C98 -> 1 | C181: =_calculos!D98 -> 49.696274 | D181: =_calculos!E98 -> 2.419919
A182: =_calculos!B99 -> ¡Última Oportunidad! Descuentos de otro nivel en L'Oréal | B182: =_calculos!C99 -> 1 | C182: =_calculos!D99 -> 45.54717 | D182: =_calculos!E99 -> 13.681301
A183: =_calculos!B100 -> 🔥 Hot Sale Anticipado: ¡Precios de locura en L'Oréal Paris! | B183: =_calculos!C100 -> 3 | C183: =_calculos!D100 -> 43.243161 | D183: =_calculos!E100 -> 7.7863944
A184: =_calculos!B101 -> ¡Ahorra YA! Flash Sale: Hasta 50% en tus favoritos | B184: =_calculos!C101 -> 21 | C184: =_calculos!D101 -> 41.593593 | D184: =_calculos!E101 -> 10.640008
A185: =_calculos!B102 -> 🔥 Hot Sale Anticipado: ¡Precios increíbles en belleza! | B185: =_calculos!C102 -> 3 | C185: =_calculos!D102 -> 39.278311 | D185: =_calculos!E102 -> 8.9045127
A186: =_calculos!B103 -> ¡Oferta Express! No parpadees, tus productos favoritos te esperan | B186: =_calculos!C103 -> 1 | C186: =_calculos!D103 -> 38.629987 | D186: =_calculos!E103 -> 11.85688
A187: =_calculos!B104 -> ¡Ahorra en tus favoritos! Oferta Flash, solo por hoy | B187: =_calculos!C104 -> 2 | C187: =_calculos!D104 -> 33.635625 | D187: =_calculos!E104 -> 5.7188245
A188: =_calculos!B105 -> ¡Ofertas que te harán sonreír! Flash Sale en tus favoritos | B188: =_calculos!C105 -> 4 | C188: =_calculos!D105 -> 31.964921 | D188: =_calculos!E105 -> 12.939709
A189: =_calculos!B106 -> Prepárate para un Ahorro Épico: ¡Flash Sale en todo! | B189: =_calculos!C106 -> 2 | C189: =_calculos!D106 -> 30.716242 | D189: =_calculos!E106 -> 13.306453
A190: =_calculos!B107 -> 🔥 Hot Sale Anticipado: ¡Precios de locura en maquillaje y más! | B190: =_calculos!C107 -> 1 | C190: =_calculos!D107 -> 28.999873 | D190: =_calculos!E107 -> 8.4319385
A191: =_calculos!B108 -> ¡Descuentos Imperdibles! Solo por tiempo limitado, no esperes | B191: =_calculos!C108 -> 1 | C191: =_calculos!D108 -> 24.542645 | D191: =_calculos!E108 -> 14.420132
A192: =_calculos!B109 -> ¡Aprovecha antes de que se acabe! Oferta Flash, productos top | B192: =_calculos!C109 -> 20 | C192: =_calculos!D109 -> 22.775067 | D192: =_calculos!E109 -> 7.6719521
... A196: =_calculos!B113 -> ¡Últimas horas! Flash Sale: No te quedes sin tu descuento | B196: =_calculos!C113 -> 4 | C196: =_calculos!D113 -> 10.812608 | D196: =_calculos!E113 -> 7.0308876
A198: ¿Cambia el resultado? Sí | D198: p = < 0,001 (calculado en Python)
A199: Los asuntos usados 1 o 2 veces pueden estar arriba o abajo por suerte; mira primero los que se usaron muchas veces.
A209: H29 · Los Hot Sale anteriores, ¿funcionaron?
A210: Se abrieron más que las otras Flash Sale, pero no tuvieron más clics. "¡Precios de locura!" genera curiosidad pero no dice qué hay, y cuando el correo no cumple, la persona no hace clic. Por eso el A/B del Hot Sale se decide por clics.
A213: Tabla H29 · Hot Sale anteriores contra otras Flash Sale: apertura, CTR y CTOR
A214: Campañas | B214: Campañas | C214: Apertura (%) | D214: CTR (%) | E214: CTOR (%)
A215: "🔥 Hot Sale Anticipado" | B215: =COUNTIFS('DATOS LIMPIOS'!$B$5:$B$493,"Flash Sale",'DATOS LIMPIOS'!$AS$5:$AS$493,"Sí") -> 7 | C215: =AVERAGEIFS('DATOS LIMPIOS'!$M$5:$M$493,'DATOS LIMPIOS'!$B$5:$B$493,"Flash Sale",'DATOS LIMPIOS'!$AS$5:$AS$493,"Sí") -> 39.509184 | D215: =AVERAGEIFS('DATOS LIMPIOS'!$N$5:$N$493,'DATOS LIMPIOS'!$B$5:$B$493,"Flash Sale",'DATOS LIMPIOS'!$AS$5:$AS$493,"Sí") -> 8.3578085 | E215: =AVERAGEIFS('DATOS LIMPIOS'!$O$5:$O$493,'DATOS LIMPIOS'!$B$5:$B$493,"Flash Sale",'DATOS LIMPIOS'!$AS$5:$AS$493,"Sí") -> 21.898342
A216: Otras Flash Sale | B216: =COUNTIFS('DATOS LIMPIOS'!$B$5:$B$493,"Flash Sale",'DATOS LIMPIOS'!$AS$5:$AS$493,"No") -> 74 | C216: =AVERAGEIFS('DATOS LIMPIOS'!$M$5:$M$493,'DATOS LIMPIOS'!$B$5:$B$493,"Flash Sale",'DATOS LIMPIOS'!$AS$5:$AS$493,"No") -> 28.488497 | D216: =AVERAGEIFS('DATOS LIMPIOS'!$N$5:$N$493,'DATOS LIMPIOS'!$B$5:$B$493,"Flash Sale",'DATOS LIMPIOS'!$AS$5:$AS$493,"No") -> 9.2853215 | E216: =AVERAGEIFS('DATOS LIMPIOS'!$O$5:$O$493,'DATOS LIMPIOS'!$B$5:$B$493,"Flash Sale",'DATOS LIMPIOS'!$AS$5:$AS$493,"No") -> 38.38148
A218: ¿Cambia el resultado? Sí | D218: p = 0,022 (calculado en Python)
...

Sheet RANKING ASUNTOS
A1: Ranking de asuntos
A2: Solo asuntos con 8 o más envíos, para que el promedio signifique algo. En estos datos cada asunto va siempre con el mismo preheader: son una pareja.
A4: # | B4: Asunto | C4: Preheader | D4: Tipo de campaña | E4: Envíos | F4: Campañas | G4: Apertura (%) | H4: CTR (%) | I4: CTOR (%) | J4: Conversión (%)
A5: 1 | B5: ¡Ahorra YA! Flash Sale: Hasta 50% en tus favoritos | C5: Edición limitada: Maquillaje, cuidado de piel y más. ¡Corre! | D5: Flash Sale | E5: 4206020 | F5: 21 | G5: 41.593593 | H5: 10.640008 | I5: 26.390562 | J5: 6.8709524
A6: 2 | B6: ¡Tu lealtad tiene recompensa! Descúbrela, sorpresas para ti | C6: Ofertas exclusivas para nuestros clientes más especiales. ¡No te las pierdas! | D6: Customer Appreciation | E6: 4785531 | F6: 16 | G6: 40.721428 | H6: 10.084078 | I6: 25.866589 | J6: 5.66375
A7: 3 | B7: ¡Pensamos en ti! Descubre estas sorpresas exclusivas | C7: Ofertas exclusivas por tu lealtad a L'Oréal. ¡Aprovecha! | D7: Customer Appreciation | E7: 3775851 | F7: 20 | G7: 39.210447 | H7: 12.290336 | I7: 33.586389 | J7: 4.851
A8: 4 | B8: ¡Solo un clic te separa de estas ofertas! L'Oréal Paris | C8: Descuentos irresistibles en productos seleccionados. ¡Últimas horas! | D8: Exclusive Offers | E8: 3947386 | F8: 15 | G8: 38.720232 | H8: 13.442773 | I8: 36.400304 | J8: 4.34
A9: 5 | B9: Lo último en L'Oréal: Mantente informad@ de las novedades | C9: Descubre las novedades y tips de la semana. ¡Entra ya! | D9: Newsletter | E9: 4444619 | F9: 19 | G9: 36.827379 | H9: 11.211794 | I9: 30.432397 | J9: 5.3384211
A10: 6 | B10: ¡El futuro de tu piel ha llegado! Nuevo Producto revolucionario | C10: Una fórmula revolucionaria para resultados visibles. ¡Compruébalo! | D10: New Product Launch | E10: 7052119 | F10: 25 | G10: 36.132518 | H10: 12.28628 | I10: 35.551095 | J10: 4.4228
A11: 7 | B11: ¡Aprovecha los descuentos! Temporada de Fiestas, beauty deals | C11: Tus productos favoritos con precios festivos. ¡No te los pierdas! | D11: Holiday Discounts | E11: 1868935 | F11: 9 | G11: 35.565837 | H11: 9.1636305 | I11: 29.842513 | J11: 5.1055556
A12: 8 | B12: ¡Regalos perfectos te esperan! Descuentos de Lujo, L'Oréal | C12: Encuentra ese detalle especial para ti o tus seres queridos. ¡Descubre! | D12: Holiday Discounts | E12: 8188063 | F12: 30 | G12: 35.409887 | H12: 10.180272 | I12: 32.355307 | J12: 5.4593333
A13: 9 | B13: Tu Dosis de Belleza: ¡No te lo pierdas! Tips y trucos | C13: Consejos expertos, tendencias y más en tu bandeja de entrada. ¡Descúbrelo! | D13: Newsletter | E13: 5849262 | F13: 25 | G13: 33.412775 | H13: 12.982834 | I13: 45.000523 | J13: 5.8272
A14: 10 | B14: ¡Ofertas Exclusivas! Solo para nuestra comunidad VIP | C14: Productos premium con descuentos únicos. ¡Acceso limitado! | D14: Exclusive Offers | E14: 5924957 | F14: 22 | G14: 33.047231 | H14: 8.8191241 | I14: 28.427689 | J14: 5.1072727
A15: 11 | B15: ¡Lo nuevo de L'Oréal! Te va a encantar: innovación en belleza | C15: Prepárate para experimentar la innovación en tu belleza. ¡Descúbrela! | D15: New Product Launch | E15: 3679079 | F15: 22 | G15: 30.936882 | H15: 11.943639 | I15: 39.988433 | J15: 5.4318182
A16: 12 | B16: ¡Celebra con nosotros! Descuentos festivos para regalar | C16: Regalos perfectos y ofertas que te encantarán. ¡Descubre más! | D16: Holiday Discounts | E16: 5453244 | F16: 20 | G16: 29.233023 | H16: 7.9784638 | I16: 33.685688 | J16: 5.469
... A26: 22 | B26: ¡Oportunidades de ahorro! Descúbrelas, solo para ti | C26: No te pierdas estas ofertas únicas que tenemos para ti. ¡Entra ya! | D26: Exclusive Offers | E26: 2045833 | F26: 8 | G26: 10.717211 | H26: 7.8528886 | I26: 73.49449 | J26: 4.7325

Sheet PROYECCIÓN COP
A1: Proyección en pesos · cuánto puede valer esto
A2: Las celdas CREMA son supuestos editables: cámbielos y todo lo demás se recalcula. Las celdas blancas son fórmulas.
A4: LO QUE SABEMOS Y LO QUE SUPONEMOS
A5: La diferencia en APERTURA está medida en los datos y es sólida. La diferencia en CLICKS es probable pero no está probada: su intervalo de confianza incluye el cero. Y la conversión a venta NO está en los datos: son supuestos que el equipo de marca debe reemplazar por sus cifras reales.
A7: Parámetro | D7: Valor | E7: Origen
A8: Tamaño del envío (emails) | D8: 234681 | E8: Mediana de las campañas analizadas
A9: Tasa de apertura · asunto típico (%) | D9: 27.85 | E9: Medido: promocionales sin cifra
A10: Tasa de apertura · con cifra (%) | D10: 41.59 | E10: Medido: asuntos con porcentaje
A11: CTR · asunto típico (%) | D11: 9.05 | E11: Medido
A12: CTR · con cifra, central (%) | D12: 10.64 | E12: Medido, estimación central
A13: CTR · con cifra, conservador (%) | D13: 8.25 | E13: Límite inferior del IC 95 %
A14: CTR · con cifra, optimista (%) | D14: 12.95 | E14: Límite superior del IC 95 %
A15: Conversión del clic a compra (%) | D15: 2 | E15: SUPUESTO · reemplazar por el real
A16: Ticket promedio (COP) | D16: 180000 | E16: SUPUESTO · reemplazar por el real
A17: Campañas promocionales al año | D17: 24 | E17: SUPUESTO · dos al mes
A19: RESULTADO POR CAMPAÑA
A20: Escenario | B20: Aperturas | C20: Aperturas ganadas | D20: Clics | E20: Pedidos | F20: Ingreso (COP) | G20: Diferencia (COP)
A21: Asunto típico (base) | B21: =$D$8*$D$9/100 -> 65358.659 | C21: — | D21: =$D$8*$D$11/100 -> 21238.631 | E21: =D21*$D$15/100 -> 424.77261 | F21: =E21*$D$16 -> 76459070 | G21: —
A22: Con cifra · conservador | B22: =$D$8*$D$10/100 -> 97603.828 | C22: =B22-B$21 -> 32245.169 | D22: =$D$8*$D$13/100 -> 19361.182 | E22: =D22*$D$15/100 -> 387.22365 | F22: =E22*$D$16 -> 69700257 | G22: =F22-F$21 -> -6758812.8
A23: Con cifra · central | B23: =$D$8*$D$10/100 -> 97603.828 | C23: =B23-B$21 -> 32245.169 | D23: =$D$8*$D$12/100 -> 24970.058 | E23: =D23*$D$15/100 -> 499.40117 | F23: =E23*$D$16 -> 89892210 | G23: =F23-F$21 -> 13433140
A24: Con cifra · optimista | B24: =$D$8*$D$10/100 -> 97603.828 | C24: =B24-B$21 -> 32245.169 | D24: =$D$8*$D$14/100 -> 30391.189 | E24: =D24*$D$15/100 -> 607.82379 | F24: =E24*$D$16 -> 1.0940828e+08 | G24: =F24-F$21 -> 32949212
A26: PROYECCIÓN ANUAL
A27: Diferencia anual · conservador | F27: =G22*$D$17 -> -1.6221151e+08
A28: Diferencia anual · central | F28: =G23*$D$17 -> 3.2239537e+08
A29: Diferencia anual · optimista | F29: =G24*$D$17 -> 7.907811e+08
A31: CÓMO LEER ESTO. Las APERTURAS GANADAS son seguras: ese aumento está medido y su intervalo de confianza nunca toca el cero. Lo que no es seguro es que esas aperturas extra se conviertan en más clics, porque la mejora en clics no está probada: su intervalo de confianza incluye valores negativos. Hay un 91 % de probabilidad de que el efecto sea positivo, no un 100 %. Y el paso de clic a venta usa supuestos que no vienen de estos datos. Por eso la cifra se presenta como rango y no como promesa. El escenario conservador no dice que la idea falle: dice que podríamos ganar alcance sin ganar clics.

Sheet PRUEBA AB
A1: Prueba A/B · cuántos correos hacen falta
A2: Calcula el tamaño mínimo de cada versión para que el resultado sea concluyente y no casualidad. Las celdas crema son editables.
A4: Tasa de apertura esperada, versión A (%) | D4: 27.85
A5: Mejora que queremos poder detectar (puntos) | D5: 2
A6: Confianza (%) | D6: 95
A7: Poder estadístico (%) | D7: 80
A8: Tamaño total de la base | D8: 234681
A10: CÁLCULO
A11: p₁ (proporción A) | D11: =$D$4/100 -> 0.2785
A12: p₂ (proporción B) | D12: =($D$4+$D$5)/100 -> 0.2985
A13: z de confianza | D13: =NORMSINV(1-(1-$D$6/100)/2) -> 1.959964
A14: z de poder | D14: =NORMSINV($D$7/100) -> 0.84162123
A15: Emails necesarios POR VERSIÓN | D15: =($D$13+$D$14)^2*($D$11*(1-$D$11)+$D$12*(1-$D$12))/($D$12-$D$11)^2 -> 8051.685
A16: % de la base que ocupa cada versión | D16: =D15/$D$8*100 -> 3.4309062
A18: LECTURA. Con el 10 % de la base en cada versión (unos 23.500 correos) la prueba detecta mejoras de alrededor de 1,2 puntos de apertura. Es de sobra para lo que buscamos: la diferencia medida entre un asunto con cifra y uno sin ella es de casi 14 puntos.

Sheet FÓRMULAS Y VERIFICACIÓN
A1: Fórmulas y verificación
A2: Cada métrica del análisis, con su fórmula, la columna de la que se alimenta y la hoja donde está calculada.
A4: Métrica | B4: Fórmula | C4: Se alimenta de | D4: Calculada en | E4: Para qué sirve
A5: Tasa de Apertura (%) | B5: Emails Abiertos ÷ Emails Enviados × 100 | C5: Columnas H e I del archivo original | D5: DATOS LIMPIOS, columna M | E5: Mide si el ASUNTO convenció en la bandeja de entrada.
A6: CTR (%) | B6: Total Clicks ÷ Emails Enviados × 100 | C6: Columnas I y J del original | D6: DATOS LIMPIOS, columna N | E6: Resultado de punta a punta: asunto más contenido.
A7: CTOR (%) | B7: Total Clicks ÷ Emails Abiertos × 100 | C7: Columnas I y J del original | D7: DATOS LIMPIOS | E7: Aísla el contenido: de los que abrieron, cuántos hicieron clic.
A8: Ingreso por mil envíos ($) | B8: Ingresos ÷ Envíos × 1.000 | C8: Columnas G y L del original | D8: DATOS LIMPIOS | E8: Compara campañas de distinto tamaño en la misma vara.
A9: % que explica una variable | B9: Suma de cuadrados entre grupos ÷ suma de cuadrados total | C9: Agrupando DATOS LIMPIOS por la variable | D9: HALLAZGOS | E9: Qué parte de la variación en apertura atribuye esa variable.
A10: p (valor p) | B10: Prueba de Kruskal-Wallis sobre los rangos | C10: DATOS LIMPIOS agrupados | D10: HALLAZGOS | E10: Probabilidad de ver esa diferencia por azar. Bajo 0,05 se toma por real.
A11: Correlación (r) | B11: Coeficiente de Pearson, con prueba de permutación | C11: Ingresos contra cada métrica | D11: HALLAZGOS | E11: Mide si dos cifras se mueven juntas. Cero significa que no.
A12: IC 95 % del aumento | B12: Bootstrap de 20.000 remuestreos | C12: Campañas con cifra vs resto | D12: PROYECCIÓN COP | E12: Rango donde cae el aumento real con 95 % de confianza.
A13: Tamaño de muestra A/B | B13: (z(α/2)+z(β))² × (p₁q₁+p₂q₂) ÷ (p₂−p₁)² | C13: Fórmula estándar de dos proporciones | D13: PRUEBA AB | E13: Cuántos correos necesita cada versión para que el test concluya.
A15: COMPROBACIÓN EN VIVO
A16: Estas celdas recalculan los totales desde DATOS LIMPIOS. Si cuadran con el TABLERO, el libro es consistente.
A18: Campañas | C18: =COUNT('DATOS LIMPIOS'!$G$5:$G$493) -> 489
A19: Emails enviados | C19: =SUM('DATOS LIMPIOS'!$G$5:$G$493) -> 120096662
A20: Emails abiertos | C20: =SUM('DATOS LIMPIOS'!$H$5:$H$493) -> 34760801
A21: Clics | C21: =SUM('DATOS LIMPIOS'!$I$5:$I$493) -> 11682604
A22: Tasa de apertura global | C22: =SUM('DATOS LIMPIOS'!$H$5:$H$493)/SUM('DATOS LIMPIOS'!$G$5:$G$493)*100 -> 28.944019
A23: CTR global | C23: =SUM('DATOS LIMPIOS'!$I$5:$I$493)/SUM('DATOS LIMPIOS'!$G$5:$G$493)*100 -> 9.7276675
A24: CTOR global | C24: =SUM('DATOS LIMPIOS'!$I$5:$I$493)/SUM('DATOS LIMPIOS'!$H$5:$H$493)*100 -> 33.608558
A27: LAS CIFRAS DEL ANÁLISIS, RECALCULADAS POR EXCEL
A28: Aquí no hay números escritos a mano. Cada celda de la columna RESULTADO es una fórmula que lee la hoja DATOS LIMPIOS y vuelve a calcular la cifra desde cero. Si alguien duda de un número del informe, hace clic en la celda y ve el cálculo completo. La columna de la derecha dice qué debería salir: si no coincide, algo está mal.
A30: Cifra del informe | B30: La fórmula, escrita | C30: Resultado | D30: Debe dar | E30: ¿Cuadra?
A31: Tasa de apertura promedio | B31: AVERAGE('DATOS LIMPIOS'!$M$5:$M$493) | C31: =AVERAGE('DATOS LIMPIOS'!$M$5:$M$493) -> 29.186614 | D31: 29.187 | E31: =IF(ABS(C31-D31)<0.05,"Sí","REVISAR") -> Sí
A32: Apertura · asuntos CON cifra | B32: AVERAGEIF('DATOS LIMPIOS'!$E$5:$E$493,"*%*",'DATOS LIMPIOS'!$M$5:$M$493) | C32: =AVERAGEIF('DATOS LIMPIOS'!$E$5:$E$493,"*%*",'DATOS LIMPIOS'!$M$5:$M$493) -> 41.593593 | D32: 41.594 | E32: =IF(ABS(C32-D32)<0.05,"Sí","REVISAR") -> Sí
A33: Apertura · asuntos SIN cifra | B33: AVERAGEIF('DATOS LIMPIOS'!$E$5:$E$493,"<>*%*",'DATOS LIMPIOS'!$M$5:$M$493) | C33: =AVERAGEIF('DATOS LIMPIOS'!$E$5:$E$493,"<>*%*",'DATOS LIMPIOS'!$M$5:$M$493) -> 28.62989 | D33: 28.63 | E33: =IF(ABS(C33-D33)<0.05,"Sí","REVISAR") -> Sí
A34: Diferencia entre ambos (puntos) | B34: AVERAGEIF('DATOS LIMPIOS'!$E$5:$E$493,"*%*",'DATOS LIMPIOS'!$M$5:$M$493)-AVERAGEIF('DATOS LIMPIOS'!$E$5:$E$493,"<>*%*",'DATOS LIMPIOS'!$M$5:$M$493) | C34: =AVERAGEIF('DATOS LIMPIOS'!$E$5:$E$493,"*%*",'DATOS LIMPIOS'!$M$5:$M$493)-AVERAGEIF('DATOS LIMPIOS'!$E$5:$E$493,"<>*%*",'DATOS LIMPIOS'!$M$5:$M$493) -> 12.963703 | D34: 12.964 | E34: =IF(ABS(C34-D34)<0.05,"Sí","REVISAR") -> Sí
A35: % que explica el ASUNTO | B35: (SUMPRODUCT(('DATOS LIMPIOS'!$M$5:$M$493-AVERAGE('DATOS LIMPIOS'!$M$5:$M$493))^2)-SUMPRODUCT(('DATOS LIMPIOS'!$M$5:$M$493-'DATOS LIMPIOS'!$Q$5:$Q$493)^2))/SUMPRODUCT(('DATOS LIMPIOS'!$M$5:$M$493-AVERAGE('DATOS LIMPIOS'!$M$5:$M$493))^2)*100 | C35: =(SUMPRODUCT(('DATOS LIMPIOS'!$M$5:$M$493-AVERAGE('DATOS LIMPIOS'!$M$5:$M$493))^2)-SUMPRODUCT(('DATOS LIMPIOS'!$M$5:$M$493-'DATOS LIMPIOS'!$Q$5:$Q$493)^2))/SUMPRODUCT(('DATOS LIMPIOS'!$M$5:$M$493-AVERAGE('DATOS LIMPIOS'!$M$5:$M$493))^2)*100 -> 47.410372 | D35: 47.41 | E35: =IF(ABS(C35-D35)<0.05,"Sí","REVISAR") -> Sí
A36: % que explica el TIPO de campaña | B36: (SUMPRODUCT(('DATOS LIMPIOS'!$M$5:$M$493-AVERAGE('DATOS LIMPIOS'!$M$5:$M$493))^2)-SUMPRODUCT(('DATOS LIMPIOS'!$M$5:$M$493-'DATOS LIMPIOS'!$R$5:$R$493)^2))/SUMPRODUCT(('DATOS LIMPIOS'!$M$5:$M$493-AVERAGE('DATOS LIMPIOS'!$M$5:$M$493))^2)*100 | C36: =(SUMPRODUCT(('DATOS LIMPIOS'!$M$5:$M$493-AVERAGE('DATOS LIMPIOS'!$M$5:$M$493))^2)-SUMPRODUCT(('DATOS LIMPIOS'!$M$5:$M$493-'DATOS LIMPIOS'!$R$5:$R$493)^2))/SUMPRODUCT(('DATOS LIMPIOS'!$M$5:$M$493-AVERAGE('DATOS LIMPIOS'!$M$5:$M$493))^2)*100 -> 1.3828802 | D36: 1.383 | E36: =IF(ABS(C36-D36)<0.05,"Sí","REVISAR") -> Sí
A37: Correlación ingresos vs clics | B37: CORREL('DATOS LIMPIOS'!$I$5:$I$493,'DATOS LIMPIOS'!$L$5:$L$493) | C37: =CORREL('DATOS LIMPIOS'!$I$5:$I$493,'DATOS LIMPIOS'!$L$5:$L$493) -> 0.037675972 | D37: 0.038 | E37: =IF(ABS(C37-D37)<0.05,"Sí","REVISAR") -> Sí
A38: Su valor p | B38: TDIST(ABS(CORREL('DATOS LIMPIOS'!$I$5:$I$493,'DATOS LIMPIOS'!$L$5:$L$493))*SQRT(489-2)/SQRT(1-CORREL('DATOS LIMPIOS'!$I$5:$I$493,'DATOS LIMPIOS'!$L$5:$L$493)^2),489-2,2) | C38: =TDIST(ABS(CORREL('DATOS LIMPIOS'!$I$5:$I$493,'DATOS LIMPIOS'!$L$5:$L$493))*SQRT(489-2)/SQRT(1-CORREL('DATOS LIMPIOS'!$I$5:$I$493,'DATOS LIMPIOS'!$L$5:$L$493)^2),489-2,2) -> 0.40580152 | D38: ver nota | E38: —
A39: Brecha mejor vs peor asunto | B39: MAX('RANKING ASUNTOS'!$G$5:$G$26)/MIN('RANKING ASUNTOS'!$G$5:$G$26) | C39: =MAX('RANKING ASUNTOS'!$G$5:$G$26)/MIN('RANKING ASUNTOS'!$G$5:$G$26) -> 3.8810091 | D39: 3.881 | E39: =IF(ABS(C39-D39)<0.05,"Sí","REVISAR") -> Sí
A41: La columna "Debe dar" viene de calcular lo mismo por fuera de Excel, en Python. Que las dos columnas coincidan significa que la cifra está comprobada por dos caminos independientes. Las dos últimas filas no llevan comparación porque son fórmulas directas de Excel, sin cálculo paralelo que confrontar.
A44: COMPROBACIÓN DE LAS HIPÓTESIS NUEVAS
A45: Cifra | B45: Dónde | C45: Resultado | D45: Debe dar | E45: ¿Cuadra?
A46: Prueba en agosto: los que ganaban | B46: H3 ASUNTO | C46: ='H3 ASUNTO'!B34 -> 39.033107 | D46: 39.03 | E46: =IF(ABS(C46-D46)<0.05,"Sí","REVISAR") -> Sí
A47: Prueba en agosto: los que perdían | B47: H3 ASUNTO | C47: ='H3 ASUNTO'!C34 -> 20.596391 | D47: 20.6 | E47: =IF(ABS(C47-D47)<0.05,"Sí","REVISAR") -> Sí
A48: Prueba en septiembre: ganaban | B48: H3 ASUNTO | C48: ='H3 ASUNTO'!B35 -> 38.936539 | D48: 38.94 | E48: =IF(ABS(C48-D48)<0.05,"Sí","REVISAR") -> Sí
A49: Prueba en septiembre: perdían | B49: H3 ASUNTO | C49: ='H3 ASUNTO'!C35 -> 16.313814 | D49: 16.31 | E49: =IF(ABS(C49-D49)<0.05,"Sí","REVISAR") -> Sí
A50: Prueba en octubre: ganaban | B50: H3 ASUNTO | C50: ='H3 ASUNTO'!B36 -> 39.55018 | D50: 39.55 | E50: =IF(ABS(C50-D50)<0.05,"Sí","REVISAR") -> Sí
A51: Prueba en octubre: perdían | B51: H3 ASUNTO | C51: ='H3 ASUNTO'!C36 -> 16.525879 | D51: 16.53 | E51: =IF(ABS(C51-D51)<0.05,"Sí","REVISAR") -> Sí
A52: Descuento con tiempo límite en el asunto: apertura | B52: H4 TEMÁTICA HOT SALE | C52: ='H4 TEMÁTICA HOT SALE'!C135 -> 20.79827 | D52: 20.8 | E52: =IF(ABS(C52-D52)<0.05,"Sí","REVISAR") -> Sí
A53: Descuento con tiempo en el preheader: apertura | B53: H4 TEMÁTICA HOT SALE | C53: ='H4 TEMÁTICA HOT SALE'!C134 -> 37.55579 | D53: 37.56 | E53: =IF(ABS(C53-D53)<0.05,"Sí","REVISAR") -> Sí
A54: Hot Sale anteriores: apertura | B54: H4 TEMÁTICA HOT SALE | C54: ='H4 TEMÁTICA HOT SALE'!C215 -> 39.509184 | D54: 39.51 | E54: =IF(ABS(C54-D54)<0.05,"Sí","REVISAR") -> Sí
A55: Hot Sale anteriores: CTR | B55: H4 TEMÁTICA HOT SALE | C55: ='H4 TEMÁTICA HOT SALE'!D215 -> 8.3578085 | D55: 8.36 | E55: =IF(ABS(C55-D55)<0.05,"Sí","REVISAR") -> Sí
A56: Etiqueta en octubre: apertura | B56: H3 ASUNTO | C56: ='H3 ASUNTO'!C84 -> 19.532131 | D56: 19.53 | E56: =IF(ABS(C56-D56)<0.05,"Sí","REVISAR") -> Sí
A57: Correlación apertura-CTR de asuntos | B57: H3 ASUNTO | C57: ='H3 ASUNTO'!B154 -> 0.73892623 | D57: 0.74 | E57: =IF(ABS(C57-D57)<0.05,"Sí","REVISAR") -> Sí
A58: Batalla de Boyacá: diferencia | B58: H1 CALENDARIO | C58: ='H1 CALENDARIO'!C106 -> 1.7606372 | D58: 1.76 | E58: =IF(ABS(C58-D58)<0.05,"Sí","REVISAR") -> Sí
A59: Estilo: solo urgencia, apertura | B59: H3 ASUNTO | C59: ='H3 ASUNTO'!C61 -> 21.257416 | D59: 21.26 | E59: =IF(ABS(C59-D59)<0.05,"Sí","REVISAR") -> Sí
A60: Estilo: recompensa, apertura | B60: H3 ASUNTO | C60: ='H3 ASUNTO'!C59 -> 29.134331 | D60: 29.13 | E60: =IF(ABS(C60-D60)<0.05,"Sí","REVISAR") -> Sí
A61: Campañas de descuento | B61: H4 TEMÁTICA HOT SALE | C61: =COUNTIF('DATOS LIMPIOS'!$AI$5:$AI$493,"Sí") -> 287 | D61: 287 | E61: =IF(ABS(C61-D61)<0.05,"Sí","REVISAR") -> Sí
A62: Filas excluidas | B62: H0 DATOS | C62: ='H0 DATOS'!B7 -> 87 | D62: 87 | E62: =IF(ABS(C62-D62)<0.05,"Sí","REVISAR") -> Sí
A63: Asuntos distintos | B63: _calculos | C63: =COUNTIF(_calculos!$B$4:$B$69,"?*") -> 66 | D63: 66 | E63: =IF(ABS(C63-D63)<0.05,"Sí","REVISAR") -> Sí

Sheet DATOS LIMPIOS
A1: Datos limpios · 489 campañas
A2: Las columnas en dorado son FÓRMULAS, no números pegados: haga clic en cualquiera y verá el cálculo. Si corrige un dato crudo, las tasas se actualizan solas. De la columna S en adelante: columnas nuevas, todas con fórmula, para probar cada hipótesis.
A4: Campaign ID | B4: Tipo de Campaña | C4: Fecha de Envío | D4: Hora de Envío | E4: Asunto del Email | F4: Preheader del Email | G4: Emails Enviados | H4: Emails Abiertos | I4: Total Clicks | J4: Tasa de Conversión (%) | K4: Tasa de Desuscripción (%) | L4: Ingresos Generados ($) | M4: Tasa de Apertura (%) | N4: CTR (%) | O4: CTOR (%) | P4: Ingreso por mil envíos ($) | Q4: Apertura media de ESTE asunto | R4: Apertura media de ESTE tipo | S4: Fecha (como fecha) | T4: Mes | U4: Día de la semana | V4: Hora | W4: Momento del mes | X4: Campañas ese día | Y4: Día masivo (20 o más) | Z4: Objetivo | AA4: Tamaño del envío | AB4: N° de uso del asunto | AC4: Veces que se usó el asunto | AD4: Tercio de uso (asuntos 8+) | AE4: Diferencia contra su asunto (puntos) | AF4: Asunto, para buscar | AG4: Preheader, para buscar | AH4: Empieza con etiqueta | AI4: Habla de descuento | AJ4: Tiempo límite en el asunto | AK4: Tiempo límite en el preheader | AL4: Grupo de descuento | AM4: Asunto con beneficio concreto | AN4: Preheader vago | AO4: Caracteres del asunto | AP4: Palabras del asunto | AQ4: Signos de puntuación | AR4: Cumple reglas de Mailchimp | AS4: Es Hot Sale | AT4: Estilo del asunto
A5: EM-001 | B5: Customer Appreciation | C5: 2025-10-15 | D5: 10:30:00 | E5: ¡Gracias por ser parte de L'Oréal! Ofertas para ti | F5: Descubre nuestras novedades y ofertas exclusivas para ti. ¡Te encantarán! | G5: 436375 | H5: 25439 | I5: 20073 | J5: 1.77 | K5: 2.84 | L5: 37643.98 | M5: =IFERROR(H5/G5*100,"") -> 5.829619 | N5: =IFERROR(I5/G5*100,"") -> 4.5999427 | O5: =IFERROR(I5/H5*100,"") -> 78.906404 | P5: =IFERROR(L5/G5*1000,"") -> 86.265208 | Q5: =AVERAGEIF($E$5:$E$493,$E5,$M$5:$M$493) -> 22.904078 | R5: =AVERAGEIF($B$5:$B$493,$B5,$M$5:$M$493) -> 31.113651 | S5: =DATEVALUE(C5) -> 45945 | T5: =CHOOSE(MONTH(S5)-7,"Agosto","Septiembre","Octubre") -> Octubre | U5: =CHOOSE(WEEKDAY(S5,2),"Lunes","Martes","Miércoles","Jueves","Viernes","Sábado","Domingo") -> Miércoles | V5: =VALUE(LEFT(D5,2)) -> 10 | W5: =IF(OR(AND(DAY(S5)>=14,DAY(S5)<=16),DAY(S5)>=DAY(EOMONTH(S5,0))-1,DAY(S5)=1),"Quincena",IF(OR(AND(DAY(S5)>=2,DAY(S5)<=5),AND(DAY(S5)>=17,DAY(S5)<=20)),"Días después del pago","Resto del mes")) -> Quincena | X5: =COUNTIF($S$5:$S$493,S5) -> 2 | Y5: =IF(X5>=20,"Sí","No") -> No | Z5: =CHOOSE(MATCH(B5,{"Customer Appreciation","Exclusive Offers","Flash Sale","Holiday Discounts","New Product Launch","Newsletter"},0),"Fidelizar","Vender","Vender","Vender","Lanzar","Educar") -> Fidelizar | AA5: =IF(G5<100000,"Menos de 100 mil",IF(G5<200000,"100 a 200 mil",IF(G5<300000,"200 a 300 mil",IF(G5<400000,"300 a 400 mil","Más de 400 mil")))) -> Más de 400 mil | AB5: =COUNTIFS($E$5:$E$493,E5,$S$5:$S$493,"<"&S5)+COUNTIFS($E$5:E5,E5,$S$5:S5,S5) -> 2 | AC5: =COUNTIF($E$5:$E$493,E5) -> 4 | AD5: =IF(AC5<8,"",IF(AB5<=AC5/3,"Primer tercio",IF(AB5>AC5*2/3,"Último tercio","Medio"))) | AE5: =M5-Q5 -> -17.074459 | AF5: =" "&LOWER(SUBSTITUTE(SUBSTITUTE(SUBSTITUTE(SUBSTITUTE(SUBSTITUTE(SUBSTITUTE(SUBSTITUTE(E5,"¡"," "),"!"," "),"¿"," "),"?"," "),":"," "),","," "),"."," "))&" " -> gracias por ser parte de l'oréal ofertas para ti | AG5: =" "&LOWER(SUBSTITUTE(SUBSTITUTE(SUBSTITUTE(SUBSTITUTE(SUBSTITUTE(SUBSTITUTE(SUBSTITUTE(F5,"¡"," "),"!"," "),"¿"," "),"?"," "),":"," "),","," "),"."," "))&" " -> descubre nuestras novedades y ofertas exclusivas para ti te encantarán | AH5: =IF(SUMPRODUCT(--(LEFT(IF(LEFT(LOWER(E5),1)="¡",MID(LOWER(E5),2,300),LOWER(E5)),LEN({"actualizaci","el resumen","tu resumen","novedades l","oportunidad","tu oportunidad","ofertas de temporada","gran oferta","últimas horas","última oportunidad","presentamos","es hora de","descuentos imperdibles","descuentos que","un pequeño detalle"}))={"actualizaci","el resumen","tu resumen","novedades l","oportunidad","tu oportunidad","ofertas de temporada","gran oferta","últimas horas","última oportunidad","presentamos","es hora de","descuentos imperdibles","descuentos que","un pequeño detalle"}))>0,"Sí","No") -> No | AI5: =IF(OR(SUMPRODUCT(--ISNUMBER(SEARCH({"descuento","oferta","ahorr","precio"," sale ","flash","deals"},AF5)))>0,SUMPRODUCT(--ISNUMBER(SEARCH({"descuento","oferta","ahorr","precio"," sale ","flash","deals"},AG5)))>0),"Sí","No") -> Sí | AJ5: =IF(SUMPRODUCT(--ISNUMBER(SEARCH({" hoy ","horas","tiempo limitado","antes de que","se acab","se agot","finalic","última oportunidad","oportunidad única","relámpago","express","no esperes","no volver","no parpadees"},AF5)))>0,"Sí","No") -> No | AK5: =IF(SUMPRODUCT(--ISNUMBER(SEARCH({" hoy ","horas","tiempo limitado","antes de que","se acab","se agot","finalic","última oportunidad","oportunidad única","relámpago","express","no esperes","no volver","no parpadees"},AG5)))>0,"Sí","No") -> No | AL5: =IF(AI5="No","Sin descuento",IF(AJ5="Sí","Descuento con tiempo límite en el asunto",IF(AK5="Sí","Descuento con tiempo límite solo en el preheader","Descuento sin tiempo límite"))) -> Descuento sin tiempo límite | AM5: =IF(SUMPRODUCT(--ISNUMBER(SEARCH({"0","1","2","3","4","5","6","7","8","9","favorit","maquillaje","piel","cabello","productos","belleza","regalo"},E5)))>0,"Sí","No") -> No | AN5: =IF(SUMPRODUCT(--ISNUMBER(SEARCH({"lo que tenemos","estas ofertas","algo especial","ofertas únicas","que preparamos","no te quedes","echa un vistazo"},F5)))>0,"Sí","No") -> No | AO5: =LEN(E5)-(LEN(E5)-LEN(SUBSTITUTE(E5,"🔥","")))/LEN("🔥")*(LEN("🔥")-1) -> 50 | AP5: =LEN(TRIM(E5))-LEN(SUBSTITUTE(TRIM(E5)," ",""))+1 -> 9 | AQ5: =SUMPRODUCT(LEN(E5)-LEN(SUBSTITUTE(E5,{"!","¡","?","¿",":",",",".","%","·","-",";"},""))) -> 2 | AR5: =IF(AND(AO5<=60,AP5<=9,AQ5<=3,(LEN(E5)-LEN(SUBSTITUTE(E5,"🔥","")))/LEN("🔥")<=1),"Sí","No") -> Sí | AS5: =IF(ISNUMBER(SEARCH("hot sale",E5)),"Sí","No") -> No | AT5: =IF(SUMPRODUCT(--ISNUMBER(FIND({"0","1","2","3","4","5","6","7","8","9"},E5)))>0,"Con cifra concreta",IF(OR(ISNUMBER(FIND("?",E5)),ISNUMBER(FIND("¿",E5))),"Pregunta abierta",IF(SUMPRODUCT(--ISNUMBER(SEARCH({" hoy ","horas","tiempo limitado","antes de que","se acab","se agot","finalic","última oportunidad","oportunidad única","relámpago","express","no esperes","no volver","no parpadees"," ya ","últimas horas","últimas unidades"," ahora "},AF5)))>0,"Solo urgencia, sin cifra",IF(SUMPRODUCT(--ISNUMBER(SEARCH({"recompensa","sorpresa","regalo","lealtad","detalle","gracias","pensamos en ti","para ti"},E5)))>0,"Recompensa o sorpresa","Otro: beneficio o novedad")))) -> Recompensa o sorpresa
A6: EM-002 | B6: Flash Sale | C6: 2025-09-02 | D6: 14:00:00 | E6: ¡Últimas horas! Flash Sale: No te quedes sin tu descuento | F6: Solo por hoy: descuentos increíbles en tus favoritos. ¡Compra ahora! | G6: 38111 | H6: 2291 | I6: 2229 | J6: 2.01 | K6: 4.08 | L6: 57634.13 | M6: =IFERROR(H6/G6*100,"") -> 6.0113878 | N6: =IFERROR(I6/G6*100,"") -> 5.8487051 | O6: =IFERROR(I6/H6*100,"") -> 97.293758 | P6: =IFERROR(L6/G6*1000,"") -> 1512.2702 | Q6: =AVERAGEIF($E$5:$E$493,$E6,$M$5:$M$493) -> 10.812608 | R6: =AVERAGEIF($B$5:$B$493,$B6,$M$5:$M$493) -> 29.440902 | S6: =DATEVALUE(C6) -> 45902 | T6: =CHOOSE(MONTH(S6)-7,"Agosto","Septiembre","Octubre") -> Septiembre | U6: =CHOOSE(WEEKDAY(S6,2),"Lunes","Martes","Miércoles","Jueves","Viernes","Sábado","Domingo") -> Martes | V6: =VALUE(LEFT(D6,2)) -> 14 | W6: =IF(OR(AND(DAY(S6)>=14,DAY(S6)<=16),DAY(S6)>=DAY(EOMONTH(S6,0))-1,DAY(S6)=1),"Quincena",IF(OR(AND(DAY(S6)>=2,DAY(S6)<=5),AND(DAY(S6)>=17,DAY(S6)<=20)),"Días después del pago","Resto del mes")) -> Días después del pago | X6: =COUNTIF($S$5:$S$493,S6) -> 1 | Y6: =IF(X6>=20,"Sí","No") -> No | Z6: =CHOOSE(MATCH(B6,{"Customer Appreciation","Exclusive Offers","Flash Sale","Holiday Discounts","New Product Launch","Newsletter"},0),"Fidelizar","Vender","Vender","Vender","Lanzar","Educar") -> Vender | AA6: =IF(G6<100000,"Menos de 100 mil",IF(G6<200000,"100 a 200 mil",IF(G6<300000,"200 a 300 mil",IF(G6<400000,"300 a 400 mil","Más de 400 mil")))) -> Menos de 100 mil | AB6: =COUNTIFS($E$5:$E$493,E6,$S$5:$S$493,"<"&S6)+COUNTIFS($E$5:E6,E6,$S$5:S6,S6) -> 2 | AC6: =COUNTIF($E$5:$E$493,E6) -> 4 | AD6: =IF(AC6<8,"",IF(AB6<=AC6/3,"Primer tercio",IF(AB6>AC6*2/3,"Último tercio","Medio"))) | AE6: =M6-Q6 -> -4.8012204 | AF6: =" "&LOWER(SUBSTITUTE(SUBSTITUTE(SUBSTITUTE(SUBSTITUTE(SUBSTITUTE(SUBSTITUTE(SUBSTITUTE(E6,"¡"," "),"!"," "),"¿"," "),"?"," "),":"," "),","," "),"."," "))&" " -> últimas horas flash sale no te quedes sin tu descuento | AG6: =" "&LOWER(SUBSTITUTE(SUBSTITUTE(SUBSTITUTE(SUBSTITUTE(SUBSTITUTE(SUBSTITUTE(SUBSTITUTE(F6,"¡"," "),"!"," "),"¿"," "),"?"," "),":"," "),","," "),"."," "))&" " -> solo por hoy descuentos increíbles en tus favoritos compra ahora | AH6: =IF(SUMPRODUCT(--(LEFT(IF(LEFT(LOWER(E6),1)="¡",MID(LOWER(E6),2,300),LOWER(E6)),LEN({"actualizaci","el resumen","tu resumen","novedades l","oportunidad","tu oportunidad","ofertas de temporada","gran oferta","últimas horas","última oportunidad","presentamos","es hora de","descuentos imperdibles","descuentos que","un pequeño detalle"}))={"actualizaci","el resumen","tu resumen","novedades l","oportunidad","tu oportunidad","ofertas de temporada","gran oferta","últimas horas","última oportunidad","presentamos","es hora de","descuentos imperdibles","descuentos que","un pequeño detalle"}))>0,"Sí","No") -> Sí | AI6: =IF(OR(SUMPRODUCT(--ISNUMBER(SEARCH({"descuento","oferta","ahorr","precio"," sale ","flash","deals"},AF6)))>0,SUMPRODUCT(--ISNUMBER(SEARCH({"descuento","oferta","ahorr","precio"," sale ","flash","deals"},AG6)))>0),"Sí","No") -> Sí | AJ6: =IF(SUMPRODUCT(--ISNUMBER(SEARCH({" hoy ","horas","tiempo limitado","antes de que","se acab","se agot","finalic","última oportunidad","oportunidad única","relámpago","express","no esperes","no volver","no parpadees"},AF6)))>0,"Sí","No") -> Sí | AK6: =IF(SUMPRODUCT(--ISNUMBER(SEARCH({" hoy ","horas","tiempo limitado","antes de que","se acab","se agot","finalic","última oportunidad","oportunidad única","relámpago","express","no esperes","no volver","no parpadees"},AG6)))>0,"Sí","No") -> Sí | AL6: =IF(AI6="No","Sin descuento",IF(AJ6="Sí","Descuento con tiempo límite en el asunto",IF(AK6="Sí","Descuento con tiempo límite solo en el preheader","Descuento sin tiempo límite"))) -> Descuento con tiempo límite en el asunto | AM6: =IF(SUMPRODUCT(--ISNUMBER(SEARCH({"0","1","2","3","4","5","6","7","8","9","favorit","maquillaje","piel","cabello","productos","belleza","regalo"},E6)))>0,"Sí","No") -> No | AN6: =IF(SUMPRODUCT(--ISNUMBER(SEARCH({"lo que tenemos","estas ofertas","algo especial","ofertas únicas","que preparamos","no te quedes","echa un vistazo"},F6)))>0,"Sí","No") -> No | AO6: =LEN(E6)-(LEN(E6)-LEN(SUBSTITUTE(E6,"🔥","")))/LEN("🔥")*(LEN("🔥")-1) -> 57 | AP6: =LEN(TRIM(E6))-LEN(SUBSTITUTE(TRIM(E6)," ",""))+1 -> 10 | AQ6: =SUMPRODUCT(LEN(E6)-LEN(SUBSTITUTE(E6,{"!","¡","?","¿",":",",",".","%","·","-",";"},""))) -> 3 | AR6: =IF(AND(AO6<=60,AP6<=9,AQ6<=3,(LEN(E6)-LEN(SUBSTITUTE(E6,"🔥","")))/LEN("🔥")<=1),"Sí","No") -> No | AS6: =IF(ISNUMBER(SEARCH("hot sale",E6)),"Sí","No") -> No | AT6: =IF(SUMPRODUCT(--ISNUMBER(FIND({"0","1","2","3","4","5","6","7","8","9"},E6)))>0,"Con cifra concreta",IF(OR(ISNUMBER(FIND("?",E6)),ISNUMBER(FIND("¿",E6))),"Pregunta abierta",IF(SUMPRODUCT(--ISNUMBER(SEARCH({" hoy ","horas","tiempo limitado","antes de que","se acab","se agot","finalic","última oportunidad","oportunidad única","relámpago","express","no esperes","no volver","no parpadees"," ya ","últimas horas","últimas unidades"," ahora "},AF6)))>0,"Solo urgencia, sin cifra",IF(SUMPRODUCT(--ISNUMBER(SEARCH({"recompensa","sorpresa","regalo","lealtad","detalle","gracias","pensamos en ti","para ti"},E6)))>0,"Recompensa o sorpresa","Otro: beneficio o novedad")))) -> Solo urgencia, sin cifra
A7: EM-003 | B7: Newsletter | C7: 2025-08-20 | D7: 09:15:00 | E7: Tu dosis semanal de belleza: Novedades y tips | F7: Novedades, tips y más para tu rutina diaria. ¡Entra ya! | G7: 34780 | H7: 8253 | I7: 3224 | J7: 0.55 | K7: 0.67 | L7: 47581.07 | M7: =IFERROR(H7/G7*100,"") -> 23.729155 | N7: =IFERROR(I7/G7*100,"") -> 9.2696952 | O7: =IFERROR(I7/H7*100,"") -> 39.064583 | P7: =IFERROR(L7/G7*1000,"") -> 1368.0584 | Q7: =AVERAGEIF($E$5:$E$493,$E7,$M$5:$M$493) -> 22.891294 | R7: =AVERAGEIF($B$5:$B$493,$B7,$M$5:$M$493) -> 27.751365 | S7: =DATEVALUE(C7) -> 45889 | T7: =CHOOSE(MONTH(S7)-7,"Agosto","Septiembre","Octubre") -> Agosto | U7: =CHOOSE(WEEKDAY(S7,2),"Lunes","Martes","Miércoles","Jueves","Viernes","Sábado","Domingo") -> Miércoles | V7: =VALUE(LEFT(D7,2)) -> 9 | W7: =IF(OR(AND(DAY(S7)>=14,DAY(S7)<=16),DAY(S7)>=DAY(EOMONTH(S7,0))-1,DAY(S7)=1),"Quincena",IF(OR(AND(DAY(S7)>=2,DAY(S7)<=5),AND(DAY(S7)>=17,DAY(S7)<=20)),"Días después del pago","Resto del mes")) -> Días después del pago | X7: =COUNTIF($S$5:$S$493,S7) -> 2 | Y7: =IF(X7>=20,"Sí","No") -> No | Z7: =CHOOSE(MATCH(B7,{"Customer Appreciation","Exclusive Offers","Flash Sale","Holiday Discounts","New Product Launch","Newsletter"},0),"Fidelizar","Vender","Vender","Vender","Lanzar","Educar") -> Educar | AA7: =IF(G7<100000,"Menos de 100 mil",IF(G7<200000,"100 a 200 mil",IF(G7<300000,"200 a 300 mil",IF(G7<400000,"300 a 400 mil","Más de 400 mil")))) -> Menos de 100 mil | AB7: =COUNTIFS($E$5:$E$493,E7,$S$5:$S$493,"<"&S7)+COUNTIFS($E$5:E7,E7,$S$5:S7,S7) -> 4 | AC7: =COUNTIF($E$5:$E$493,E7) -> 22 | AD7: =IF(AC7<8,"",IF(AB7<=AC7/3,"Primer tercio",IF(AB7>AC7*2/3,"Último tercio","Medio"))) -> Primer tercio | AE7: =M7-Q7 -> 0.83786086 | AF7: =" "&LOWER(SUBSTITUTE(SUBSTITUTE(SUBSTITUTE(SUBSTITUTE(SUBSTITUTE(SUBSTITUTE(SUBSTITUTE(E7,"¡"," "),"!"," "),"¿"," "),"?"," "),":"," "),","," "),"."," "))&" " -> tu dosis semanal de belleza novedades y tips | AG7: =" "&LOWER(SUBSTITUTE(SUBSTITUTE(SUBSTITUTE(SUBSTITUTE(SUBSTITUTE(SUBSTITUTE(SUBSTITUTE(F7,"¡"," "),"!"," "),"¿"," "),"?"," "),":"," "),","," "),"."," "))&" " -> novedades tips y más para tu rutina diaria entra ya | AH7: =IF(SUMPRODUCT(--(LEFT(IF(LEFT(LOWER(E7),1)="¡",MID(LOWER(E7),2,300),LOWER(E7)),LEN({"actualizaci","el resumen","tu resumen","novedades l","oportunidad","tu oportunidad","ofertas de temporada","gran oferta","últimas horas","última oportunidad","presentamos","es hora de","descuentos imperdibles","descuentos que","un pequeño detalle"}))={"actualizaci","el resumen","tu resumen","novedades l","oportunidad","tu oportunidad","ofertas de temporada","gran oferta","últimas horas","última oportunidad","presentamos","es hora de","descuentos imperdibles","descuentos que","un pequeño detalle"}))>0,"Sí","No") -> No | AI7: =IF(OR(SUMPRODUCT(--ISNUMBER(SEARCH({"descuento","oferta","ahorr","precio"," sale ","flash","deals"},AF7)))>0,SUMPRODUCT(--ISNUMBER(SEARCH({"descuento","oferta","ahorr","precio"," sale ","flash","deals"},AG7)))>0),"Sí","No") -> No | AJ7: =IF(SUMPRODUCT(--ISNUMBER(SEARCH({" hoy ","horas","tiempo limitado","antes de que","se acab","se agot","finalic","última oportunidad","oportunidad única","relámpago","express","no esperes","no volver","no parpadees"},AF7)))>0,"Sí","No") -> No | AK7: =IF(SUMPRODUCT(--ISNUMBER(SEARCH({" hoy ","horas","tiempo limitado","antes de que","se acab","se agot","finalic","última oportunidad","oportunidad única","relámpago","express","no esperes","no volver","no parpadees"},AG7)))>0,"Sí","No") -> No | AL7: =IF(AI7="No","Sin descuento",IF(AJ7="Sí","Descuento con tiempo límite en el asunto",IF(AK7="Sí","Descuento con tiempo límite solo en el preheader","Descuento sin tiempo límite"))) -> Sin descuento | AM7: =IF(SUMPRODUCT(--ISNUMBER(SEARCH({"0","1","2","3","4","5","6","7","8","9","favorit","maquillaje","piel","cabello","productos","belleza","regalo"},E7)))>0,"Sí","No") -> Sí | AN7: =IF(SUMPRODUCT(--ISNUMBER(SEARCH({"lo que tenemos","estas ofertas","algo especial","ofertas únicas","que preparamos","no te quedes","echa un vistazo"},F7)))>0,"Sí","No") -> No | AO7: =LEN(E7)-(LEN(E7)-LEN(SUBSTITUTE(E7,"🔥","")))/LEN("🔥")*(LEN("🔥")-1) -> 45 | AP7: =LEN(TRIM(E7))-LEN(SUBSTITUTE(TRIM(E7)," ",""))+1 -> 8 | AQ7: =SUMPRODUCT(LEN(E7)-LEN(SUBSTITUTE(E7,{"!","¡","?","¿",":",",",".","%","·","-",";"},""))) -> 1 | AR7: =IF(AND(AO7<=60,AP7<=9,AQ7<=3,(LEN(E7)-LEN(SUBSTITUTE(E7,"🔥","")))/LEN("🔥")<=1),"Sí","No") -> Sí | AS7: =IF(ISNUMBER(SEARCH("hot sale",E7)),"Sí","No") -> No | AT7: =IF(SUMPRODUCT(--ISNUMBER(FIND({"0","1","2","3","4","5","6","7","8","9"},E7)))>0,"Con cifra concreta",IF(OR(ISNUMBER(FIND("?",E7)),ISNUMBER(FIND("¿",E7))),"Pregunta abierta",IF(SUMPRODUCT(--ISNUMBER(SEARCH({" hoy ","horas","tiempo limitado","antes de que","se acab","se agot","finalic","última oportunidad","oportunidad única","relámpago","express","no esperes","no volver","no parpadees"," ya ","últimas horas","últimas unidades"," ahora "},AF7)))>0,"Solo urgencia, sin cifra",IF(SUMPRODUCT(--ISNUMBER(SEARCH({"recompensa","sorpresa","regalo","lealtad","detalle","gracias","pensamos en ti","para ti"},E7)))>0,"Recompensa o sorpresa","Otro: beneficio o novedad")))) -> Otro: beneficio o novedad
A8: EM-004 | B8: Flash Sale | C8: 2025-10-28 | D8: 11:45:00 | E8: ¡Ahorra YA! Flash Sale: Hasta 50% en tus favoritos | F8: Edición limitada: Maquillaje, cuidado de piel y más. ¡Corre! | G8: 163962 | H8: 80696 | I8: 17739 | J8: 6.25 | K8: 3.75 | L8: 55342.07 | M8: =IFERROR(H8/G8*100,"") -> 49.216282 | N8: =IFERROR(I8/G8*100,"") -> 10.81897 | O8: =IFERROR(I8/H8*100,"") -> 21.982502 | P8: =IFERROR(L8/G8*1000,"") -> 337.52985 | Q8: =AVERAGEIF($E$5:$E$493,$E8,$M$5:$M$493) -> 41.593593 | R8: =AVERAGEIF($B$5:$B$493,$B8,$M$5:$M$493) -> 29.440902 | S8: =DATEVALUE(C8) -> 45958 | T8: =CHOOSE(MONTH(S8)-7,"Agosto","Septiembre","Octubre") -> Octubre | U8: =CHOOSE(WEEKDAY(S8,2),"Lunes","Martes","Miércoles","Jueves","Viernes","Sábado","Domingo") -> Martes | V8: =VALUE(LEFT(D8,2)) -> 11 | W8: =IF(OR(AND(DAY(S8)>=14,DAY(S8)<=16),DAY(S8)>=DAY(EOMONTH(S8,0))-1,DAY(S8)=1),"Quincena",IF(OR(AND(DAY(S8)>=2,DAY(S8)<=5),AND(DAY(S8)>=17,DAY(S8)<=20)),"Días después del pago","Resto del mes")) -> Resto del mes | X8: =COUNTIF($S$5:$S$493,S8) -> 2 | Y8: =IF(X8>=20,"Sí","No") -> No | Z8: =CHOOSE(MATCH(B8,{"Customer Appreciation","Exclusive Offers","Flash Sale","Holiday Discounts","New Product Launch","Newsletter"},0),"Fidelizar","Vender","Vender","Vender","Lanzar","Educar") -> Vender | AA8: =IF(G8<100000,"Menos de 100 mil",IF(G8<200000,"100 a 200 mil",IF(G8<300000,"200 a 300 mil",IF(G8<400000,"300 a 400 mil","Más de 400 mil")))) -> 100 a 200 mil | AB8: =COUNTIFS($E$5:$E$493,E8,$S$5:$S$493,"<"&S8)+COUNTIFS($E$5:E8,E8,$S$5:S8,S8) -> 19 | AC8: =COUNTIF($E$5:$E$493,E8) -> 21 | AD8: =IF(AC8<8,"",IF(AB8<=AC8/3,"Primer tercio",IF(AB8>AC8*2/3,"Último tercio","Medio"))) -> Último tercio | AE8: =M8-Q8 -> 7.6226888 | AF8: =" "&LOWER(SUBSTITUTE(SUBSTITUTE(SUBSTITUTE(SUBSTITUTE(SUBSTITUTE(SUBSTITUTE(SUBSTITUTE(E8,"¡"," "),"!"," "),"¿"," "),"?"," "),":"," "),","," "),"."," "))&" " -> ahorra ya flash sale hasta 50% en tus favoritos | AG8: =" "&LOWER(SUBSTITUTE(SUBSTITUTE(SUBSTITUTE(SUBSTITUTE(SUBSTITUTE(SUBSTITUTE(SUBSTITUTE(F8,"¡"," "),"!"," "),"¿"," "),"?"," "),":"," "),","," "),"."," "))&" " -> edición limitada maquillaje cuidado de piel y más corre | AH8: =IF(SUMPRODUCT(--(LEFT(IF(LEFT(LOWER(E8),1)="¡",MID(LOWER(E8),2,300),LOWER(E8)),LEN({"actualizaci","el resumen","tu resumen","novedades l","oportunidad","tu oportunidad","ofertas de temporada","gran oferta","últimas horas","última oportunidad","presentamos","es hora de","descuentos imperdibles","descuentos que","un pequeño detalle"}))={"actualizaci","el resumen","tu resumen","novedades l","oportunidad","tu oportunidad","ofertas de temporada","gran oferta","últimas horas","última oportunidad","presentamos","es hora de","descuentos imperdibles","descuentos que","un pequeño detalle"}))>0,"Sí","No") -> No | AI8: =IF(OR(SUMPRODUCT(--ISNUMBER(SEARCH({"descuento","oferta","ahorr","precio"," sale ","flash","deals"},AF8)))>0,SUMPRODUCT(--ISNUMBER(SEARCH({"descuento","oferta","ahorr","precio"," sale ","flash","deals"},AG8)))>0),"Sí","No") -> Sí | AJ8: =IF(SUMPRODUCT(--ISNUMBER(SEARCH({" hoy ","horas","tiempo limitado","antes de que","se acab","se agot","finalic","última oportunidad","oportunidad única","relámpago","express","no esperes","no volver","no parpadees"},AF8)))>0,"Sí","No") -> No | AK8: =IF(SUMPRODUCT(--ISNUMBER(SEARCH({" hoy ","horas","tiempo limitado","antes de que","se acab","se agot","finalic","última oportunidad","oportunidad única","relámpago","express","no esperes","no volver","no parpadees"},AG8)))>0,"Sí","No") -> No | AL8: =IF(AI8="No","Sin descuento",IF(AJ8="Sí","Descuento con tiempo límite en el asunto",IF(AK8="Sí","Descuento con tiempo límite solo en el preheader","Descuento sin tiempo límite"))) -> Descuento sin tiempo límite | AM8: =IF(SUMPRODUCT(--ISNUMBER(SEARCH({"0","1","2","3","4","5","6","7","8","9","favorit","maquillaje","piel","cabello","productos","belleza","regalo"},E8)))>0,"Sí","No") -> Sí | AN8: =IF(SUMPRODUCT(--ISNUMBER(SEARCH({"lo que tenemos","estas ofertas","algo especial","ofertas únicas","que preparamos","no te quedes","echa un vistazo"},F8)))>0,"Sí","No") -> No | AO8: =LEN(E8)-(LEN(E8)-LEN(SUBSTITUTE(E8,"🔥","")))/LEN("🔥")*(LEN("🔥")-1) -> 50 | AP8: =LEN(TRIM(E8))-LEN(SUBSTITUTE(TRIM(E8)," ",""))+1 -> 9 | AQ8: =SUMPRODUCT(LEN(E8)-LEN(SUBSTITUTE(E8,{"!","¡","?","¿",":",",",".","%","·","-",";"},""))) -> 4 | AR8: =IF(AND(AO8<=60,AP8<=9,AQ8<=3,(LEN(E8)-LEN(SUBSTITUTE(E8,"🔥","")))/LEN("🔥")<=1),"Sí","No") -> No | AS8: =IF(ISNUMBER(SEARCH("hot sale",E8)),"Sí","No") -> No | AT8: =IF(SUMPRODUCT(--ISNUMBER(FIND({"0","1","2","3","4","5","6","7","8","9"},E8)))>0,"Con cifra concreta",IF(OR(ISNUMBER(FIND("?",E8)),ISNUMBER(FIND("¿",E8))),"Pregunta abierta",IF(SUMPRODUCT(--ISNUMBER(SEARCH({" hoy ","horas","tiempo limitado","antes de que","se acab","se agot","finalic","última oportunidad","oportunidad única","relámpago","express","no esperes","no volver","no parpadees"," ya ","últimas horas","últimas unidades"," ahora "},AF8)))>0,"Solo urgencia, sin cifra",IF(SUMPRODUCT(--ISNUMBER(SEARCH({"recompensa","sorpresa","regalo","lealtad","detalle","gracias","pensamos en ti","para ti"},E8)))>0,"Recompensa o sorpresa","Otro: beneficio o novedad")))) -> Con cifra concreta
A9: EM-005 | B9: Customer Appreciation | C9: 2025-09-10 | D9: 16:00:00 | E9: Para ti, con cariño: ¡Descubre tu regalo exclusivo! | F9: Tu código exclusivo te espera adentro. ¡No te lo pierdas! | G9: 259551 | H9: 70275 | I9: 13237 | J9: 5.78 | K9: 2.04 | L9: 51666.46 | M9: =IFERROR(H9/G9*100,"") -> 27.075604 | N9: =IFERROR(I9/G9*100,"") -> 5.0999611 | O9: =IFERROR(I9/H9*100,"") -> 18.836001 | P9: =IFERROR(L9/G9*1000,"") -> 199.06092 | Q9: =AVERAGEIF($E$5:$E$493,$E9,$M$5:$M$493) -> 27.075604 | R9: =AVERAGEIF($B$5:$B$493,$B9,$M$5:$M$493) -> 31.113651 | S9: =DATEVALUE(C9) -> 45910 | T9: =CHOOSE(MONTH(S9)-7,"Agosto","Septiembre","Octubre") -> Septiembre | U9: =CHOOSE(WEEKDAY(S9,2),"Lunes","Martes","Miércoles","Jueves","Viernes","Sábado","Domingo") -> Miércoles | V9: =VALUE(LEFT(D9,2)) -> 16 | W9: =IF(OR(AND(DAY(S9)>=14,DAY(S9)<=16),DAY(S9)>=DAY(EOMONTH(S9,0))-1,DAY(S9)=1),"Quincena",IF(OR(AND(DAY(S9)>=2,DAY(S9)<=5),AND(DAY(S9)>=17,DAY(S9)<=20)),"Días después del pago","Resto del mes")) -> Resto del mes | X9: =COUNTIF($S$5:$S$493,S9) -> 2 | Y9: =IF(X9>=20,"Sí","No") -> No | Z9: =CHOOSE(MATCH(B9,{"Customer Appreciation","Exclusive Offers","Flash Sale","Holiday Discounts","New Product Launch","Newsletter"},0),"Fidelizar","Vender","Vender","Vender","Lanzar","Educar") -> Fidelizar | AA9: =IF(G9<100000,"Menos de 100 mil",IF(G9<200000,"100 a 200 mil",IF(G9<300000,"200 a 300 mil",IF(G9<400000,"300 a 400 mil","Más de 400 mil")))) -> 200 a 300 mil | AB9: =COUNTIFS($E$5:$E$493,E9,$S$5:$S$493,"<"&S9)+COUNTIFS($E$5:E9,E9,$S$5:S9,S9) -> 1 | AC9: =COUNTIF($E$5:$E$493,E9) -> 1 | AD9: =IF(AC9<8,"",IF(AB9<=AC9/3,"Primer tercio",IF(AB9>AC9*2/3,"Último tercio","Medio"))) | AE9: =M9-Q9 -> 0 | AF9: =" "&LOWER(SUBSTITUTE(SUBSTITUTE(SUBSTITUTE(SUBSTITUTE(SUBSTITUTE(SUBSTITUTE(SUBSTITUTE(E9,"¡"," "),"!"," "),"¿"," "),"?"," "),":"," "),","," "),"."," "))&" " -> para ti con cariño descubre tu regalo exclusivo | AG9: =" "&LOWER(SUBSTITUTE(SUBSTITUTE(SUBSTITUTE(SUBSTITUTE(SUBSTITUTE(SUBSTITUTE(SUBSTITUTE(F9,"¡"," "),"!"," "),"¿"," "),"?"," "),":"," "),","," "),"."," "))&" " -> tu código exclusivo te espera adentro no te lo pierdas | AH9: =IF(SUMPRODUCT(--(LEFT(IF(LEFT(LOWER(E9),1)="¡",MID(LOWER(E9),2,300),LOWER(E9)),LEN({"actualizaci","el resumen","tu resumen","novedades l","oportunidad","tu oportunidad","ofertas de temporada","gran oferta","últimas horas","última oportunidad","presentamos","es hora de","descuentos imperdibles","descuentos que","un pequeño detalle"}))={"actualizaci","el resumen","tu resumen","novedades l","oportunidad","tu oportunidad","ofertas de temporada","gran oferta","últimas horas","última oportunidad","presentamos","es hora de","descuentos imperdibles","descuentos que","un pequeño detalle"}))>0,"Sí","No") -> No | AI9: =IF(OR(SUMPRODUCT(--ISNUMBER(SEARCH({"descuento","oferta","ahorr","precio"," sale ","flash","deals"},AF9)))>0,SUMPRODUCT(--ISNUMBER(SEARCH({"descuento","oferta","ahorr","precio"," sale ","flash","deals"},AG9)))>0),"Sí","No") -> No | AJ9: =IF(SUMPRODUCT(--ISNUMBER(SEARCH({" hoy ","horas","tiempo limitado","antes de que","se acab","se agot","finalic","última oportunidad","oportunidad única","relámpago","express","no esperes","no volver","no parpadees"},AF9)))>0,"Sí","No") -> No | AK9: =IF(SUMPRODUCT(--ISNUMBER(SEARCH({" hoy ","horas","tiempo limitado","antes de que","se acab","se agot","finalic","última oportunidad","oportunidad única","relámpago","express","no esperes","no volver","no parpadees"},AG9)))>0,"Sí","No") -> No | AL9: =IF(AI9="No","Sin descuento",IF(AJ9="Sí","Descuento con tiempo límite en el asunto",IF(AK9="Sí","Descuento con tiempo límite solo en el preheader","Descuento sin tiempo límite"))) -> Sin descuento | AM9: =IF(SUMPRODUCT(--ISNUMBER(SEARCH({"0","1","2","3","4","5","6","7","8","9","favorit","maquillaje","piel","cabello","productos","belleza","regalo"},E9)))>0,"Sí","No") -> Sí | AN9: =IF(SUMPRODUCT(--ISNUMBER(SEARCH({"lo que tenemos","estas ofertas","algo especial","ofertas únicas","que preparamos","no te quedes","echa un vistazo"},F9)))>0,"Sí","No") -> No | AO9: =LEN(E9)-(LEN(E9)-LEN(SUBSTITUTE(E9,"🔥","")))/LEN("🔥")*(LEN("🔥")-1) -> 51 | AP9: =LEN(TRIM(E9))-LEN(SUBSTITUTE(TRIM(E9)," ",""))+1 -> 8 | AQ9: =SUMPRODUCT(LEN(E9)-LEN(SUBSTITUTE(E9,{"!","¡","?","¿",":",",",".","%","·","-",";"},""))) -> 4 | AR9: =IF(AND(AO9<=60,AP9<=9,AQ9<=3,(LEN(E9)-LEN(SUBSTITUTE(E9,"🔥","")))/LEN("🔥")<=1),"Sí","No") -> No | AS9: =IF(ISNUMBER(SEARCH("hot sale",E9)),"Sí","No") -> No | AT9: =IF(SUMPRODUCT(--ISNUMBER(FIND({"0","1","2","3","4","5","6","7","8","9"},E9)))>0,"Con cifra concreta",IF(OR(ISNUMBER(FIND("?",E9)),ISNUMBER(FIND("¿",E9))),"Pregunta abierta",IF(SUMPRODUCT(--ISNUMBER(SEARCH({" hoy ","horas","tiempo limitado","antes de que","se acab","se agot","finalic","última oportunidad","oportunidad única","relámpago","express","no esperes","no volver","no parpadees"," ya ","últimas horas","últimas unidades"," ahora "},AF9)))>0,"Solo urgencia, sin cifra",IF(SUMPRODUCT(--ISNUMBER(SEARCH({"recompensa","sorpresa","regalo","lealtad","detalle","gracias","pensamos en ti","para ti"},E9)))>0,"Recompensa o sorpresa","Otro: beneficio o novedad")))) -> Recompensa o sorpresa
A10: EM-007 | B10: Exclusive Offers | C10: 2025-10-01 | D10: 13:30:00 | E10: ¡Ofertas Exclusivas! Solo para nuestra comunidad VIP | F10: Productos premium con descuentos únicos. ¡Acceso limitado! | G10: 266500 | H10: 72365 | I10: 42023 | J10: 5.56 | K10: 4.48 | L10: 57418.39 | M10: =IFERROR(H10/G10*100,"") -> 27.153846 | N10: =IFERROR(I10/G10*100,"") -> 15.76848 | O10: =IFERROR(I10/H10*100,"") -> 58.070891 | P10: =IFERROR(L10/G10*1000,"") -> 215.45362 | Q10: =AVERAGEIF($E$5:$E$493,$E10,$M$5:$M$493) -> 33.047231 | R10: =AVERAGEIF($B$5:$B$493,$B10,$M$5:$M$493) -> 27.021448 | S10: =DATEVALUE(C10) -> 45931 | T10: =CHOOSE(MONTH(S10)-7,"Agosto","Septiembre","Octubre") -> Octubre | U10: =CHOOSE(WEEKDAY(S10,2),"Lunes","Martes","Miércoles","Jueves","Viernes","Sábado","Domingo") -> Miércoles | V10: =VALUE(LEFT(D10,2)) -> 13 | W10: =IF(OR(AND(DAY(S10)>=14,DAY(S10)<=16),DAY(S10)>=DAY(EOMONTH(S10,0))-1,DAY(S10)=1),"Quincena",IF(OR(AND(DAY(S10)>=2,DAY(S10)<=5),AND(DAY(S10)>=17,DAY(S10)<=20)),"Días después del pago","Resto del mes")) -> Quincena | X10: =COUNTIF($S$5:$S$493,S10) -> 1 | Y10: =IF(X10>=20,"Sí","No") -> No | Z10: =CHOOSE(MATCH(B10,{"Customer Appreciation","Exclusive Offers","Flash Sale","Holiday Discounts","New Product Launch","Newsletter"},0),"Fidelizar","Vender","Vender","Vender","Lanzar","Educar") -> Vender | AA10: =IF(G10<100000,"Menos de 100 mil",IF(G10<200000,"100 a 200 mil",IF(G10<300000,"200 a 300 mil",IF(G10<400000,"300 a 400 mil","Más de 400 mil")))) -> 200 a 300 mil | AB10: =COUNTIFS($E$5:$E$493,E10,$S$5:$S$493,"<"&S10)+COUNTIFS($E$5:E10,E10,$S$5:S10,S10) -> 13 | AC10: =COUNTIF($E$5:$E$493,E10) -> 22 | AD10: =IF(AC10<8,"",IF(AB10<=AC10/3,"Primer tercio",IF(AB10>AC10*2/3,"Último tercio","Medio"))) -> Medio | AE10: =M10-Q10 -> -5.8933846 | AF10: =" "&LOWER(SUBSTITUTE(SUBSTITUTE(SUBSTITUTE(SUBSTITUTE(SUBSTITUTE(SUBSTITUTE(SUBSTITUTE(E10,"¡"," "),"!"," "),"¿"," "),"?"," "),":"," "),","," "),"."," "))&" " -> ofertas exclusivas solo para nuestra comunidad vip | AG10: =" "&LOWER(SUBSTITUTE(SUBSTITUTE(SUBSTITUTE(SUBSTITUTE(SUBSTITUTE(SUBSTITUTE(SUBSTITUTE(F10,"¡"," "),"!"," "),"¿"," "),"?"," "),":"," "),","," "),"."," "))&" " -> productos premium con descuentos únicos acceso limitado | AH10: =IF(SUMPRODUCT(--(LEFT(IF(LEFT(LOWER(E10),1)="¡",MID(LOWER(E10),2,300),LOWER(E10)),LEN({"actualizaci","el resumen","tu resumen","novedades l","oportunidad","tu oportunidad","ofertas de temporada","gran oferta","últimas horas","última oportunidad","presentamos","es hora de","descuentos imperdibles","descuentos que","un pequeño detalle"}))={"actualizaci","el resumen","tu resumen","novedades l","oportunidad","tu oportunidad","ofertas de temporada","gran oferta","últimas horas","última oportunidad","presentamos","es hora de","descuentos imperdibles","descuentos que","un pequeño detalle"}))>0,"Sí","No") -> No | AI10: =IF(OR(SUMPRODUCT(--ISNUMBER(SEARCH({"descuento","oferta","ahorr","precio"," sale ","flash","deals"},AF10)))>0,SUMPRODUCT(--ISNUMBER(SEARCH({"descuento","oferta","ahorr","precio"," sale ","flash","deals"},AG10)))>0),"Sí","No") -> Sí | AJ10: =IF(SUMPRODUCT(--ISNUMBER(SEARCH({" hoy ","horas","tiempo limitado","antes de que","se acab","se agot","finalic","última oportunidad","oportunidad única","relámpago","express","no esperes","no volver","no parpadees"},AF10)))>0,"Sí","No") -> No | AK10: =IF(SUMPRODUCT(--ISNUMBER(SEARCH({" hoy ","horas","tiempo limitado","antes de que","se acab","se agot","finalic","última oportunidad","oportunidad única","relámpago","express","no esperes","no volver","no parpadees"},AG10)))>0,"Sí","No") -> No | AL10: =IF(AI10="No","Sin descuento",IF(AJ10="Sí","Descuento con tiempo límite en el asunto",IF(AK10="Sí","Descuento con tiempo límite solo en el preheader","Descuento sin tiempo límite"))) -> Descuento sin tiempo límite | AM10: =IF(SUMPRODUCT(--ISNUMBER(SEARCH({"0","1","2","3","4","5","6","7","8","9","favorit","maquillaje","piel","cabello","productos","belleza","regalo"},E10)))>0,"Sí","No") -> No | AN10: =IF(SUMPRODUCT(--ISNUMBER(SEARCH({"lo que tenemos","estas ofertas","algo especial","ofertas únicas","que preparamos","no te quedes","echa un vistazo"},F10)))>0,"Sí","No") -> No | AO10: =LEN(E10)-(LEN(E10)-LEN(SUBSTITUTE(E10,"🔥","")))/LEN("🔥")*(LEN("🔥")-1) -> 52 | AP10: =LEN(TRIM(E10))-LEN(SUBSTITUTE(TRIM(E10)," ",""))+1 -> 7 | AQ10: =SUMPRODUCT(LEN(E10)-LEN(SUBSTITUTE(E10,{"!","¡","?","¿",":",",",".","%","·","-",";"},""))) -> 2 | AR10: =IF(AND(AO10<=60,AP10<=9,AQ10<=3,(LEN(E10)-LEN(SUBSTITUTE(E10,"🔥","")))/LEN("🔥")<=1),"Sí","No") -> Sí | AS10: =IF(ISNUMBER(SEARCH("hot sale",E10)),"Sí","No") -> No | AT10: =IF(SUMPRODUCT(--ISNUMBER(FIND({"0","1","2","3","4","5","6","7","8","9"},E10)))>0,"Con cifra concreta",IF(OR(ISNUMBER(FIND("?",E10)),ISNUMBER(FIND("¿",E10))),"Pregunta abierta",IF(SUMPRODUCT(--ISNUMBER(SEARCH({" hoy ","horas","tiempo limitado","antes de que","se acab","se agot","finalic","última oportunidad","oportunidad única","relámpago","express","no esperes","no volver","no parpadees"," ya ","últimas horas","últimas unidades"," ahora "},AF10)))>0,"Solo urgencia, sin cifra",IF(SUMPRODUCT(--ISNUMBER(SEARCH({"recompensa","sorpresa","regalo","lealtad","detalle","gracias","pensamos en ti","para ti"},E10)))>0,"Recompensa o sorpresa","Otro: beneficio o novedad")))) -> Otro: beneficio o novedad
A11: EM-008 | B11: Flash Sale | C11: 2025-09-18 | D11: 12:15:00 | E11: Prepárate para un Ahorro Épico: ¡Flash Sale en todo! | F11: Tus productos favoritos con un precio que te encantará. ¡Entra ya! | G11: 488415 | H11: 164923 | I11: 46845 | J11: 6.74 | K11: 4.35 | L11: 78459.67 | M11: =IFERROR(H11/G11*100,"") -> 33.766981 | N11: =IFERROR(I11/G11*100,"") -> 9.5912288 | O11: =IFERROR(I11/H11*100,"") -> 28.404164 | P11: =IFERROR(L11/G11*1000,"") -> 160.6414 | Q11: =AVERAGEIF($E$5:$E$493,$E11,$M$5:$M$493) -> 30.716242 | R11: =AVERAGEIF($B$5:$B$493,$B11,$M$5:$M$493) -> 29.440902 | S11: =DATEVALUE(C11) -> 45918 | T11: =CHOOSE(MONTH(S11)-7,"Agosto","Septiembre","Octubre") -> Septiembre | U11: =CHOOSE(WEEKDAY(S11,2),"Lunes","Martes","Miércoles","Jueves","Viernes","Sábado","Domingo") -> Jueves | V11: =VALUE(LEFT(D11,2)) -> 12 | W11: =IF(OR(AND(DAY(S11)>=14,DAY(S11)<=16),DAY(S11)>=DAY(EOMONTH(S11,0))-1,DAY(S11)=1),"Quincena",IF(OR(AND(DAY(S11)>=2,DAY(S11)<=5),AND(DAY(S11)>=17,DAY(S11)<=20)),"Días después del pago","Resto del mes")) -> Días después del pago | X11: =COUNTIF($S$5:$S$493,S11) -> 1 | Y11: =IF(X11>=20,"Sí","No") -> No | Z11: =CHOOSE(MATCH(B11,{"Customer Appreciation","Exclusive Offers","Flash Sale","Holiday Discounts","New Product Launch","Newsletter"},0),"Fidelizar","Vender","Vender","Vender","Lanzar","Educar") -> Vender | AA11: =IF(G11<100000,"Menos de 100 mil",IF(G11<200000,"100 a 200 mil",IF(G11<300000,"200 a 300 mil",IF(G11<400000,"300 a 400 mil","Más de 400 mil")))) -> Más de 400 mil | AB11: =COUNTIFS($E$5:$E$493,E11,$S$5:$S$493,"<"&S11)+COUNTIFS($E$5:E11,E11,$S$5:S11,S11) -> 2 | AC11: =COUNTIF($E$5:$E$493,E11) -> 2 | AD11: =IF(AC11<8,"",IF(AB11<=AC11/3,"Primer tercio",IF(AB11>AC11*2/3,"Último tercio","Medio"))) | AE11: =M11-Q11 -> 3.0507393 | AF11: =" "&LOWER(SUBSTITUTE(SUBSTITUTE(SUBSTITUTE(SUBSTITUTE(SUBSTITUTE(SUBSTITUTE(SUBSTITUTE(E11,"¡"," "),"!"," "),"¿"," "),"?"," "),":"," "),","," "),"."," "))&" " -> prepárate para un ahorro épico flash sale en todo | AG11: =" "&LOWER(SUBSTITUTE(SUBSTITUTE(SUBSTITUTE(SUBSTITUTE(SUBSTITUTE(SUBSTITUTE(SUBSTITUTE(F11,"¡"," "),"!"," "),"¿"," "),"?"," "),":"," "),","," "),"."," "))&" " -> tus productos favoritos con un precio que te encantará entra ya | AH11: =IF(SUMPRODUCT(--(LEFT(IF(LEFT(LOWER(E11),1)="¡",MID(LOWER(E11),2,300),LOWER(E11)),LEN({"actualizaci","el resumen","tu resumen","novedades l","oportunidad","tu oportunidad","ofertas de temporada","gran oferta","últimas horas","última oportunidad","presentamos","es hora de","descuentos imperdibles","descuentos que","un pequeño detalle"}))={"actualizaci","el resumen","tu resumen","novedades l","oportunidad","tu oportunidad","ofertas de temporada","gran oferta","últimas horas","última oportunidad","presentamos","es hora de","descuentos imperdibles","descuentos que","un pequeño detalle"}))>0,"Sí","No") -> No | AI11: =IF(OR(SUMPRODUCT(--ISNUMBER(SEARCH({"descuento","oferta","ahorr","precio"," sale ","flash","deals"},AF11)))>0,SUMPRODUCT(--ISNUMBER(SEARCH({"descuento","oferta","ahorr","precio"," sale ","flash","deals"},AG11)))>0),"Sí","No") -> Sí | AJ11: =IF(SUMPRODUCT(--ISNUMBER(SEARCH({" hoy ","horas","tiempo limitado","antes de que","se acab","se agot","finalic","última oportunidad","oportunidad única","relámpago","express","no esperes","no volver","no parpadees"},AF11)))>0,"Sí","No") -> No | AK11: =IF(SUMPRODUCT(--ISNUMBER(SEARCH({" hoy ","horas","tiempo limitado","antes de que","se acab","se agot","finalic","última oportunidad","oportunidad única","relámpago","express","no esperes","no volver","no parpadees"},AG11)))>0,"Sí","No") -> No | AL11: =IF(AI11="No","Sin descuento",IF(AJ11="Sí","Descuento con tiempo límite en el asunto",IF(AK11="Sí","Descuento con tiempo límite solo en el preheader","Descuento sin tiempo límite"))) -> Descuento sin tiempo límite | AM11: =IF(SUMPRODUCT(--ISNUMBER(SEARCH({"0","1","2","3","4","5","6","7","8","9","favorit","maquillaje","piel","cabello","productos","belleza","regalo"},E11)))>0,"Sí","No") -> No | AN11: =IF(SUMPRODUCT(--ISNUMBER(SEARCH({"lo que tenemos","estas ofertas","algo especial","ofertas únicas","que preparamos","no te quedes","echa un vistazo"},F11)))>0,"Sí","No") -> No | AO11: =LEN(E11)-(LEN(E11)-LEN(SUBSTITUTE(E11,"🔥","")))/LEN("🔥")*(LEN("🔥")-1) -> 52 | AP11: =LEN(TRIM(E11))-LEN(SUBSTITUTE(TRIM(E11)," ",""))+1 -> 9 | AQ11: =SUMPRODUCT(LEN(E11)-LEN(SUBSTITUTE(E11,{"!","¡","?","¿",":",",",".","%","·","-",";"},""))) -> 3 | AR11: =IF(AND(AO11<=60,AP11<=9,AQ11<=3,(LEN(E11)-LEN(SUBSTITUTE(E11,"🔥","")))/LEN("🔥")<=1),"Sí","No") -> Sí | AS11: =IF(ISNUMBER(SEARCH("hot sale",E11)),"Sí","No") -> No | AT11: =IF(SUMPRODUCT(--ISNUMBER(FIND({"0","1","2","3","4","5","6","7","8","9"},E11)))>0,"Con cifra concreta",IF(OR(ISNUMBER(FIND("?",E11)),ISNUMBER(FIND("¿",E11))),"Pregunta abierta",IF(SUMPRODUCT(--ISNUMBER(SEARCH({" hoy ","horas","tiempo limitado","antes de que","se acab","se agot","finalic","última oportunidad","oportunidad única","relámpago","express","no esperes","no volver","no parpadees"," ya ","últimas horas","últimas unidades"," ahora "},AF11)))>0,"Solo urgencia, sin cifra",IF(SUMPRODUCT(--ISNUMBER(SEARCH({"recompensa","sorpresa","regalo","lealtad","detalle","gracias","pensamos en ti","para ti"},E11)))>0,"Recompensa o sorpresa","Otro: beneficio o novedad")))) -> Otro: beneficio o novedad
A12: EM-009 | B12: New Product Launch | C12: 2025-08-25 | D12: 11:00:00 | E12: Presentamos: Nuestro último lanzamiento de belleza ¡Imperdible! | F12: Una innovación que cambiará tu rutina. ¡Sé de los primeros! | G12: 87060 | H12: 16367 | I12: 7287 | J12: 3.21 | K12: 4.77 | L12: 81300.96 | M12: =IFERROR(H12/G12*100,"") -> 18.799678 | N12: =IFERROR(I12/G12*100,"") -> 8.3700896 | O12: =IFERROR(I12/H12*100,"") -> 44.522515 | P12: =IFERROR(L12/G12*1000,"") -> 933.84976 | Q12: =AVERAGEIF($E$5:$E$493,$E12,$M$5:$M$493) -> 23.315841 | R12: =AVERAGEIF($B$5:$B$493,$B12,$M$5:$M$493) -> 29.458248 | S12: =DATEVALUE(C12) -> 45894 | T12: =CHOOSE(MONTH(S12)-7,"Agosto","Septiembre","Octubre") -> Agosto | U12: =CHOOSE(WEEKDAY(S12,2),"Lunes","Martes","Miércoles","Jueves","Viernes","Sábado","Domingo") -> Lunes | V12: =VALUE(LEFT(D12,2)) -> 11 | W12: =IF(OR(AND(DAY(S12)>=14,DAY(S12)<=16),DAY(S12)>=DAY(EOMONTH(S12,0))-1,DAY(S12)=1),"Quincena",IF(OR(AND(DAY(S12)>=2,DAY(S12)<=5),AND(DAY(S12)>=17,DAY(S12)<=20)),"Días después del pago","Resto del mes")) -> Resto del mes | X12: =COUNTIF($S$5:$S$493,S12) -> 1 | Y12: =IF(X12>=20,"Sí","No") -> No | Z12: =CHOOSE(MATCH(B12,{"Customer Appreciation","Exclusive Offers","Flash Sale","Holiday Discounts","New Product Launch","Newsletter"},0),"Fidelizar","Vender","Vender","Vender","Lanzar","Educar") -> Lanzar | AA12: =IF(G12<100000,"Menos de 100 mil",IF(G12<200000,"100 a 200 mil",IF(G12<300000,"200 a 300 mil",IF(G12<400000,"300 a 400 mil","Más de 400 mil")))) -> Menos de 100 mil | AB12: =COUNTIFS($E$5:$E$493,E12,$S$5:$S$493,"<"&S12)+COUNTIFS($E$5:E12,E12,$S$5:S12,S12) -> 10 | AC12: =COUNTIF($E$5:$E$493,E12) -> 33 | AD12: =IF(AC12<8,"",IF(AB12<=AC12/3,"Primer tercio",IF(AB12>AC12*2/3,"Último tercio","Medio"))) -> Primer tercio | AE12: =M12-Q12 -> -4.5161624 | AF12: =" "&LOWER(SUBSTITUTE(SUBSTITUTE(SUBSTITUTE(SUBSTITUTE(SUBSTITUTE(SUBSTITUTE(SUBSTITUTE(E12,"¡"," "),"!"," "),"¿"," "),"?"," "),":"," "),","," "),"."," "))&" " -> presentamos nuestro último lanzamiento de belleza imperdible | AG12: =" "&LOWER(SUBSTITUTE(SUBSTITUTE(SUBSTITUTE(SUBSTITUTE(SUBSTITUTE(SUBSTITUTE(SUBSTITUTE(F12,"¡"," "),"!"," "),"¿"," "),"?"," "),":"," "),","," "),"."," "))&" " -> una innovación que cambiará tu rutina sé de los primeros | AH12: =IF(SUMPRODUCT(--(LEFT(IF(LEFT(LOWER(E12),1)="¡",MID(LOWER(E12),2,300),LOWER(E12)),LEN({"actualizaci","el resumen","tu resumen","novedades l","oportunidad","tu oportunidad","ofertas de temporada","gran oferta","últimas horas","última oportunidad","presentamos","es hora de","descuentos imperdibles","descuentos que","un pequeño detalle"}))={"actualizaci","el resumen","tu resumen","novedades l","oportunidad","tu oportunidad","ofertas de temporada","gran oferta","últimas horas","última oportunidad","presentamos","es hora de","descuentos imperdibles","descuentos que","un pequeño detalle"}))>0,"Sí","No") -> Sí | AI12: =IF(OR(SUMPRODUCT(--ISNUMBER(SEARCH({"descuento","oferta","ahorr","precio"," sale ","flash","deals"},AF12)))>0,SUMPRODUCT(--ISNUMBER(SEARCH({"descuento","oferta","ahorr","precio"," sale ","flash","deals"},AG12)))>0),"Sí","No") -> No | AJ12: =IF(SUMPRODUCT(--ISNUMBER(SEARCH({" hoy ","horas","tiempo limitado","antes de que","se acab","se agot","finalic","última oportunidad","oportunidad única","relámpago","express","no esperes","no volver","no parpadees"},AF12)))>0,"Sí","No") -> No | AK12: =IF(SUMPRODUCT(--ISNUMBER(SEARCH({" hoy ","horas","tiempo limitado","antes de que","se acab","se agot","finalic","última oportunidad","oportunidad única","relámpago","express","no esperes","no volver","no parpadees"},AG12)))>0,"Sí","No") -> No | AL12: =IF(AI12="No","Sin descuento",IF(AJ12="Sí","Descuento con tiempo límite en el asunto",IF(AK12="Sí","Descuento con tiempo límite solo en el preheader","Descuento sin tiempo límite"))) -> Sin descuento | AM12: =IF(SUMPRODUCT(--ISNUMBER(SEARCH({"0","1","2","3","4","5","6","7","8","9","favorit","maquillaje","piel","cabello","productos","belleza","regalo"},E12)))>0,"Sí","No") -> Sí | AN12: =IF(SUMPRODUCT(--ISNUMBER(SEARCH({"lo que tenemos","estas ofertas","algo especial","ofertas únicas","que preparamos","no te quedes","echa un vistazo"},F12)))>0,"Sí","No") -> No | AO12: =LEN(E12)-(LEN(E12)-LEN(SUBSTITUTE(E12,"🔥","")))/LEN("🔥")*(LEN("🔥")-1) -> 63 | AP12: =LEN(TRIM(E12))-LEN(SUBSTITUTE(TRIM(E12)," ",""))+1 -> 7 | AQ12: =SUMPRODUCT(LEN(E12)-LEN(SUBSTITUTE(E12,{"!","¡","?","¿",":",",",".","%","·","-",";"},""))) -> 3 | AR12: =IF(AND(AO12<=60,AP12<=9,AQ12<=3,(LEN(E12)-LEN(SUBSTITUTE(E12,"🔥","")))/LEN("🔥")<=1),"Sí","No") -> No | AS12: =IF(ISNUMBER(SEARCH("hot sale",E12)),"Sí","No") -> No | AT12: =IF(SUMPRODUCT(--ISNUMBER(FIND({"0","1","2","3","4","5","6","7","8","9"},E12)))>0,"Con cifra concreta",IF(OR(ISNUMBER(FIND("?",E12)),ISNUMBER(FIND("¿",E12))),"Pregunta abierta",IF(SUMPRODUCT(--ISNUMBER(SEARCH({" hoy ","horas","tiempo limitado","antes de que","se acab","se agot","finalic","última oportunidad","oportunidad única","relámpago","express","no esperes","no volver","no parpadees"," ya ","últimas horas","últimas unidades"," ahora "},AF12)))>0,"Solo urgencia, sin cifra",IF(SUMPRODUCT(--ISNUMBER(SEARCH({"recompensa","sorpresa","regalo","lealtad","detalle","gracias","pensamos en ti","para ti"},E12)))>0,"Recompensa o sorpresa","Otro: beneficio o novedad")))) -> Otro: beneficio o novedad
A13: EM-010 | B13: Customer Appreciation | C13: 2025-10-05 | D13: 15:45:00 | E13: ¡Pensamos en ti! Descubre estas sorpresas exclusivas | F13: Ofertas exclusivas por tu lealtad a L'Oréal. ¡Aprovecha! | G13: 303989 | H13: 142875 | I13: 29335 | J13: 0.66 | K13: 1.52 | L13: 55378.06 | M13: =IFERROR(H13/G13*100,"") -> 47.000056 | N13: =IFERROR(I13/G13*100,"") -> 9.6500202 | O13: =IFERROR(I13/H13*100,"") -> 20.531934 | P13: =IFERROR(L13/G13*1000,"") -> 182.17126 | Q13: =AVERAGEIF($E$5:$E$493,$E13,$M$5:$M$493) -> 39.210447 | R13: =AVERAGEIF($B$5:$B$493,$B13,$M$5:$M$493) -> 31.113651 | S13: =DATEVALUE(C13) -> 45935 | T13: =CHOOSE(MONTH(S13)-7,"Agosto","Septiembre","Octubre") -> Octubre | U13: =CHOOSE(WEEKDAY(S13,2),"Lunes","Martes","Miércoles","Jueves","Viernes","Sábado","Domingo") -> Domingo | V13: =VALUE(LEFT(D13,2)) -> 15 | W13: =IF(OR(AND(DAY(S13)>=14,DAY(S13)<=16),DAY(S13)>=DAY(EOMONTH(S13,0))-1,DAY(S13)=1),"Quincena",IF(OR(AND(DAY(S13)>=2,DAY(S13)<=5),AND(DAY(S13)>=17,DAY(S13)<=20)),"Días después del pago","Resto del mes")) -> Días después del pago | X13: =COUNTIF($S$5:$S$493,S13) -> 2 | Y13: =IF(X13>=20,"Sí","No") -> No | Z13: =CHOOSE(MATCH(B13,{"Customer Appreciation","Exclusive Offers","Flash Sale","Holiday Discounts","New Product Launch","Newsletter"},0),"Fidelizar","Vender","Vender","Vender","Lanzar","Educar") -> Fidelizar | AA13: =IF(G13<100000,"Menos de 100 mil",IF(G13<200000,"100 a 200 mil",IF(G13<300000,"200 a 300 mil",IF(G13<400000,"300 a 400 mil","Más de 400 mil")))) -> 300 a 400 mil | AB13: =COUNTIFS($E$5:$E$493,E13,$S$5:$S$493,"<"&S13)+COUNTIFS($E$5:E13,E13,$S$5:S13,S13) -> 18 | AC13: =COUNTIF($E$5:$E$493,E13) -> 20 | AD13: =IF(AC13<8,"",IF(AB13<=AC13/3,"Primer tercio",IF(AB13>AC13*2/3,"Último tercio","Medio"))) -> Último tercio | AE13: =M13-Q13 -> 7.7896094 | AF13: =" "&LOWER(SUBSTITUTE(SUBSTITUTE(SUBSTITUTE(SUBSTITUTE(SUBSTITUTE(SUBSTITUTE(SUBSTITUTE(E13,"¡"," "),"!"," "),"¿"," "),"?"," "),":"," "),","," "),"."," "))&" " -> pensamos en ti descubre estas sorpresas exclusivas | AG13: =" "&LOWER(SUBSTITUTE(SUBSTITUTE(SUBSTITUTE(SUBSTITUTE(SUBSTITUTE(SUBSTITUTE(SUBSTITUTE(F13,"¡"," "),"!"," "),"¿"," "),"?"," "),":"," "),","," "),"."," "))&" " -> ofertas exclusivas por tu lealtad a l'oréal aprovecha | AH13: =IF(SUMPRODUCT(--(LEFT(IF(LEFT(LOWER(E13),1)="¡",MID(LOWER(E13),2,300),LOWER(E13)),LEN({"actualizaci","el resumen","tu resumen","novedades l","oportunidad","tu oportunidad","ofertas de temporada","gran oferta","últimas horas","última oportunidad","presentamos","es hora de","descuentos imperdibles","descuentos que","un pequeño detalle"}))={"actualizaci","el resumen","tu resumen","novedades l","oportunidad","tu oportunidad","ofertas de temporada","gran oferta","últimas horas","última oportunidad","presentamos","es hora de","descuentos imperdibles","descuentos que","un pequeño detalle"}))>0,"Sí","No") -> No | AI13: =IF(OR(SUMPRODUCT(--ISNUMBER(SEARCH({"descuento","oferta","ahorr","precio"," sale ","flash","deals"},AF13)))>0,SUMPRODUCT(--ISNUMBER(SEARCH({"descuento","oferta","ahorr","precio"," sale ","flash","deals"},AG13)))>0),"Sí","No") -> Sí | AJ13: =IF(SUMPRODUCT(--ISNUMBER(SEARCH({" hoy ","horas","tiempo limitado","antes de que","se acab","se agot","finalic","última oportunidad","oportunidad única","relámpago","express","no esperes","no volver","no parpadees"},AF13)))>0,"Sí","No") -> No | AK13: =IF(SUMPRODUCT(--ISNUMBER(SEARCH({" hoy ","horas","tiempo limitado","antes de que","se acab","se agot","finalic","última oportunidad","oportunidad única","relámpago","express","no esperes","no volver","no parpadees"},AG13)))>0,"Sí","No") -> No | AL13: =IF(AI13="No","Sin descuento",IF(AJ13="Sí","Descuento con tiempo límite en el asunto",IF(AK13="Sí","Descuento con tiempo límite solo en el preheader","Descuento sin tiempo límite"))) -> Descuento sin tiempo límite | AM13: =IF(SUMPRODUCT(--ISNUMBER(SEARCH({"0","1","2","3","4","5","6","7","8","9","favorit","maquillaje","piel","cabello","productos","belleza","regalo"},E13)))>0,"Sí","No") -> No | AN13: =IF(SUMPRODUCT(--ISNUMBER(SEARCH({"lo que tenemos","estas ofertas","algo especial","ofertas únicas","que preparamos","no te quedes","echa un vistazo"},F13)))>0,"Sí","No") -> No | AO13: =LEN(E13)-(LEN(E13)-LEN(SUBSTITUTE(E13,"🔥","")))/LEN("🔥")*(LEN("🔥")-1) -> 52 | AP13: =LEN(TRIM(E13))-LEN(SUBSTITUTE(TRIM(E13)," ",""))+1 -> 7 | AQ13: =SUMPRODUCT(LEN(E13)-LEN(SUBSTITUTE(E13,{"!","¡","?","¿",":",",",".","%","·","-",";"},""))) -> 2 | AR13: =IF(AND(AO13<=60,AP13<=9,AQ13<=3,(LEN(E13)-LEN(SUBSTITUTE(E13,"🔥","")))/LEN("🔥")<=1),"Sí","No") -> Sí | AS13: =IF(ISNUMBER(SEARCH("hot sale",E13)),"Sí","No") -> No | AT13: =IF(SUMPRODUCT(--ISNUMBER(FIND({"0","1","2","3","4","5","6","7","8","9"},E13)))>0,"Con cifra concreta",IF(OR(ISNUMBER(FIND("?",E13)),ISNUMBER(FIND("¿",E13))),"Pregunta abierta",IF(SUMPRODUCT(--ISNUMBER(SEARCH({" hoy ","horas","tiempo limitado","antes de que","se acab","se agot","finalic","última oportunidad","oportunidad única","relámpago","express","no esperes","no volver","no parpadees"," ya ","últimas horas","últimas unidades"," ahora "},AF13)))>0,"Solo urgencia, sin cifra",IF(SUMPRODUCT(--ISNUMBER(SEARCH({"recompensa","sorpresa","regalo","lealtad","detalle","gracias","pensamos en ti","para ti"},E13)))>0,"Recompensa o sorpresa","Otro: beneficio o novedad")))) -> Recompensa o sorpresa
A14: EM-011 | B14: Newsletter | C14: 2025-09-07 | D14: 09:30:00 | E14: Tu Dosis de Belleza: ¡No te lo pierdas! Tips y trucos | F14: Consejos expertos, tendencias y más en tu bandeja de entrada. ¡Descúbrelo! | G14: 190560 | H14: 83707 | I14: 37424 | J14: 9.63 | K14: 1.22 | L14: 92095.51 | M14: =IFERROR(H14/G14*100,"") -> 43.926847 | N14: =IFERROR(I14/G14*100,"") -> 19.638959 | O14: =IFERROR(I14/H14*100,"") -> 44.708328 | P14: =IFERROR(L14/G14*1000,"") -> 483.28878 | Q14: =AVERAGEIF($E$5:$E$493,$E14,$M$5:$M$493) -> 33.412775 | R14: =AVERAGEIF($B$5:$B$493,$B14,$M$5:$M$493) -> 27.751365 | S14: =DATEVALUE(C14) -> 45907 | T14: =CHOOSE(MONTH(S14)-7,"Agosto","Septiembre","Octubre") -> Septiembre | U14: =CHOOSE(WEEKDAY(S14,2),"Lunes","Martes","Miércoles","Jueves","Viernes","Sábado","Domingo") -> Domingo | V14: =VALUE(LEFT(D14,2)) -> 9 | W14: =IF(OR(AND(DAY(S14)>=14,DAY(S14)<=16),DAY(S14)>=DAY(EOMONTH(S14,0))-1,DAY(S14)=1),"Quincena",IF(OR(AND(DAY(S14)>=2,DAY(S14)<=5),AND(DAY(S14)>=17,DAY(S14)<=20)),"Días después del pago","Resto del mes")) -> Resto del mes | X14: =COUNTIF($S$5:$S$493,S14) -> 2 | Y14: =IF(X14>=20,"Sí","No") -> No | Z14: =CHOOSE(MATCH(B14,{"Customer Appreciation","Exclusive Offers","Flash Sale","Holiday Discounts","New Product Launch","Newsletter"},0),"Fidelizar","Vender","Vender","Vender","Lanzar","Educar") -> Educar | AA14: =IF(G14<100000,"Menos de 100 mil",IF(G14<200000,"100 a 200 mil",IF(G14<300000,"200 a 300 mil",IF(G14<400000,"300 a 400 mil","Más de 400 mil")))) -> 100 a 200 mil | AB14: =COUNTIFS($E$5:$E$493,E14,$S$5:$S$493,"<"&S14)+COUNTIFS($E$5:E14,E14,$S$5:S14,S14) -> 11 | AC14: =COUNTIF($E$5:$E$493,E14) -> 25 | AD14: =IF(AC14<8,"",IF(AB14<=AC14/3,"Primer tercio",IF(AB14>AC14*2/3,"Último tercio","Medio"))) -> Medio | AE14: =M14-Q14 -> 10.514072 | AF14: =" "&LOWER(SUBSTITUTE(SUBSTITUTE(SUBSTITUTE(SUBSTITUTE(SUBSTITUTE(SUBSTITUTE(SUBSTITUTE(E14,"¡"," "),"!"," "),"¿"," "),"?"," "),":"," "),","," "),"."," "))&" " -> tu dosis de belleza no te lo pierdas tips y trucos | AG14: =" "&LOWER(SUBSTITUTE(SUBSTITUTE(SUBSTITUTE(SUBSTITUTE(SUBSTITUTE(SUBSTITUTE(SUBSTITUTE(F14,"¡"," "),"!"," "),"¿"," "),"?"," "),":"," "),","," "),"."," "))&" " -> consejos expertos tendencias y más en tu bandeja de entrada descúbrelo | AH14: =IF(SUMPRODUCT(--(LEFT(IF(LEFT(LOWER(E14),1)="¡",MID(LOWER(E14),2,300),LOWER(E14)),LEN({"actualizaci","el resumen","tu resumen","novedades l","oportunidad","tu oportunidad","ofertas de temporada","gran oferta","últimas horas","última oportunidad","presentamos","es hora de","descuentos imperdibles","descuentos que","un pequeño detalle"}))={"actualizaci","el resumen","tu resumen","novedades l","oportunidad","tu oportunidad","ofertas de temporada","gran oferta","últimas horas","última oportunidad","presentamos","es hora de","descuentos imperdibles","descuentos que","un pequeño detalle"}))>0,"Sí","No") -> No | AI14: =IF(OR(SUMPRODUCT(--ISNUMBER(SEARCH({"descuento","oferta","ahorr","precio"," sale ","flash","deals"},AF14)))>0,SUMPRODUCT(--ISNUMBER(SEARCH({"descuento","oferta","ahorr","precio"," sale ","flash","deals"},AG14)))>0),"Sí","No") -> No | AJ14: =IF(SUMPRODUCT(--ISNUMBER(SEARCH({" hoy ","horas","tiempo limitado","antes de que","se acab","se agot","finalic","última oportunidad","oportunidad única","relámpago","express","no esperes","no volver","no parpadees"},AF14)))>0,"Sí","No") -> No | AK14: =IF(SUMPRODUCT(--ISNUMBER(SEARCH({" hoy ","horas","tiempo limitado","antes de que","se acab","se agot","finalic","última oportunidad","oportunidad única","relámpago","express","no esperes","no volver","no parpadees"},AG14)))>0,"Sí","No") -> No | AL14: =IF(AI14="No","Sin descuento",IF(AJ14="Sí","Descuento con tiempo límite en el asunto",IF(AK14="Sí","Descuento con tiempo límite solo en el preheader","Descuento sin tiempo límite"))) -> Sin descuento | AM14: =IF(SUMPRODUCT(--ISNUMBER(SEARCH({"0","1","2","3","4","5","6","7","8","9","favorit","maquillaje","piel","cabello","productos","belleza","regalo"},E14)))>0,"Sí","No") -> Sí | AN14: =IF(SUMPRODUCT(--ISNUMBER(SEARCH({"lo que tenemos","estas ofertas","algo especial","ofertas únicas","que preparamos","no te quedes","echa un vistazo"},F14)))>0,"Sí","No") -> No | AO14: =LEN(E14)-(LEN(E14)-LEN(SUBSTITUTE(E14,"🔥","")))/LEN("🔥")*(LEN("🔥")-1) -> 53 | AP14: =LEN(TRIM(E14))-LEN(SUBSTITUTE(TRIM(E14)," ",""))+1 -> 11 | AQ14: =SUMPRODUCT(LEN(E14)-LEN(SUBSTITUTE(E14,{"!","¡","?","¿",":",",",".","%","·","-",";"},""))) -> 3 | AR14: =IF(AND(AO14<=60,AP14<=9,AQ14<=3,(LEN(E14)-LEN(SUBSTITUTE(E14,"🔥","")))/LEN("🔥")<=1),"Sí","No") -> No | AS14: =IF(ISNUMBER(SEARCH("hot sale",E14)),"Sí","No") -> No | AT14: =IF(SUMPRODUCT(--ISNUMBER(FIND({"0","1","2","3","4","5","6","7","8","9"},E14)))>0,"Con cifra concreta",IF(OR(ISNUMBER(FIND("?",E14)),ISNUMBER(FIND("¿",E14))),"Pregunta abierta",IF(SUMPRODUCT(--ISNUMBER(SEARCH({" hoy ","horas","tiempo limitado","antes de que","se acab","se agot","finalic","última oportunidad","oportunidad única","relámpago","express","no esperes","no volver","no parpadees"," ya ","últimas horas","últimas unidades"," ahora "},AF14)))>0,"Solo urgencia, sin cifra",IF(SUMPRODUCT(--ISNUMBER(SEARCH({"recompensa","sorpresa","regalo","lealtad","detalle","gracias","pensamos en ti","para ti"},E14)))>0,"Recompensa o sorpresa","Otro: beneficio o novedad")))) -> Otro: beneficio o novedad
A15: EM-012 | B15: Exclusive Offers | C15: 2025-08-12 | D15: 14:15:00 | E15: ¡Exclusivo para nuestros clientes VIP! Descuentos únicos | F15: No te pierdas estas ofertas que preparamos para ti. ¡Acceso limitado! | G15: 194890 | H15: 23959 | I15: 4132 | J15: 9.64 | K15: 2.44 | L15: 6070.02 | M15: =IFERROR(H15/G15*100,"") -> 12.293602 | N15: =IFERROR(I15/G15*100,"") -> 2.1201704 | O15: =IFERROR(I15/H15*100,"") -> 17.246129 | P15: =IFERROR(L15/G15*1000,"") -> 31.145877 | Q15: =AVERAGEIF($E$5:$E$493,$E15,$M$5:$M$493) -> 12.293602 | R15: =AVERAGEIF($B$5:$B$493,$B15,$M$5:$M$493) -> 27.021448 | S15: =DATEVALUE(C15) -> 45881 | T15: =CHOOSE(MONTH(S15)-7,"Agosto","Septiembre","Octubre") -> Agosto | U15: =CHOOSE(WEEKDAY(S15,2),"Lunes","Martes","Miércoles","Jueves","Viernes","Sábado","Domingo") -> Martes | V15: =VALUE(LEFT(D15,2)) -> 14 | W15: =IF(OR(AND(DAY(S15)>=14,DAY(S15)<=16),DAY(S15)>=DAY(EOMONTH(S15,0))-1,DAY(S15)=1),"Quincena",IF(OR(AND(DAY(S15)>=2,DAY(S15)<=5),AND(DAY(S15)>=17,DAY(S15)<=20)),"Días después del pago","Resto del mes")) -> Resto del mes | X15: =COUNTIF($S$5:$S$493,S15) -> 1 | Y15: =IF(X15>=20,"Sí","No") -> No | Z15: =CHOOSE(MATCH(B15,{"Customer Appreciation","Exclusive Offers","Flash Sale","Holiday Discounts","New Product Launch","Newsletter"},0),"Fidelizar","Vender","Vender","Vender","Lanzar","Educar") -> Vender | AA15: =IF(G15<100000,"Menos de 100 mil",IF(G15<200000,"100 a 200 mil",IF(G15<300000,"200 a 300 mil",IF(G15<400000,"300 a 400 mil","Más de 400 mil")))) -> 100 a 200 mil | AB15: =COUNTIFS($E$5:$E$493,E15,$S$5:$S$493,"<"&S15)+COUNTIFS($E$5:E15,E15,$S$5:S15,S15) -> 1 | AC15: =COUNTIF($E$5:$E$493,E15) -> 1 | AD15: =IF(AC15<8,"",IF(AB15<=AC15/3,"Primer tercio",IF(AB15>AC15*2/3,"Último tercio","Medio"))) | AE15: =M15-Q15 -> 0 | AF15: =" "&LOWER(SUBSTITUTE(SUBSTITUTE(SUBSTITUTE(SUBSTITUTE(SUBSTITUTE(SUBSTITUTE(SUBSTITUTE(E15,"¡"," "),"!"," "),"¿"," "),"?"," "),":"," "),","," "),"."," "))&" " -> exclusivo para nuestros clientes vip descuentos únicos | AG15: =" "&LOWER(SUBSTITUTE(SUBSTITUTE(SUBSTITUTE(SUBSTITUTE(SUBSTITUTE(SUBSTITUTE(SUBSTITUTE(F15,"¡"," "),"!"," "),"¿"," "),"?"," "),":"," "),","," "),"."," "))&" " -> no te pierdas estas ofertas que preparamos para ti acceso limitado | AH15: =IF(SUMPRODUCT(--(LEFT(IF(LEFT(LOWER(E15),1)="¡",MID(LOWER(E15),2,300),LOWER(E15)),LEN({"actualizaci","el resumen","tu resumen","novedades l","oportunidad","tu oportunidad","ofertas de temporada","gran oferta","últimas horas","última oportunidad","presentamos","es hora de","descuentos imperdibles","descuentos que","un pequeño detalle"}))={"actualizaci","el resumen","tu resumen","novedades l","oportunidad","tu oportunidad","ofertas de temporada","gran oferta","últimas horas","última oportunidad","presentamos","es hora de","descuentos imperdibles","descuentos que","un pequeño detalle"}))>0,"Sí","No") -> No | AI15: =IF(OR(SUMPRODUCT(--ISNUMBER(SEARCH({"descuento","oferta","ahorr","precio"," sale ","flash","deals"},AF15)))>0,SUMPRODUCT(--ISNUMBER(SEARCH({"descuento","oferta","ahorr","precio"," sale ","flash","deals"},AG15)))>0),"Sí","No") -> Sí | AJ15: =IF(SUMPRODUCT(--ISNUMBER(SEARCH({" hoy ","horas","tiempo limitado","antes de que","se acab","se agot","finalic","última oportunidad","oportunidad única","relámpago","express","no esperes","no volver","no parpadees"},AF15)))>0,"Sí","No") -> No | AK15: =IF(SUMPRODUCT(--ISNUMBER(SEARCH({" hoy ","horas","tiempo limitado","antes de que","se acab","se agot","finalic","última oportunidad","oportunidad única","relámpago","express","no esperes","no volver","no parpadees"},AG15)))>0,"Sí","No") -> No | AL15: =IF(AI15="No","Sin descuento",IF(AJ15="Sí","Descuento con tiempo límite en el asunto",IF(AK15="Sí","Descuento con tiempo límite solo en el preheader","Descuento sin tiempo límite"))) -> Descuento sin tiempo límite | AM15: =IF(SUMPRODUCT(--ISNUMBER(SEARCH({"0","1","2","3","4","5","6","7","8","9","favorit","maquillaje","piel","cabello","productos","belleza","regalo"},E15)))>0,"Sí","No") -> No | AN15: =IF(SUMPRODUCT(--ISNUMBER(SEARCH({"lo que tenemos","estas ofertas","algo especial","ofertas únicas","que preparamos","no te quedes","echa un vistazo"},F15)))>0,"Sí","No") -> Sí | AO15: =LEN(E15)-(LEN(E15)-LEN(SUBSTITUTE(E15,"🔥","")))/LEN("🔥")*(LEN("🔥")-1) -> 56 | AP15: =LEN(TRIM(E15))-LEN(SUBSTITUTE(TRIM(E15)," ",""))+1 -> 7 | AQ15: =SUMPRODUCT(LEN(E15)-LEN(SUBSTITUTE(E15,{"!","¡","?","¿",":",",",".","%","·","-",";"},""))) -> 2 | AR15: =IF(AND(AO15<=60,AP15<=9,AQ15<=3,(LEN(E15)-LEN(SUBSTITUTE(E15,"🔥","")))/LEN("🔥")<=1),"Sí","No") -> Sí | AS15: =IF(ISNUMBER(SEARCH("hot sale",E15)),"Sí","No") -> No | AT15: =IF(SUMPRODUCT(--ISNUMBER(FIND({"0","1","2","3","4","5","6","7","8","9"},E15)))>0,"Con cifra concreta",IF(OR(ISNUMBER(FIND("?",E15)),ISNUMBER(FIND("¿",E15))),"Pregunta abierta",IF(SUMPRODUCT(--ISNUMBER(SEARCH({" hoy ","horas","tiempo limitado","antes de que","se acab","se agot","finalic","última oportunidad","oportunidad única","relámpago","express","no esperes","no volver","no parpadees"," ya ","últimas horas","últimas unidades"," ahora "},AF15)))>0,"Solo urgencia, sin cifra",IF(SUMPRODUCT(--ISNUMBER(SEARCH({"recompensa","sorpresa","regalo","lealtad","detalle","gracias","pensamos en ti","para ti"},E15)))>0,"Recompensa o sorpresa","Otro: beneficio o novedad")))) -> Otro: beneficio o novedad
A16: EM-013 | B16: Newsletter | C16: 2025-10-22 | D16: 10:45:00 | E16: Novedades L'Oréal: Mantente al día con lo último en belleza | F16: Tu resumen semanal de noticias de belleza. ¡Entérate ya! | G16: 208140 | H16: 16421 | I16: 14925 | J16: 5.86 | K16: 2.95 | L16: 7682.24 | M16: =IFERROR(H16/G16*100,"") -> 7.8894014 | N16: =IFERROR(I16/G16*100,"") -> 7.1706544 | O16: =IFERROR(I16/H16*100,"") -> 90.889714 | P16: =IFERROR(L16/G16*1000,"") -> 36.909004 | Q16: =AVERAGEIF($E$5:$E$493,$E16,$M$5:$M$493) -> 25.803012 | R16: =AVERAGEIF($B$5:$B$493,$B16,$M$5:$M$493) -> 27.751365 | S16: =DATEVALUE(C16) -> 45952 | T16: =CHOOSE(MONTH(S16)-7,"Agosto","Septiembre","Octubre") -> Octubre | U16: =CHOOSE(WEEKDAY(S16,2),"Lunes","Martes","Miércoles","Jueves","Viernes","Sábado","Domingo") -> Miércoles | V16: =VALUE(LEFT(D16,2)) -> 10 | W16: =IF(OR(AND(DAY(S16)>=14,DAY(S16)<=16),DAY(S16)>=DAY(EOMONTH(S16,0))-1,DAY(S16)=1),"Quincena",IF(OR(AND(DAY(S16)>=2,DAY(S16)<=5),AND(DAY(S16)>=17,DAY(S16)<=20)),"Días después del pago","Resto del mes")) -> Resto del mes | X16: =COUNTIF($S$5:$S$493,S16) -> 2 | Y16: =IF(X16>=20,"Sí","No") -> No | Z16: =CHOOSE(MATCH(B16,{"Customer Appreciation","Exclusive Offers","Flash Sale","Holiday Discounts","New Product Launch","Newsletter"},0),"Fidelizar","Vender","Vender","Vender","Lanzar","Educar") -> Educar | AA16: =IF(G16<100000,"Menos de 100 mil",IF(G16<200000,"100 a 200 mil",IF(G16<300000,"200 a 300 mil",IF(G16<400000,"300 a 400 mil","Más de 400 mil")))) -> 200 a 300 mil | AB16: =COUNTIFS($E$5:$E$493,E16,$S$5:$S$493,"<"&S16)+COUNTIFS($E$5:E16,E16,$S$5:S16,S16) -> 2 | AC16: =COUNTIF($E$5:$E$493,E16) -> 2 | AD16: =IF(AC16<8,"",IF(AB16<=AC16/3,"Primer tercio",IF(AB16>AC16*2/3,"Último tercio","Medio"))) | AE16: =M16-Q16 -> -17.91361 | AF16: =" "&LOWER(SUBSTITUTE(SUBSTITUTE(SUBSTITUTE(SUBSTITUTE(SUBSTITUTE(SUBSTITUTE(SUBSTITUTE(E16,"¡"," "),"!"," "),"¿"," "),"?"," "),":"," "),","," "),"."," "))&" " -> novedades l'oréal mantente al día con lo último en belleza | AG16: =" "&LOWER(SUBSTITUTE(SUBSTITUTE(SUBSTITUTE(SUBSTITUTE(SUBSTITUTE(SUBSTITUTE(SUBSTITUTE(F16,"¡"," "),"!"," "),"¿"," "),"?"," "),":"," "),","," "),"."," "))&" " -> tu resumen semanal de noticias de belleza entérate ya | AH16: =IF(SUMPRODUCT(--(LEFT(IF(LEFT(LOWER(E16),1)="¡",MID(LOWER(E16),2,300),LOWER(E16)),LEN({"actualizaci","el resumen","tu resumen","novedades l","oportunidad","tu oportunidad","ofertas de temporada","gran oferta","últimas horas","última oportunidad","presentamos","es hora de","descuentos imperdibles","descuentos que","un pequeño detalle"}))={"actualizaci","el resumen","tu resumen","novedades l","oportunidad","tu oportunidad","ofertas de temporada","gran oferta","últimas horas","última oportunidad","presentamos","es hora de","descuentos imperdibles","descuentos que","un pequeño detalle"}))>0,"Sí","No") -> Sí | AI16: =IF(OR(SUMPRODUCT(--ISNUMBER(SEARCH({"descuento","oferta","ahorr","precio"," sale ","flash","deals"},AF16)))>0,SUMPRODUCT(--ISNUMBER(SEARCH({"descuento","oferta","ahorr","precio"," sale ","flash","deals"},AG16)))>0),"Sí","No") -> No | AJ16: =IF(SUMPRODUCT(--ISNUMBER(SEARCH({" hoy ","horas","tiempo limitado","antes de que","se acab","se agot","finalic","última oportunidad","oportunidad única","relámpago","express","no esperes","no volver","no parpadees"},AF16)))>0,"Sí","No") -> No | AK16: =IF(SUMPRODUCT(--ISNUMBER(SEARCH({" hoy ","horas","tiempo limitado","antes de que","se acab","se agot","finalic","última oportunidad","oportunidad única","relámpago","express","no esperes","no volver","no parpadees"},AG16)))>0,"Sí","No") -> No | AL16: =IF(AI16="No","Sin descuento",IF(AJ16="Sí","Descuento con tiempo límite en el asunto",IF(AK16="Sí","Descuento con tiempo límite solo en el preheader","Descuento sin tiempo límite"))) -> Sin descuento | AM16: =IF(SUMPRODUCT(--ISNUMBER(SEARCH({"0","1","2","3","4","5","6","7","8","9","favorit","maquillaje","piel","cabello","productos","belleza","regalo"},E16)))>0,"Sí","No") -> Sí | AN16: =IF(SUMPRODUCT(--ISNUMBER(SEARCH({"lo que tenemos","estas ofertas","algo especial","ofertas únicas","que preparamos","no te quedes","echa un vistazo"},F16)))>0,"Sí","No") -> No | AO16: =LEN(E16)-(LEN(E16)-LEN(SUBSTITUTE(E16,"🔥","")))/LEN("🔥")*(LEN("🔥")-1) -> 59 | AP16: =LEN(TRIM(E16))-LEN(SUBSTITUTE(TRIM(E16)," ",""))+1 -> 10 | AQ16: =SUMPRODUCT(LEN(E16)-LEN(SUBSTITUTE(E16,{"!","¡","?","¿",":",",",".","%","·","-",";"},""))) -> 1 | AR16: =IF(AND(AO16<=60,AP16<=9,AQ16<=3,(LEN(E16)-LEN(SUBSTITUTE(E16,"🔥","")))/LEN("🔥")<=1),"Sí","No") -> No | AS16: =IF(ISNUMBER(SEARCH("hot sale",E16)),"Sí","No") -> No | AT16: =IF(SUMPRODUCT(--ISNUMBER(FIND({"0","1","2","3","4","5","6","7","8","9"},E16)))>0,"Con cifra concreta",IF(OR(ISNUMBER(FIND("?",E16)),ISNUMBER(FIND("¿",E16))),"Pregunta abierta",IF(SUMPRODUCT(--ISNUMBER(SEARCH({" hoy ","horas","tiempo limitado","antes de que","se acab","se agot","finalic","última oportunidad","oportunidad única","relámpago","express","no esperes","no volver","no parpadees"," ya ","últimas horas","últimas unidades"," ahora "},AF16)))>0,"Solo urgencia, sin cifra",IF(SUMPRODUCT(--ISNUMBER(SEARCH({"recompensa","sorpresa","regalo","lealtad","detalle","gracias","pensamos en ti","para ti"},E16)))>0,"Recompensa o sorpresa","Otro: beneficio o novedad")))) -> Otro: beneficio o novedad
... A493: EM-575 | B493: Newsletter | C493: 2025-09-01 | D493: 14:30:00 | E493: Tu Dosis de Belleza: ¡No te lo pierdas! Tips y trucos | F493: Consejos expertos, tendencias y más en tu bandeja de entrada. ¡Descúbrelo! | G493: 146973 | H493: 69888 | I493: 20257 | J493: 2.59 | K493: 3.52 | L493: 57132.21 | M493: =IFERROR(H493/G493*100,"") -> 47.551591 | N493: =IFERROR(I493/G493*100,"") -> 13.782804 | O493: =IFERROR(I493/H493*100,"") -> 28.984947 | P493: =IFERROR(L493/G493*1000,"") -> 388.72589 | Q493: =AVERAGEIF($E$5:$E$493,$E493,$M$5:$M$493) -> 33.412775 | R493: =AVERAGEIF($B$5:$B$493,$B493,$M$5:$M$493) -> 27.751365 | S493: =DATEVALUE(C493) -> 45901 | T493: =CHOOSE(MONTH(S493)-7,"Agosto","Septiembre","Octubre") -> Septiembre | U493: =CHOOSE(WEEKDAY(S493,2),"Lunes","Martes","Miércoles","Jueves","Viernes","Sábado","Domingo") -> Lunes | V493: =VALUE(LEFT(D493,2)) -> 14 | W493: =IF(OR(AND(DAY(S493)>=14,DAY(S493)<=16),DAY(S493)>=DAY(EOMONTH(S493,0))-1,DAY(S493)=1),"Quincena",IF(OR(AND(DAY(S493)>=2,DAY(S493)<=5),AND(DAY(S493)>=17,DAY(S493)<=20)),"Días después del pago","Resto del mes")) -> Quincena | X493: =COUNTIF($S$5:$S$493,S493) -> 29 | Y493: =IF(X493>=20,"Sí","No") -> Sí | Z493: =CHOOSE(MATCH(B493,{"Customer Appreciation","Exclusive Offers","Flash Sale","Holiday Discounts","New Product Launch","Newsletter"},0),"Fidelizar","Vender","Vender","Vender","Lanzar","Educar") -> Educar | AA493: =IF(G493<100000,"Menos de 100 mil",IF(G493<200000,"100 a 200 mil",IF(G493<300000,"200 a 300 mil",IF(G493<400000,"300 a 400 mil","Más de 400 mil")))) -> 100 a 200 mil | AB493: =COUNTIFS($E$5:$E$493,E493,$S$5:$S$493,"<"&S493)+COUNTIFS($E$5:E493,E493,$S$5:S493,S493) -> 10 | AC493: =COUNTIF($E$5:$E$493,E493) -> 25 | AD493: =IF(AC493<8,"",IF(AB493<=AC493/3,"Primer tercio",IF(AB493>AC493*2/3,"Último tercio","Medio"))) -> Medio | AE493: =M493-Q493 -> 14.138816 | AF493: =" "&LOWER(SUBSTITUTE(SUBSTITUTE(SUBSTITUTE(SUBSTITUTE(SUBSTITUTE(SUBSTITUTE(SUBSTITUTE(E493,"¡"," "),"!"," "),"¿"," "),"?"," "),":"," "),","," "),"."," "))&" " -> tu dosis de belleza no te lo pierdas tips y trucos | AG493: =" "&LOWER(SUBSTITUTE(SUBSTITUTE(SUBSTITUTE(SUBSTITUTE(SUBSTITUTE(SUBSTITUTE(SUBSTITUTE(F493,"¡"," "),"!"," "),"¿"," "),"?"," "),":"," "),","," "),"."," "))&" " -> consejos expertos tendencias y más en tu bandeja de entrada descúbrelo | AH493: =IF(SUMPRODUCT(--(LEFT(IF(LEFT(LOWER(E493),1)="¡",MID(LOWER(E493),2,300),LOWER(E493)),LEN({"actualizaci","el resumen","tu resumen","novedades l","oportunidad","tu oportunidad","ofertas de temporada","gran oferta","últimas horas","última oportunidad","presentamos","es hora de","descuentos imperdibles","descuentos que","un pequeño detalle"}))={"actualizaci","el resumen","tu resumen","novedades l","oportunidad","tu oportunidad","ofertas de temporada","gran oferta","últimas horas","última oportunidad","presentamos","es hora de","descuentos imperdibles","descuentos que","un pequeño detalle"}))>0,"Sí","No") -> No | AI493: =IF(OR(SUMPRODUCT(--ISNUMBER(SEARCH({"descuento","oferta","ahorr","precio"," sale ","flash","deals"},AF493)))>0,SUMPRODUCT(--ISNUMBER(SEARCH({"descuento","oferta","ahorr","precio"," sale ","flash","deals"},AG493)))>0),"Sí","No") -> No | AJ493: =IF(SUMPRODUCT(--ISNUMBER(SEARCH({" hoy ","horas","tiempo limitado","antes de que","se acab","se agot","finalic","última oportunidad","oportunidad única","relámpago","express","no esperes","no volver","no parpadees"},AF493)))>0,"Sí","No") -> No | AK493: =IF(SUMPRODUCT(--ISNUMBER(SEARCH({" hoy ","horas","tiempo limitado","antes de que","se acab","se agot","finalic","última oportunidad","oportunidad única","relámpago","express","no esperes","no volver","no parpadees"},AG493)))>0,"Sí","No") -> No | AL493: =IF(AI493="No","Sin descuento",IF(AJ493="Sí","Descuento con tiempo límite en el asunto",IF(AK493="Sí","Descuento con tiempo límite solo en el preheader","Descuento sin tiempo límite"))) -> Sin descuento | AM493: =IF(SUMPRODUCT(--ISNUMBER(SEARCH({"0","1","2","3","4","5","6","7","8","9","favorit","maquillaje","piel","cabello","productos","belleza","regalo"},E493)))>0,"Sí","No") -> Sí | AN493: =IF(SUMPRODUCT(--ISNUMBER(SEARCH({"lo que tenemos","estas ofertas","algo especial","ofertas únicas","que preparamos","no te quedes","echa un vistazo"},F493)))>0,"Sí","No") -> No | AO493: =LEN(E493)-(LEN(E493)-LEN(SUBSTITUTE(E493,"🔥","")))/LEN("🔥")*(LEN("🔥")-1) -> 53 | AP493: =LEN(TRIM(E493))-LEN(SUBSTITUTE(TRIM(E493)," ",""))+1 -> 11 | AQ493: =SUMPRODUCT(LEN(E493)-LEN(SUBSTITUTE(E493,{"!","¡","?","¿",":",",",".","%","·","-",";"},""))) -> 3 | AR493: =IF(AND(AO493<=60,AP493<=9,AQ493<=3,(LEN(E493)-LEN(SUBSTITUTE(E493,"🔥","")))/LEN("🔥")<=1),"Sí","No") -> No | AS493: =IF(ISNUMBER(SEARCH("hot sale",E493)),"Sí","No") -> No | AT493: =IF(SUMPRODUCT(--ISNUMBER(FIND({"0","1","2","3","4","5","6","7","8","9"},E493)))>0,"Con cifra concreta",IF(OR(ISNUMBER(FIND("?",E493)),ISNUMBER(FIND("¿",E493))),"Pregunta abierta",IF(SUMPRODUCT(--ISNUMBER(SEARCH({" hoy ","horas","tiempo limitado","antes de que","se acab","se agot","finalic","última oportunidad","oportunidad única","relámpago","express","no esperes","no volver","no parpadees"," ya ","últimas horas","últimas unidades"," ahora "},AF493)))>0,"Solo urgencia, sin cifra",IF(SUMPRODUCT(--ISNUMBER(SEARCH({"recompensa","sorpresa","regalo","lealtad","detalle","gracias","pensamos en ti","para ti"},E493)))>0,"Recompensa o sorpresa","Otro: beneficio o novedad")))) -> Otro: beneficio o novedad

Sheet FILAS EXCLUIDAS
A1: Filas excluidas · 87 de 576
A2: Ninguna fila se descartó en silencio. "Fila en el archivo original" permite volver al Excel de origen y verificar cada caso.
A4: Fila en el archivo original | B4: Campaign ID | C4: Motivo de exclusión | D4: Tipo de Campaña | E4: Fecha de Envío | F4: Emails Enviados | G4: Emails Abiertos | H4: Total Clicks | I4: Ingresos Generados ($)
A5: 577 | B5: EM-576 | C5: Campos vacíos en métricas de cálculo | D5: Newsletter | E5: 2025-08-23
A6: 492 | B6: EM-491 | C6: Campos vacíos en métricas de cálculo | D6: Holiday Discounts | E6: 2025-09-17 | H6: 7142 | I6: 3606.16
A7: 159 | B7: EM-158 | C7: Campos vacíos en métricas de cálculo | D7: Exclusive Offers | E7: 2025-09-09 | H7: 29853 | I7: 92485.69
A8: 328 | B8: EM-327 | C8: Fecha fuera de la ventana ago-oct 2025 | D8: Exclusive Offers | E8: 2022-08-14 | F8: 282483 | G8: 119409 | H8: 48464 | I8: 54045.44
A9: 314 | B9: EM-313 | C9: Fecha fuera de la ventana ago-oct 2025 | D9: Exclusive Offers | E9: 1990-10-13 | F9: 453971 | G9: 98057 | H9: 69389 | I9: 66298.96
A10: 308 | B10: EM-307 | C10: Fecha fuera de la ventana ago-oct 2025 | D10: Customer Appreciation | E10: 2026-10-18 | F10: 298945 | G10: 45625 | H10: 38711 | I10: 44584.68
A11: 161 | B11: EM-160 | C11: Fecha fuera de la ventana ago-oct 2025 | D11: Flash Sale | E11: 2026-10-29 | F11: 212228 | G11: 101211 | H11: 25630 | I11: 52436.59
A12: 135 | B12: EM-134 | C12: Fecha fuera de la ventana ago-oct 2025 | D12: Customer Appreciation | E12: 2026-09-08 | F12: 473622 | G12: 155532 | H12: 10557 | I12: 31500.07
A13: 111 | B13: EM-110 | C13: Fecha fuera de la ventana ago-oct 2025 | D13: Exclusive Offers | E13: 2026-09-14 | F13: 378857 | G13: 63648 | H13: 68972 | I13: 30583.7
A14: 103 | B14: EM-102 | C14: Fecha fuera de la ventana ago-oct 2025 | D14: Exclusive Offers | E14: 2026-08-20 | F14: 145862 | G14: 33333 | H14: 14046 | I14: 94732.05
A15: 253 | B15: EM-252 | C15: Imposible: más aperturas que envíos | D15: Customer Appreciation | E15: 2025-08-14 | F15: 82 | G15: 327 | H15: 3000 | I15: 87657.57
A16: 252 | B16: EM-251 | C16: Imposible: más aperturas que envíos | D16: Flash Sale | E16: 2025-09-17 | F16: 169383 | G16: 459650 | H16: 89437 | I16: 9272.39
A17: 7 | B17: EM-006 | C17: Imposible: más aperturas que envíos | D17: Customer Appreciation | E17: 2025-08-05 | F17: 16090 | G17: 31453 | H17: 40149 | I17: 98169.73
A18: 31 | B18: EM-030 | C18: Imposible: más aperturas que envíos | D18: Holiday Discounts | E18: 2025-08-28 | F18: 267040 | G18: 649234 | H18: 30349 | I18: 29192.05
A19: 52 | B19: EM-051 | C19: Imposible: más aperturas que envíos | D19: Flash Sale | E19: 2025-08-11 | F19: 193751 | G19: 509892 | H19: 34241 | I19: 13154.76
... A91: 274 | B91: EM-273 | C91: Imposible: más clics que aperturas | D91: Exclusive Offers | E91: 2025-08-04 | F91: 320980 | G91: 22818 | H91: 34956 | I91: 61644.16

Sheet _datos_graficos
A1: Asunto | B1: Tasa de apertura (%) | D1: Dimensión | E1: % de la variación que explica | G1: Mes | H1: Apertura (%) | I1: CTR (%) | K1: Clics | L1: Ingresos
A2: ¡Ahorra YA! Flash Sale: Hasta 50% en tus favoritos | B2: 41.6 | D2: Asunto + preheader | E2: 47.4 | G2: Agosto | H2: 29.5 | I2: 10 | K2: 20073 | L2: 37643.98
A3: ¡Tu lealtad tiene recompensa! Descúbrela, sorpresas para t | B3: 40.7 | D3: Tipo de campaña | E3: 1.4 | G3: Septiembre | H3: 28.7 | I3: 9.6 | K3: 2229 | L3: 57634.13
A4: ¡Pensamos en ti! Descubre estas sorpresas exclusivas | B4: 39.2 | D4: Hora de envío | E4: 1 | G4: Octubre | H4: 29.4 | I4: 9.7 | K4: 3224 | L4: 47581.07
A5: ¡Solo un clic te separa de estas ofertas! L'Oréal Paris | B5: 38.7 | D5: Día de la semana | E5: 0.5 | K5: 17739 | L5: 55342.07
A6: Lo último en L'Oréal: Mantente informad@ de las novedades | B6: 36.8 | D6: Mes | E6: 0.1 | K6: 13237 | L6: 51666.46
A7: ¡El futuro de tu piel ha llegado! Nuevo Producto revolucio | B7: 36.1 | K7: 42023 | L7: 57418.39
A8: ¡Aprovecha los descuentos! Temporada de Fiestas, beauty de | B8: 35.6 | K8: 46845 | L8: 78459.67
A9: ¡Regalos perfectos te esperan! Descuentos de Lujo, L'Oréal | B9: 35.4 | K9: 7287 | L9: 81300.96
A10: Tu Dosis de Belleza: ¡No te lo pierdas! Tips y trucos | B10: 33.4 | K10: 29335 | L10: 55378.06
A11: ¡Ofertas Exclusivas! Solo para nuestra comunidad VIP | B11: 33 | K11: 37424 | L11: 92095.51
A12: ¡Un pequeño detalle para agradecerte tu lealtad! L'Oréal | B12: 20.7 | K12: 4132 | L12: 6070.02
A13: ¡Oportunidad Única! Solo por hoy, tus favoritos a un clic | B13: 18.4 | K13: 14925 | L13: 7682.24
A14: ¡Gran oferta! Por tiempo limitado, no te lo pierdas | B14: 17.4 | K14: 1934 | L14: 77099.27
A15: Actualización de L'Oréal: ¿Qué hay de nuevo en el mundo be | B15: 15.9 | K15: 61376 | L15: 61885.22
A16: ¡Oportunidades de ahorro! Descúbrelas, solo para ti | B16: 10.7 | K16: 1463 | L16: 41057.08
K17: 10452 | L17: 78024.83
K18: 1750 | L18: 92852.77
K19: 32630 | L19: 54788.94
K20: 254 | L20: 21469.34
K21: 5284 | L21: 7323.9
K22: 16599 | L22: 73501.82
K23: 24598 | L23: 71686.22
K24: 1501 | L24: 99555.03
K25: 12903 | L25: 33369.83
K26: 290 | L26: 27543.42
K27: 13010 | L27: 4496.23
K28: 52796 | L28: 15388.5
... K490: 20257 | L490: 57132.21

Sheet _calculos
A1: Tabla de asuntos y cálculos auxiliares para las gráficas. Todo es fórmula sobre DATOS LIMPIOS.
A3: # | B3: Asunto | C3: Campañas | D3: Apertura (%) | E3: CTR (%) | F3: Tipo | G3: Empieza con etiqueta | H3: Preheader vago | I3: Beneficio concreto | J3: Tiempo límite en el asunto | K3: Habla de descuento | L3: Cumple Mailchimp | N3: Campañas sin Agosto | O3: Apertura sin Agosto | P3: Entra (sin Agosto) | Q3: Puesto arriba | R3: Puesto abajo | S3: Grupo, prueba en Agosto | T3: Suma apertura en Agosto | U3: Campañas en Agosto | V3: Campañas sin Septiembre | W3: Apertura sin Septiembre | X3: Entra (sin Septiembre) | Y3: Puesto arriba | Z3: Puesto abajo | AA3: Grupo, prueba en Septiembre | AB3: Suma apertura en Septiembre | AC3: Campañas en Septiembre | AD3: Campañas sin Octubre | AE3: Apertura sin Octubre | AF3: Entra (sin Octubre) | AG3: Puesto arriba | AH3: Puesto abajo | AI3: Grupo, prueba en Octubre | AJ3: Suma apertura en Octubre | AK3: Campañas en Octubre
A4: 1 | B4: {=IFERROR(INDEX('DATOS LIMPIOS'!$E$5:$E$493,MATCH(0,COUNTIF($B$3:B3,'DATOS LIMPIOS'!$E$5:$E$493),0)),"")} -> ¡Gracias por ser parte de L'Oréal! Ofertas para ti | C4: =COUNTIF('DATOS LIMPIOS'!$E$5:$E$493,B4) -> 4 | D4: =AVERAGEIF('DATOS LIMPIOS'!$E$5:$E$493,B4,'DATOS LIMPIOS'!$M$5:$M$493) -> 22.904078 | E4: =AVERAGEIF('DATOS LIMPIOS'!$E$5:$E$493,B4,'DATOS LIMPIOS'!$N$5:$N$493) -> 7.0614977 | F4: =INDEX('DATOS LIMPIOS'!$B$5:$B$493,MATCH(B4,'DATOS LIMPIOS'!$E$5:$E$493,0)) -> Customer Appreciation | G4: =INDEX('DATOS LIMPIOS'!$AH$5:$AH$493,MATCH(B4,'DATOS LIMPIOS'!$E$5:$E$493,0)) -> No | H4: =INDEX('DATOS LIMPIOS'!$AN$5:$AN$493,MATCH(B4,'DATOS LIMPIOS'!$E$5:$E$493,0)) -> No | I4: =INDEX('DATOS LIMPIOS'!$AM$5:$AM$493,MATCH(B4,'DATOS LIMPIOS'!$E$5:$E$493,0)) -> No | J4: =INDEX('DATOS LIMPIOS'!$AJ$5:$AJ$493,MATCH(B4,'DATOS LIMPIOS'!$E$5:$E$493,0)) -> No | K4: =INDEX('DATOS LIMPIOS'!$AI$5:$AI$493,MATCH(B4,'DATOS LIMPIOS'!$E$5:$E$493,0)) -> Sí | L4: =INDEX('DATOS LIMPIOS'!$AR$5:$AR$493,MATCH(B4,'DATOS LIMPIOS'!$E$5:$E$493,0)) -> Sí | N4: =COUNTIFS('DATOS LIMPIOS'!$E$5:$E$493,B4,'DATOS LIMPIOS'!$T$5:$T$493,"<>Agosto") -> 4 | O4: =IFERROR(AVERAGEIFS('DATOS LIMPIOS'!$M$5:$M$493,'DATOS LIMPIOS'!$E$5:$E$493,B4,'DATOS LIMPIOS'!$T$5:$T$493,"<>Agosto"),"") -> 22.904078 | P4: =IF(N4>=5,"Sí","No") -> No | Q4: =IF(P4="Sí",SUMPRODUCT(($P$4:$P$69="Sí")*($O$4:$O$69>O4))+1,"") | R4: =IF(P4="Sí",SUMPRODUCT(($P$4:$P$69="Sí")*($O$4:$O$69<O4))+1,"") | S4: =IF(P4<>"Sí","Resto",IF(Q4<=5,"5 mejores",IF(R4<=5,"5 peores","Resto"))) -> Resto | T4: =SUMIFS('DATOS LIMPIOS'!$M$5:$M$493,'DATOS LIMPIOS'!$E$5:$E$493,B4,'DATOS LIMPIOS'!$T$5:$T$493,"Agosto") -> 0 | U4: =COUNTIFS('DATOS LIMPIOS'!$E$5:$E$493,B4,'DATOS LIMPIOS'!$T$5:$T$493,"Agosto") -> 0 | V4: =COUNTIFS('DATOS LIMPIOS'!$E$5:$E$493,B4,'DATOS LIMPIOS'!$T$5:$T$493,"<>Septiembre") -> 3 | W4: =IFERROR(AVERAGEIFS('DATOS LIMPIOS'!$M$5:$M$493,'DATOS LIMPIOS'!$E$5:$E$493,B4,'DATOS LIMPIOS'!$T$5:$T$493,"<>Septiembre"),"") -> 25.89542 | X4: =IF(V4>=5,"Sí","No") -> No | Y4: =IF(X4="Sí",SUMPRODUCT(($X$4:$X$69="Sí")*($W$4:$W$69>W4))+1,"") | Z4: =IF(X4="Sí",SUMPRODUCT(($X$4:$X$69="Sí")*($W$4:$W$69<W4))+1,"") | AA4: =IF(X4<>"Sí","Resto",IF(Y4<=5,"5 mejores",IF(Z4<=5,"5 peores","Resto"))) -> Resto | AB4: =SUMIFS('DATOS LIMPIOS'!$M$5:$M$493,'DATOS LIMPIOS'!$E$5:$E$493,B4,'DATOS LIMPIOS'!$T$5:$T$493,"Septiembre") -> 13.930053 | AC4: =COUNTIFS('DATOS LIMPIOS'!$E$5:$E$493,B4,'DATOS LIMPIOS'!$T$5:$T$493,"Septiembre") -> 1 | AD4: =COUNTIFS('DATOS LIMPIOS'!$E$5:$E$493,B4,'DATOS LIMPIOS'!$T$5:$T$493,"<>Octubre") -> 1 | AE4: =IFERROR(AVERAGEIFS('DATOS LIMPIOS'!$M$5:$M$493,'DATOS LIMPIOS'!$E$5:$E$493,B4,'DATOS LIMPIOS'!$T$5:$T$493,"<>Octubre"),"") -> 13.930053 | AF4: =IF(AD4>=5,"Sí","No") -> No | AG4: =IF(AF4="Sí",SUMPRODUCT(($AF$4:$AF$69="Sí")*($AE$4:$AE$69>AE4))+1,"") | AH4: =IF(AF4="Sí",SUMPRODUCT(($AF$4:$AF$69="Sí")*($AE$4:$AE$69<AE4))+1,"") | AI4: =IF(AF4<>"Sí","Resto",IF(AG4<=5,"5 mejores",IF(AH4<=5,"5 peores","Resto"))) -> Resto | AJ4: =SUMIFS('DATOS LIMPIOS'!$M$5:$M$493,'DATOS LIMPIOS'!$E$5:$E$493,B4,'DATOS LIMPIOS'!$T$5:$T$493,"Octubre") -> 77.686259 | AK4: =COUNTIFS('DATOS LIMPIOS'!$E$5:$E$493,B4,'DATOS LIMPIOS'!$T$5:$T$493,"Octubre") -> 3
A5: 2 | B5: {=IFERROR(INDEX('DATOS LIMPIOS'!$E$5:$E$493,MATCH(0,COUNTIF($B$3:B4,'DATOS LIMPIOS'!$E$5:$E$493),0)),"")} -> ¡Últimas horas! Flash Sale: No te quedes sin tu descuento | C5: =COUNTIF('DATOS LIMPIOS'!$E$5:$E$493,B5) -> 4 | D5: =AVERAGEIF('DATOS LIMPIOS'!$E$5:$E$493,B5,'DATOS LIMPIOS'!$M$5:$M$493) -> 10.812608 | E5: =AVERAGEIF('DATOS LIMPIOS'!$E$5:$E$493,B5,'DATOS LIMPIOS'!$N$5:$N$493) -> 7.0308876 | F5: =INDEX('DATOS LIMPIOS'!$B$5:$B$493,MATCH(B5,'DATOS LIMPIOS'!$E$5:$E$493,0)) -> Flash Sale | G5: =INDEX('DATOS LIMPIOS'!$AH$5:$AH$493,MATCH(B5,'DATOS LIMPIOS'!$E$5:$E$493,0)) -> Sí | H5: =INDEX('DATOS LIMPIOS'!$AN$5:$AN$493,MATCH(B5,'DATOS LIMPIOS'!$E$5:$E$493,0)) -> No | I5: =INDEX('DATOS LIMPIOS'!$AM$5:$AM$493,MATCH(B5,'DATOS LIMPIOS'!$E$5:$E$493,0)) -> No | J5: =INDEX('DATOS LIMPIOS'!$AJ$5:$AJ$493,MATCH(B5,'DATOS LIMPIOS'!$E$5:$E$493,0)) -> Sí | K5: =INDEX('DATOS LIMPIOS'!$AI$5:$AI$493,MATCH(B5,'DATOS LIMPIOS'!$E$5:$E$493,0)) -> Sí | L5: =INDEX('DATOS LIMPIOS'!$AR$5:$AR$493,MATCH(B5,'DATOS LIMPIOS'!$E$5:$E$493,0)) -> No | N5: =COUNTIFS('DATOS LIMPIOS'!$E$5:$E$493,B5,'DATOS LIMPIOS'!$T$5:$T$493,"<>Agosto") -> 4 | O5: =IFERROR(AVERAGEIFS('DATOS LIMPIOS'!$M$5:$M$493,'DATOS LIMPIOS'!$E$5:$E$493,B5,'DATOS LIMPIOS'!$T$5:$T$493,"<>Agosto"),"") -> 10.812608 | P5: =IF(N5>=5,"Sí","No") -> No | Q5: =IF(P5="Sí",SUMPRODUCT(($P$4:$P$69="Sí")*($O$4:$O$69>O5))+1,"") | R5: =IF(P5="Sí",SUMPRODUCT(($P$4:$P$69="Sí")*($O$4:$O$69<O5))+1,"") | S5: =IF(P5<>"Sí","Resto",IF(Q5<=5,"5 mejores",IF(R5<=5,"5 peores","Resto"))) -> Resto | T5: =SUMIFS('DATOS LIMPIOS'!$M$5:$M$493,'DATOS LIMPIOS'!$E$5:$E$493,B5,'DATOS LIMPIOS'!$T$5:$T$493,"Agosto") -> 0 | U5: =COUNTIFS('DATOS LIMPIOS'!$E$5:$E$493,B5,'DATOS LIMPIOS'!$T$5:$T$493,"Agosto") -> 0 | V5: =COUNTIFS('DATOS LIMPIOS'!$E$5:$E$493,B5,'DATOS LIMPIOS'!$T$5:$T$493,"<>Septiembre") -> 2 | W5: =IFERROR(AVERAGEIFS('DATOS LIMPIOS'!$M$5:$M$493,'DATOS LIMPIOS'!$E$5:$E$493,B5,'DATOS LIMPIOS'!$T$5:$T$493,"<>Septiembre"),"") -> 11.56169 | X5: =IF(V5>=5,"Sí","No") -> No | Y5: =IF(X5="Sí",SUMPRODUCT(($X$4:$X$69="Sí")*($W$4:$W$69>W5))+1,"") | Z5: =IF(X5="Sí",SUMPRODUCT(($X$4:$X$69="Sí")*($W$4:$W$69<W5))+1,"") | AA5: =IF(X5<>"Sí","Resto",IF(Y5<=5,"5 mejores",IF(Z5<=5,"5 peores","Resto"))) -> Resto | AB5: =SUMIFS('DATOS LIMPIOS'!$M$5:$M$493,'DATOS LIMPIOS'!$E$5:$E$493,B5,'DATOS LIMPIOS'!$T$5:$T$493,"Septiembre") -> 20.127052 | AC5: =COUNTIFS('DATOS LIMPIOS'!$E$5:$E$493,B5,'DATOS LIMPIOS'!$T$5:$T$493,"Septiembre") -> 2 | AD5: =COUNTIFS('DATOS LIMPIOS'!$E$5:$E$493,B5,'DATOS LIMPIOS'!$T$5:$T$493,"<>Octubre") -> 2 | AE5: =IFERROR(AVERAGEIFS('DATOS LIMPIOS'!$M$5:$M$493,'DATOS LIMPIOS'!$E$5:$E$493,B5,'DATOS LIMPIOS'!$T$5:$T$493,"<>Octubre"),"") -> 10.063526 | AF5: =IF(AD5>=5,"Sí","No") -> No | AG5: =IF(AF5="Sí",SUMPRODUCT(($AF$4:$AF$69="Sí")*($AE$4:$AE$69>AE5))+1,"") | AH5: =IF(AF5="Sí",SUMPRODUCT(($AF$4:$AF$69="Sí")*($AE$4:$AE$69<AE5))+1,"") | AI5: =IF(AF5<>"Sí","Resto",IF(AG5<=5,"5 mejores",IF(AH5<=5,"5 peores","Resto"))) -> Resto | AJ5: =SUMIFS('DATOS LIMPIOS'!$M$5:$M$493,'DATOS LIMPIOS'!$E$5:$E$493,B5,'DATOS LIMPIOS'!$T$5:$T$493,"Octubre") -> 23.123381 | AK5: =COUNTIFS('DATOS LIMPIOS'!$E$5:$E$493,B5,'DATOS LIMPIOS'!$T$5:$T$493,"Octubre") -> 2
A6: 3 | B6: {=IFERROR(INDEX('DATOS LIMPIOS'!$E$5:$E$493,MATCH(0,COUNTIF($B$3:B5,'DATOS LIMPIOS'!$E$5:$E$493),0)),"")} -> Tu dosis semanal de belleza: Novedades y tips | C6: =COUNTIF('DATOS LIMPIOS'!$E$5:$E$493,B6) -> 22 | D6: =AVERAGEIF('DATOS LIMPIOS'!$E$5:$E$493,B6,'DATOS LIMPIOS'!$M$5:$M$493) -> 22.891294 | E6: =AVERAGEIF('DATOS LIMPIOS'!$E$5:$E$493,B6,'DATOS LIMPIOS'!$N$5:$N$493) -> 8.9502193 | F6: =INDEX('DATOS LIMPIOS'!$B$5:$B$493,MATCH(B6,'DATOS LIMPIOS'!$E$5:$E$493,0)) -> Newsletter | G6: =INDEX('DATOS LIMPIOS'!$AH$5:$AH$493,MATCH(B6,'DATOS LIMPIOS'!$E$5:$E$493,0)) -> No | H6: =INDEX('DATOS LIMPIOS'!$AN$5:$AN$493,MATCH(B6,'DATOS LIMPIOS'!$E$5:$E$493,0)) -> No | I6: =INDEX('DATOS LIMPIOS'!$AM$5:$AM$493,MATCH(B6,'DATOS LIMPIOS'!$E$5:$E$493,0)) -> Sí | J6: =INDEX('DATOS LIMPIOS'!$AJ$5:$AJ$493,MATCH(B6,'DATOS LIMPIOS'!$E$5:$E$493,0)) -> No | K6: =INDEX('DATOS LIMPIOS'!$AI$5:$AI$493,MATCH(B6,'DATOS LIMPIOS'!$E$5:$E$493,0)) -> No | L6: =INDEX('DATOS LIMPIOS'!$AR$5:$AR$493,MATCH(B6,'DATOS LIMPIOS'!$E$5:$E$493,0)) -> Sí | N6: =COUNTIFS('DATOS LIMPIOS'!$E$5:$E$493,B6,'DATOS LIMPIOS'!$T$5:$T$493,"<>Agosto") -> 16 | O6: =IFERROR(AVERAGEIFS('DATOS LIMPIOS'!$M$5:$M$493,'DATOS LIMPIOS'!$E$5:$E$493,B6,'DATOS LIMPIOS'!$T$5:$T$493,"<>Agosto"),"") -> 20.13192 | P6: =IF(N6>=5,"Sí","No") -> Sí | Q6: =IF(P6="Sí",SUMPRODUCT(($P$4:$P$69="Sí")*($O$4:$O$69>O6))+1,"") -> 15 | R6: =IF(P6="Sí",SUMPRODUCT(($P$4:$P$69="Sí")*($O$4:$O$69<O6))+1,"") -> 7 | S6: =IF(P6<>"Sí","Resto",IF(Q6<=5,"5 mejores",IF(R6<=5,"5 peores","Resto"))) -> Resto | T6: =SUMIFS('DATOS LIMPIOS'!$M$5:$M$493,'DATOS LIMPIOS'!$E$5:$E$493,B6,'DATOS LIMPIOS'!$T$5:$T$493,"Agosto") -> 181.49775 | U6: =COUNTIFS('DATOS LIMPIOS'!$E$5:$E$493,B6,'DATOS LIMPIOS'!$T$5:$T$493,"Agosto") -> 6 | V6: =COUNTIFS('DATOS LIMPIOS'!$E$5:$E$493,B6,'DATOS LIMPIOS'!$T$5:$T$493,"<>Septiembre") -> 13 | W6: =IFERROR(AVERAGEIFS('DATOS LIMPIOS'!$M$5:$M$493,'DATOS LIMPIOS'!$E$5:$E$493,B6,'DATOS LIMPIOS'!$T$5:$T$493,"<>Septiembre"),"") -> 23.61129 | X6: =IF(V6>=5,"Sí","No") -> Sí | Y6: =IF(X6="Sí",SUMPRODUCT(($X$4:$X$69="Sí")*($W$4:$W$69>W6))+1,"") -> 16 | Z6: =IF(X6="Sí",SUMPRODUCT(($X$4:$X$69="Sí")*($W$4:$W$69<W6))+1,"") -> 10 | AA6: =IF(X6<>"Sí","Resto",IF(Y6<=5,"5 mejores",IF(Z6<=5,"5 peores","Resto"))) -> Resto | AB6: =SUMIFS('DATOS LIMPIOS'!$M$5:$M$493,'DATOS LIMPIOS'!$E$5:$E$493,B6,'DATOS LIMPIOS'!$T$5:$T$493,"Septiembre") -> 196.6617 | AC6: =COUNTIFS('DATOS LIMPIOS'!$E$5:$E$493,B6,'DATOS LIMPIOS'!$T$5:$T$493,"Septiembre") -> 9 | AD6: =COUNTIFS('DATOS LIMPIOS'!$E$5:$E$493,B6,'DATOS LIMPIOS'!$T$5:$T$493,"<>Octubre") -> 15 | AE6: =IFERROR(AVERAGEIFS('DATOS LIMPIOS'!$M$5:$M$493,'DATOS LIMPIOS'!$E$5:$E$493,B6,'DATOS LIMPIOS'!$T$5:$T$493,"<>Octubre"),"") -> 25.21063 | AF6: =IF(AD6>=5,"Sí","No") -> Sí | AG6: =IF(AF6="Sí",SUMPRODUCT(($AF$4:$AF$69="Sí")*($AE$4:$AE$69>AE6))+1,"") -> 13 | AH6: =IF(AF6="Sí",SUMPRODUCT(($AF$4:$AF$69="Sí")*($AE$4:$AE$69<AE6))+1,"") -> 13 | AI6: =IF(AF6<>"Sí","Resto",IF(AG6<=5,"5 mejores",IF(AH6<=5,"5 peores","Resto"))) -> Resto | AJ6: =SUMIFS('DATOS LIMPIOS'!$M$5:$M$493,'DATOS LIMPIOS'!$E$5:$E$493,B6,'DATOS LIMPIOS'!$T$5:$T$493,"Octubre") -> 125.44902 | AK6: =COUNTIFS('DATOS LIMPIOS'!$E$5:$E$493,B6,'DATOS LIMPIOS'!$T$5:$T$493,"Octubre") -> 7
